Workbook

Sheet PDI
A1: Nome | B1: Email | C1: Cpf | D1: Times | E1: Tags Privadas | F1: Tags Públicas | G1: Área | H1: Identificador | I1: status | J1: Líder | K1: Aprovado pelo líder? | L1: Total de Áreas de desenvolvimento | M1: Atualizado em (yyyy-mm-dd) | N1: Não iniciada | O1: Em progresso | P1: Finalizada | Q1: Engajamento | R1: PDI Finalizado? | S1: Progresso | T1: Macroáreas Desenvolvidas | U1: Macroáreas com Ações Pendentes
A2: Adelice Thomaz Soares Novak | B2: adelice@to.sebrae.com.br | D2: UAC-UNIDADE DE ARTICULAÇÃO E COMPETITIVIDADE | I2: Ativo | J2: Bruno Martins Vieira | K2: Sim | L2: 8 | M2: 2025-09-12 | N2: 0 | O2: 0 | P2: 8 | Q2: 4 | R2: =IF(OR(L2="",L2=0)," ",IF(P2=L2,"Terminou","Não terminou")) -> Terminou | S2: =IFERROR(P2/L2,0) -> 1 | T2: =IFERROR(VLOOKUP(TRIM($A2),'Ações Finalizadas'!$A:$O,15,FALSE),"") -> Comunicação, Ética, Integridade e Responsabilidade, Liderança e Gestão de Pessoas, Relacionamento, Planejamento, Foco e Resultados, Gestão de Equipes, Tecnologia, Dados e Transformação Digital | U2: =IFERROR(VLOOKUP(TRIM($A2),'Ações Não Finalizadas'!$A:$G,15,FALSE),"")
A3: Ademir Whitman Gomes Rego | B3: ademir@to.sebrae.com.br | D3: Regional Vale do Araguaia | I3: Ativo | J3: Renata Moura Alves Simas | K3: Sim | L3: 11 | M3: 2025-08-19 | N3: 11 | O3: 0 | P3: 0 | Q3: 2 | R3: =IF(OR(L3="",L3=0)," ",IF(P3=L3,"Terminou","Não terminou")) -> Não terminou | S3: =IFERROR(P3/L3,0) -> 0 | T3: =IFERROR(VLOOKUP(TRIM($A3),'Ações Finalizadas'!$A:$O,15,FALSE),"") | U3: =IFERROR(VLOOKUP(TRIM($A3),'Ações Não Finalizadas'!$A:$G,15,FALSE),"")
A4: Admary Monteiro Barbosa | B4: admary.monteiro@to.sebrae.com.br | D4: Regional Portal do Jalapao | I4: Ativo | J4: Millena Pereira Lima Rodrigues | K4: Sim | L4: 9 | M4: 2025-12-19 | N4: 0 | O4: 0 | P4: 9 | Q4: 4 | R4: =IF(OR(L4="",L4=0)," ",IF(P4=L4,"Terminou","Não terminou")) -> Terminou | S4: =IFERROR(P4/L4,0) -> 1 | T4: =IFERROR(VLOOKUP(TRIM($A4),'Ações Finalizadas'!$A:$O,15,FALSE),"") -> Atendimento e Relacionamento com o Cliente, Estratégia e Indicadores, Ética, Integridade e Responsabilidade, Gestão de Projetos e Processos, Liderança e Gestão de Pessoas, Planejamento, Foco e Resultados, Vendas, Negociação e Soluções Comerciais, Comunicação | U4: =IFERROR(VLOOKUP(TRIM($A4),'Ações Não Finalizadas'!$A:$G,15,FALSE),"")
A5: Adrielle Andrade | B5: adrielle.andrade@to.sebrae.com.br | D5: Regional Sul | I5: Ativo | J5: Paula dos Reis Coelho Alencar Sousa | K5: Sim | L5: 2 | M5: 2025-12-19 | N5: 0 | O5: 0 | P5: 2 | Q5: 3 | R5: =IF(OR(L5="",L5=0)," ",IF(P5=L5,"Terminou","Não terminou")) -> Terminou | S5: =IFERROR(P5/L5,0) -> 1 | T5: =IFERROR(VLOOKUP(TRIM($A5),'Ações Finalizadas'!$A:$O,15,FALSE),"") -> Desenvolvimento Programa Integração | U5: =IFERROR(VLOOKUP(TRIM($A5),'Ações Não Finalizadas'!$A:$G,15,FALSE),"")
A6: Aldeni Batista Torres | B6: aldeni.torres@to.sebrae.com.br | D6: Regional Médio Norte Colinas | I6: Ativo | J6: Aldeni Batista Torres | K6: Sim | L6: 7 | M6: 2025-12-18 | N6: 0 | O6: 1 | P6: 6 | Q6: 4 | R6: =IF(OR(L6="",L6=0)," ",IF(P6=L6,"Terminou","Não terminou")) -> Não terminou | S6: =(P6 + 0.5*O6) / L6 -> 0.92857143 | T6: =IFERROR(VLOOKUP(TRIM($A6),'Ações Finalizadas'!$A:$O,15,FALSE),"") -> Atendimento e Relacionamento com o Cliente, Inteligência Emocional e Autoconhecimento, Gestão de Projetos e Processos, Protagonismo, Autogestão e Tomada de Decisão, Gestão de Equipes | U6: =IFERROR(VLOOKUP(TRIM($A6),'Ações Não Finalizadas'!$A:$G,15,FALSE),"")
A7: Alencar Hubner Borelli | B7: alencar.borelli@to.sebrae.com.br | D7: UAS-UNIDADE DE ADMINISTRAÇÃO E SUPRIMENTOS | I7: Ativo | J7: Ana Paula Alves Santos | K7: Sim | L7: 2 | M7: 2025-12-09 | N7: 0 | O7: 0 | P7: 2 | Q7: 3 | R7: =IF(OR(L7="",L7=0)," ",IF(P7=L7,"Terminou","Não terminou")) -> Terminou | S7: =IFERROR(P7/L7,0) -> 1 | T7: =IFERROR(VLOOKUP(TRIM($A7),'Ações Finalizadas'!$A:$O,15,FALSE),"") -> Desenvolvimento de Ferramentas de Apoio na Execução, Ética, Integridade e Responsabilidade | U7: =IFERROR(VLOOKUP(TRIM($A7),'Ações Não Finalizadas'!$A:$G,15,FALSE),"")
A8: Alex Veras Dias | B8: alex.dias@to.sebrae.com.br | D8: URI-UNIDADE DE RELACIONAMENTO INSTITUCIONAL | I8: Ativo | J8: Gilzane Pereira Amaral | K8: Sim | L8: 9 | M8: 2025-12-19 | N8: 0 | O8: 0 | P8: 9 | Q8: 4 | R8: =IF(OR(L8="",L8=0)," ",IF(P8=L8,"Terminou","Não terminou")) -> Terminou | S8: =IFERROR(P8/L8,0) -> 1 | T8: =IFERROR(VLOOKUP(TRIM($A8),'Ações Finalizadas'!$A:$O,15,FALSE),"") -> Comunicação, Estratégia e Indicadores, Ética, Integridade e Responsabilidade, Finanças, Orçamento e Contabilidade Pública, Gestão de Tempo, Liderança e Gestão de Pessoas, Planejamento, Foco e Resultados, Políticas Públicas e Desenvolvimento Territorial | U8: =IFERROR(VLOOKUP(TRIM($A8),'Ações Não Finalizadas'!$A:$G,15,FALSE),"")
A9: Alice Sousa Santos Costa | B9: alice.costa@to.sebrae.com.br | D9: Regional Sul | I9: Ativo | J9: Paula dos Reis Coelho Alencar Sousa | K9: Sim | L9: 7 | M9: 2025-12-01 | N9: 0 | O9: 0 | P9: 7 | Q9: 4 | R9: =IF(OR(L9="",L9=0)," ",IF(P9=L9,"Terminou","Não terminou")) -> Terminou | S9: =IFERROR(P9/L9,0) -> 1 | T9: =IFERROR(VLOOKUP(TRIM($A9),'Ações Finalizadas'!$A:$O,15,FALSE),"") -> Atitude Inovadora com Visão de Futuro, Estratégia e Indicadores, Gestão do Conhecimento e Documentação Institucional, Inteligência Emocional e Autoconhecimento, Planejamento, Foco e Resultados, Vendas, Negociação e Soluções Comerciais, Comunicação | U9: =IFERROR(VLOOKUP(TRIM($A9),'Ações Não Finalizadas'!$A:$G,15,FALSE),"")
A10: Aline Almeida | B10: aline.almeida@to.sebrae.com.br | D10: Regional Médio Norte Colinas | I10: Ativo | J10: Aldeni Batista Torres | K10: Sim | L10: 2 | M10: 2025-12-15 | N10: 0 | O10: 0 | P10: 2 | Q10: 3 | R10: =IF(OR(L10="",L10=0)," ",IF(P10=L10,"Terminou","Não terminou")) -> Terminou | S10: =IFERROR(P10/L10,0) -> 1 | T10: =IFERROR(VLOOKUP(TRIM($A10),'Ações Finalizadas'!$A:$O,15,FALSE),"") -> Desenvolvimento Programa Integração | U10: =IFERROR(VLOOKUP(TRIM($A10),'Ações Não Finalizadas'!$A:$G,15,FALSE),"")
A11: Alorran de Freitas Barbosa | B11: alorran.barbosa@to.sebrae.com.br | D11: UTIC-UNIDADE DE TECNOLOGIA DA INFORM. E COMUNICAÇÃO DE DADOS | I11: Ativo | J11: Leonardo Campelo Leite Guedes | K11: Sim | L11: 8 | M11: 2025-12-19 | N11: 3 | O11: 0 | P11: 7 | Q11: 4 | R11: =IF(OR(L11="",L11=0)," ",IF(P11=L11,"Terminou","Não terminou")) -> Não terminou | S11: =IFERROR(P11/L11,0) -> 0.875 | T11: =IFERROR(VLOOKUP(TRIM($A11),'Ações Finalizadas'!$A:$O,15,FALSE),"") -> Competências Técnicas da Área, Ética, Integridade e Responsabilidade, Gestão de Tempo, Inteligência Emocional e Autoconhecimento, Planejamento, Foco e Resultados, Comunicação | U11: =IFERROR(VLOOKUP(TRIM($A11),'Ações Não Finalizadas'!$A:$G,15,FALSE),"")
A12: Amaggeldo Barbosa | B12: amaggeldo@to.sebrae.com.br | D12: Regional Metropolitana | I12: Ativo | J12: Amaggeldo Barbosa | K12: Sim | L12: 6 | M12: 2025-12-11 | N12: 0 | O12: 0 | P12: 6 | Q12: 4 | R12: =IF(OR(L12="",L12=0)," ",IF(P12=L12,"Terminou","Não terminou")) -> Terminou | S12: =IFERROR(P12/L12,0) -> 1 | T12: =IFERROR(VLOOKUP(TRIM($A12),'Ações Finalizadas'!$A:$O,15,FALSE),"") -> Ética, Integridade e Responsabilidade, Atitude Inovadora com Visão de Futuro, Estratégia e Indicadores, Tecnologia, Dados e Transformação Digital, Comunicação | U12: =IFERROR(VLOOKUP(TRIM($A12),'Ações Não Finalizadas'!$A:$G,15,FALSE),"")
A13: Amanda Soares Santos | B13: amanda.santos@to.sebrae.com.br | D13: UGOC-UNIDADE DE GESTÃO ORÇ. CONTABILIDADE E FINANÇAS | I13: Ativo | J13: Andreia Rodrigues Facundes | K13: Sim | L13: 11 | M13: 2025-12-19 | N13: 0 | O13: 0 | P13: 11 | Q13: 4 | R13: =IF(OR(L13="",L13=0)," ",IF(P13=L13,"Terminou","Não terminou")) -> Terminou | S13: =IFERROR(P13/L13,0) -> 1 | T13: =IFERROR(VLOOKUP(TRIM($A13),'Ações Finalizadas'!$A:$O,15,FALSE),"") -> Estratégia e Indicadores, Ética, Integridade e Responsabilidade, Gestão de Tempo, Gestão do Conhecimento e Documentação Institucional, Inovação, Criatividade e Visão Estratégica, Inteligência Emocional e Autoconhecimento, Planejamento, Foco e Resultados, Protagonismo, Autogestão e Tomada de Decisão, Comunicação | U13: =IFERROR(VLOOKUP(TRIM($A13),'Ações Não Finalizadas'!$A:$G,15,FALSE),"")
A14: Ana Cassia de Oliveira Costa | B14: ana.costa@to.sebrae.com.br | D14: UMC-UNIDADE DE MARKETING E COMUNICAÇÃO | I14: Ativo | J14: Nemias Gomes | K14: Sim | L14: 8 | M14: 2025-12-19 | N14: 0 | O14: 0 | P14: 8 | Q14: 4 | R14: =IF(OR(L14="",L14=0)," ",IF(P14=L14,"Terminou","Não terminou")) -> Terminou | S14: =IFERROR(P14/L14,0) -> 1 | T14: =IFERROR(VLOOKUP(TRIM($A14),'Ações Finalizadas'!$A:$O,15,FALSE),"") -> Atitude Inovadora com Visão de Futuro, Ética, Integridade e Responsabilidade, Gestão de Projetos e Processos, Gestão de Tempo, Planejamento, Foco e Resultados, Protagonismo, Autogestão e Tomada de Decisão, Comunicação | U14: =IFERROR(VLOOKUP(TRIM($A14),'Ações Não Finalizadas'!$A:$G,15,FALSE),"")
A15: Ana Estela Goetten | B15: ana.goetten@to.sebrae.com.br | D15: Regional Metropolitana | I15: Ativo | J15: Amaggeldo Barbosa | K15: Sim | L15: 3 | M15: 2025-12-03 | N15: 0 | O15: 0 | P15: 3 | Q15: 4 | R15: =IF(OR(L15="",L15=0)," ",IF(P15=L15,"Terminou","Não terminou")) -> Terminou | S15: =IFERROR(P15/L15,0) -> 1 | T15: =IFERROR(VLOOKUP(TRIM($A15),'Ações Finalizadas'!$A:$O,15,FALSE),"") -> Desenvolvimento Programa Integração | U15: =IFERROR(VLOOKUP(TRIM($A15),'Ações Não Finalizadas'!$A:$G,15,FALSE),"")
A16: Ana Flávia Mendes Borges | B16: ana.borges@to.sebrae.com.br | D16: UAC-UNIDADE DE ARTICULAÇÃO E COMPETITIVIDADE | I16: Ativo | J16: Bruno Martins Vieira | K16: Sim | L16: 5 | M16: 2025-09-23 | N16: 0 | O16: 0 | P16: 5 | Q16: 4 | R16: =IF(OR(L16="",L16=0)," ",IF(P16=L16,"Terminou","Não terminou")) -> Terminou | S16: =IFERROR(P16/L16,0) -> 1 | T16: =IFERROR(VLOOKUP(TRIM($A16),'Ações Finalizadas'!$A:$O,15,FALSE),"") -> Atitude Inovadora com Visão de Futuro, Ética, Integridade e Responsabilidade, Gestão de Tempo, Comunicação | U16: =IFERROR(VLOOKUP(TRIM($A16),'Ações Não Finalizadas'!$A:$G,15,FALSE),"")
A17: Ana Maria Leal Cunha de Freitas | B17: ana.freitas@to.sebrae.com.br | D17: Regional Médio Norte Colinas | I17: Ativo | J17: Aldeni Batista Torres | K17: Sim | L17: 13 | M17: 2025-12-17 | N17: 0 | O17: 0 | P17: 13 | Q17: 4 | R17: =IF(OR(L17="",L17=0)," ",IF(P17=L17,"Terminou","Não terminou")) -> Terminou | S17: =IFERROR(P17/L17,0) -> 1 | T17: =IFERROR(VLOOKUP(TRIM($A17),'Ações Finalizadas'!$A:$O,15,FALSE),"") -> Ética, Integridade e Responsabilidade, Atitude Inovadora com Visão de Futuro, Finanças, Orçamento e Contabilidade Pública, Gestão de Projetos e Processos, Gestão de Tempo, Protagonismo, Autogestão e Tomada de Decisão, Vendas, Negociação e Soluções Comerciais, Competências Técnicas da Área, Comunicação, Desenvolvimento Programa Integração | U17: =IFERROR(VLOOKUP(TRIM($A17),'Ações Não Finalizadas'!$A:$G,15,FALSE),"")
A18: Ana Paula Alves de Lima Rocha | B18: anapaula.lima@to.sebrae.com.br | D18: UTIC-UNIDADE DE TECNOLOGIA DA INFORM. E COMUNICAÇÃO DE DADOS | I18: Ativo | J18: Leonardo Campelo Leite Guedes | K18: Sim | L18: 1 | M18: 2025-12-03 | N18: 1 | O18: 0 | P18: 1 | Q18: 2 | R18: =IF(OR(L18="",L18=0)," ",IF(P18=L18,"Terminou","Não terminou")) -> Terminou | S18: =IFERROR(P18/L18,0) -> 1 | T18: =IFERROR(VLOOKUP(TRIM($A18),'Ações Finalizadas'!$A:$O,15,FALSE),"") -> Inteligência Emocional e Autoconhecimento | U18: =IFERROR(VLOOKUP(TRIM($A18),'Ações Não Finalizadas'!$A:$G,15,FALSE),"")
A19: Ana Paula Alves Santos | B19: paula.alves@to.sebrae.com.br | D19: UAS-UNIDADE DE ADMINISTRAÇÃO E SUPRIMENTOS | H19: ANA PAULA ALVES SANTOS | I19: Ativo | J19: Ana Paula Alves Santos | K19: Sim | L19: 4 | M19: 2025-12-11 | N19: 0 | O19: 0 | P19: 4 | Q19: 4 | R19: =IF(OR(L19="",L19=0)," ",IF(P19=L19,"Terminou","Não terminou")) -> Terminou | S19: =IFERROR(P19/L19,0) -> 1 | T19: =IFERROR(VLOOKUP(TRIM($A19),'Ações Finalizadas'!$A:$O,15,FALSE),"") -> Ética, Integridade e Responsabilidade, Gestão de Equipes, Inovação, Criatividade e Visão Estratégica, Inteligência Emocional e Autoconhecimento | U19: =IFERROR(VLOOKUP(TRIM($A19),'Ações Não Finalizadas'!$A:$G,15,FALSE),"")
A20: Ana Paula Carvalho Desconsi | B20: anapaula.desconsi@to.sebrae.com.br | D20: Regional Bico do Papagaio | I20: Ativo | J20: Edvaldo Pereira Lima Júnior | K20: Sim | L20: 3 | M20: 2025-12-19 | N20: 0 | O20: 0 | P20: 3 | Q20: 4 | R20: =IF(OR(L20="",L20=0)," ",IF(P20=L20,"Terminou","Não terminou")) -> Terminou | S20: =IFERROR(P20/L20,0) -> 1 | T20: =IFERROR(VLOOKUP(TRIM($A20),'Ações Finalizadas'!$A:$O,15,FALSE),"") -> Protagonismo, Autogestão e Tomada de Decisão, Desenvolvimento Programa Integração | U20: =IFERROR(VLOOKUP(TRIM($A20),'Ações Não Finalizadas'!$A:$G,15,FALSE),"")
A21: Ana Paula Cunha Soares | B21: paula.soares@to.sebrae.com.br | D21: UAS-UNIDADE DE ADMINISTRAÇÃO E SUPRIMENTOS | I21: Ativo | J21: Ana Paula Alves Santos | K21: Sim | L21: 10 | M21: 2025-12-04 | N21: 0 | O21: 0 | P21: 10 | Q21: 4 | R21: =IF(OR(L21="",L21=0)," ",IF(P21=L21,"Terminou","Não terminou")) -> Terminou | S21: =IFERROR(P21/L21,0) -> 1 | T21: =IFERROR(VLOOKUP(TRIM($A21),'Ações Finalizadas'!$A:$O,15,FALSE),"") -> Ética, Integridade e Responsabilidade, Atendimento e Relacionamento com o Cliente, Compras, Facilities e Gestão Contratual, Estratégia e Indicadores, Gestão de Tempo, Inteligência Emocional e Autoconhecimento, Planejamento, Foco e Resultados, Presença Executiva, Comunicação | U21: =IFERROR(VLOOKUP(TRIM($A21),'Ações Não Finalizadas'!$A:$G,15,FALSE),"")
A22: Andre Silva Gomes | B22: andre.gomes@to.sebrae.com.br | D22: Regional Portal do Jalapao | I22: Ativo | J22: Millena Pereira Lima Rodrigues | K22: Sim | L22: 11 | M22: 2025-12-19 | N22: 0 | O22: 0 | P22: 11 | Q22: 4 | R22: =IF(OR(L22="",L22=0)," ",IF(P22=L22,"Terminou","Não terminou")) -> Terminou | S22: =IFERROR(P22/L22,0) -> 1 | T22: =IFERROR(VLOOKUP(TRIM($A22),'Ações Finalizadas'!$A:$O,15,FALSE),"") -> Estratégia e Indicadores, Ética, Integridade e Responsabilidade, Gestão do Conhecimento e Documentação Institucional, Inteligência Emocional e Autoconhecimento, Liderança e Gestão de Pessoas, Planejamento, Foco e Resultados, Vendas, Negociação e Soluções Comerciais, Comunicação | U22: =IFERROR(VLOOKUP(TRIM($A22),'Ações Não Finalizadas'!$A:$G,15,FALSE),"")
A23: Andreia Rodrigues Facundes | B23: andreia.facundes@to.sebrae.com.br | D23: UGOC-UNIDADE DE GESTÃO ORÇ. CONTABILIDADE E FINANÇAS | I23: Ativo | J23: Andreia Rodrigues Facundes | K23: Sim | L23: 4 | M23: 2025-12-09 | N23: 4 | O23: 0 | P23: 0 | Q23: 2 | R23: =IF(OR(L23="",L23=0)," ",IF(P23=L23,"Terminou","Não terminou")) -> Não terminou | S23: =IFERROR(P23/L23,0) -> 0 | T23: =IFERROR(VLOOKUP(TRIM($A23),'Ações Finalizadas'!$A:$O,15,FALSE),"") | U23: =IFERROR(VLOOKUP(TRIM($A23),'Ações Não Finalizadas'!$A:$G,15,FALSE),"")
A24: Andressa Ibiapina | B24: andressa.ibiapina@to.sebrae.com.br | D24: Regional Norte | I24: Ativo | J24: Marcus Vinicius Vieira Queiroz | K24: Sim | L24: 10 | M24: 2025-11-24 | N24: 0 | O24: 0 | P24: 10 | Q24: 4 | R24: =IF(OR(L24="",L24=0)," ",IF(P24=L24,"Terminou","Não terminou")) -> Terminou | S24: =IFERROR(P24/L24,0) -> 1 | T24: =IFERROR(VLOOKUP(TRIM($A24),'Ações Finalizadas'!$A:$O,15,FALSE),"") -> Atendimento e Relacionamento com o Cliente, Gestão do Conhecimento e Documentação Institucional, Liderança e Gestão de Pessoas, Planejamento, Foco e Resultados, Vendas, Negociação e Soluções Comerciais, Comunicação | U24: =IFERROR(VLOOKUP(TRIM($A24),'Ações Não Finalizadas'!$A:$G,15,FALSE),"")
A25: Anteia Tavares | B25: anteia.tavares@to.sebrae.com.br | D25: UGOC-UNIDADE DE GESTÃO ORÇ. CONTABILIDADE E FINANÇAS | I25: Ativo | J25: Andreia Rodrigues Facundes | K25: Sim | L25: 2 | M25: 2025-09-09 | N25: 0 | O25: 0 | P25: 2 | Q25: 3 | R25: =IF(OR(L25="",L25=0)," ",IF(P25=L25,"Terminou","Não terminou")) -> Terminou | S25: =IFERROR(P25/L25,0) -> 1 | T25: =IFERROR(VLOOKUP(TRIM($A25),'Ações Finalizadas'!$A:$O,15,FALSE),"") -> Desenvolvimento Programa Integração | U25: =IFERROR(VLOOKUP(TRIM($A25),'Ações Não Finalizadas'!$A:$G,15,FALSE),"")
A26: Antonia Gelma Pereira da Silva Carvalho | B26: antonia.carvalho@to.sebrae.com.br | D26: Regional Metropolitana | I26: Ativo | J26: Amaggeldo Barbosa | K26: Sim | L26: 11 | M26: 2025-12-19 | N26: 3 | O26: 1 | P26: 7 | Q26: 4 | R26: =IF(OR(L26="",L26=0)," ",IF(P26=L26,"Terminou","Não terminou")) -> Não terminou | S26: =(P26 + O26*(1/3)) / L26 -> 0.66666667 | T26: =IFERROR(VLOOKUP(TRIM($A26),'Ações Finalizadas'!$A:$O,15,FALSE),"") -> Ética, Integridade e Responsabilidade, Políticas Públicas e Desenvolvimento Territorial, Vendas, Negociação e Soluções Comerciais, Comunicação | U26: =IFERROR(VLOOKUP(TRIM($A26),'Ações Não Finalizadas'!$A:$G,15,FALSE),"")
A27: Antonio Louça Curcino | B27: antonio.curcino@to.sebrae.com.br | D27: Regional Serras Gerais | I27: Ativo | J27: Antonio Louça Curcino | K27: Sim | L27: 7 | M27: 2025-12-12 | N27: 0 | O27: 0 | P27: 7 | Q27: 4 | R27: =IF(OR(L27="",L27=0)," ",IF(P27=L27,"Terminou","Não terminou")) -> Terminou | S27: =IFERROR(P27/L27,0) -> 1 | T27: =IFERROR(VLOOKUP(TRIM($A27),'Ações Finalizadas'!$A:$O,15,FALSE),"") -> Ética, Integridade e Responsabilidade, Gestão do Conhecimento e Documentação Institucional, Liderança e Gestão de Pessoas, Vendas, Negociação e Soluções Comerciais, Comunicação | U27: =IFERROR(VLOOKUP(TRIM($A27),'Ações Não Finalizadas'!$A:$G,15,FALSE),"")
A28: Antonio Luis Ferreira dos Anjos Filho | B28: antonio.filho@to.sebrae.com.br | D28: URC - UNIDADE DE RELACIONAMENTO COM O CLIENTE | I28: Ativo | J28: Emerson Montenegro Lima | K28: Sim | L28: 10 | M28: 2025-12-09 | N28: 0 | O28: 0 | P28: 10 | Q28: 4 | R28: =IF(OR(L28="",L28=0)," ",IF(P28=L28,"Terminou","Não terminou")) -> Terminou | S28: =IFERROR(P28/L28,0) -> 1 | T28: =IFERROR(VLOOKUP(TRIM($A28),'Ações Finalizadas'!$A:$O,15,FALSE),"") -> Atendimento e Relacionamento com o Cliente, Conhecimentos Práticos e Acadêmicos em Marketing, Ética, Integridade e Responsabilidade, Vendas, Negociação e Soluções Comerciais | U28: =IFERROR(VLOOKUP(TRIM($A28),'Ações Não Finalizadas'!$A:$G,15,FALSE),"")
A29: Antonio Neto dos Santos | B29: antonio.santos@to.sebrae.com.br | D29: UGE-UNIDADE DE GESTÃO ESTRATÉGICA E INTEGRIDADE | I29: Ativo | J29: Pedro Junior da Rocha Silva | K29: Sim | L29: 3 | M29: 2025-12-03 | N29: 3 | O29: 0 | P29: 0 | Q29: 2 | R29: =IF(OR(L29="",L29=0)," ",IF(P29=L29,"Terminou","Não terminou")) -> Não terminou | S29: =IFERROR(P29/L29,0) -> 0 | T29: =IFERROR(VLOOKUP(TRIM($A29),'Ações Finalizadas'!$A:$O,15,FALSE),"") | U29: =IFERROR(VLOOKUP(TRIM($A29),'Ações Não Finalizadas'!$A:$G,15,FALSE),"")
A30: Barbara de Moura Nunes Rezende | B30: barbara.nunes@to.sebrae.com.br | D30: URC - UNIDADE DE RELACIONAMENTO COM O CLIENTE | I30: Ativo | J30: Emerson Montenegro Lima | K30: Sim | L30: 2 | M30: 2025-11-19 | N30: 0 | O30: 0 | P30: 2 | Q30: 3 | R30: =IF(OR(L30="",L30=0)," ",IF(P30=L30,"Terminou","Não terminou")) -> Terminou | S30: =IFERROR(P30/L30,0) -> 1 | T30: =IFERROR(VLOOKUP(TRIM($A30),'Ações Finalizadas'!$A:$O,15,FALSE),"") -> Conhecimentos Práticos e Acadêmicos em Marketing | U30: =IFERROR(VLOOKUP(TRIM($A30),'Ações Não Finalizadas'!$A:$G,15,FALSE),"")
A31: Bruno de Jesus Rodrigues | B31: bruno.rodrigues@to.sebrae.com.br | D31: Regional Serras Gerais | I31: Ativo | J31: Antonio Louça Curcino | K31: Sim | L31: 7 | M31: 2025-12-16 | N31: 0 | O31: 0 | P31: 7 | Q31: 4 | R31: =IF(OR(L31="",L31=0)," ",IF(P31=L31,"Terminou","Não terminou")) -> Terminou | S31: =IFERROR(P31/L31,0) -> 1 | T31: =IFERROR(VLOOKUP(TRIM($A31),'Ações Finalizadas'!$A:$O,15,FALSE),"") -> Atitude Inovadora com Visão de Futuro, Gestão de Projetos e Processos, Inteligência Emocional e Autoconhecimento, Planejamento, Foco e Resultados, Presença Executiva, Estratégia e Indicadores, Comunicação | U31: =IFERROR(VLOOKUP(TRIM($A31),'Ações Não Finalizadas'!$A:$G,15,FALSE),"")
A32: Bruno Henrique Vila Verde | B32: bruno.vilaverde@to.sebrae.com.br | D32: UGE-UNIDADE DE GESTÃO ESTRATÉGICA E INTEGRIDADE | I32: Ativo | J32: Pedro Junior da Rocha Silva | K32: Sim | L32: 11 | M32: 2025-12-16 | N32: 0 | O32: 0 | P32: 11 | Q32: 4 | R32: =IF(OR(L32="",L32=0)," ",IF(P32=L32,"Terminou","Não terminou")) -> Terminou | S32: =IFERROR(P32/L32,0) -> 1 | T32: =IFERROR(VLOOKUP(TRIM($A32),'Ações Finalizadas'!$A:$O,15,FALSE),"") -> Atitude Inovadora com Visão de Futuro, Estratégia e Indicadores, Ética, Integridade e Responsabilidade, Gestão de Tempo, Inteligência Emocional e Autoconhecimento, Protagonismo, Autogestão e Tomada de Decisão, Resolução de Problemas, Comunicação | U32: =IFERROR(VLOOKUP(TRIM($A32),'Ações Não Finalizadas'!$A:$G,15,FALSE),"")
A33: Bruno Martins Vieira | B33: bruno.vieira@to.sebrae.com.br | D33: UAC-UNIDADE DE ARTICULAÇÃO E COMPETITIVIDADE | I33: Ativo | J33: Bruno Martins Vieira | K33: Sim | L33: 5 | M33: 2025-12-09 | N33: 0 | O33: 0 | P33: 5 | Q33: 4 | R33: =IF(OR(L33="",L33=0)," ",IF(P33=L33,"Terminou","Não terminou")) -> Terminou | S33: =IFERROR(P33/L33,0) -> 1 | T33: =IFERROR(VLOOKUP(TRIM($A33),'Ações Finalizadas'!$A:$O,15,FALSE),"") -> Atitude Inovadora com Visão de Futuro, Ética, Integridade e Responsabilidade, Gestão de Tempo, Tecnologia, Dados e Transformação Digital, Comunicação | U33: =IFERROR(VLOOKUP(TRIM($A33),'Ações Não Finalizadas'!$A:$G,15,FALSE),"")
A34: Carlucia Saraiva de Brito | B34: carlucia.brito@to.sebrae.com.br | D34: Regional Portal do Jalapao | I34: Ativo | J34: Millena Pereira Lima Rodrigues | K34: Sim | L34: 14 | M34: 2025-11-23 | N34: 0 | O34: 0 | P34: 14 | Q34: 4 | R34: =IF(OR(L34="",L34=0)," ",IF(P34=L34,"Terminou","Não terminou")) -> Terminou | S34: =IFERROR(P34/L34,0) -> 1 | T34: =IFERROR(VLOOKUP(TRIM($A34),'Ações Finalizadas'!$A:$O,15,FALSE),"") -> Ética, Integridade e Responsabilidade, Atendimento e Relacionamento com o Cliente, Estratégia e Indicadores, Gestão de Projetos e Processos, Gestão do Conhecimento e Documentação Institucional, Inteligência Emocional e Autoconhecimento, Liderança e Gestão de Pessoas, Planejamento, Foco e Resultados, Vendas, Negociação e Soluções Comerciais, Comunicação | U34: =IFERROR(VLOOKUP(TRIM($A34),'Ações Não Finalizadas'!$A:$G,15,FALSE),"")
A35: Celina Soares | B35: celina@to.sebrae.com.br | D35: UAC-UNIDADE DE ARTICULAÇÃO E COMPETITIVIDADE | I35: Ativo | J35: Bruno Martins Vieira | K35: Sim | L35: 2 | M35: 2025-10-06 | N35: 0 | O35: 0 | P35: 2 | Q35: 3 | R35: =IF(OR(L35="",L35=0)," ",IF(P35=L35,"Terminou","Não terminou")) -> Terminou | S35: =IFERROR(P35/L35,0) -> 1 | T35: =IFERROR(VLOOKUP(TRIM($A35),'Ações Finalizadas'!$A:$O,15,FALSE),"") -> Gestão de Projetos e Processos, Gestão de Tempo | U35: =IFERROR(VLOOKUP(TRIM($A35),'Ações Não Finalizadas'!$A:$G,15,FALSE),"")
A36: Cesar Augusto de Sa Moreira | B36: cesar.moreira@to.sebrae.com.br | D36: Regional Vale do Araguaia | I36: Ativo | J36: Renata Moura Alves Simas | K36: Sim | L36: 9 | M36: 2025-12-26 | N36: 1 | O36: 0 | P36: 8 | Q36: 4 | R36: =IF(OR(L36="",L36=0)," ",IF(P36=L36,"Terminou","Não terminou")) -> Não terminou | S36: =IFERROR(P36/L36,0) -> 0.88888889 | T36: =IFERROR(VLOOKUP(TRIM($A36),'Ações Finalizadas'!$A:$O,15,FALSE),"") -> Atendimento e Relacionamento com o Cliente, Compras, Facilities e Gestão Contratual, Ética, Integridade e Responsabilidade, Gestão de Projetos e Processos, Inteligência Emocional e Autoconhecimento, Tecnologia, Dados e Transformação Digital, Vendas, Negociação e Soluções Comerciais, Comunicação | U36: =IFERROR(VLOOKUP(TRIM($A36),'Ações Não Finalizadas'!$A:$G,15,FALSE),"")
A37: Clarice da Rosa Correa Soares | B37: clarice@to.sebrae.com.br | D37: Regional Metropolitana | I37: Ativo | J37: Amaggeldo Barbosa | K37: Sim | L37: 5 | M37: 2025-10-08 | N37: 0 | O37: 0 | P37: 5 | Q37: 4 | R37: =IF(OR(L37="",L37=0)," ",IF(P37=L37,"Terminou","Não terminou")) -> Terminou | S37: =IFERROR(P37/L37,0) -> 1 | T37: =IFERROR(VLOOKUP(TRIM($A37),'Ações Finalizadas'!$A:$O,15,FALSE),"") -> Ética, Integridade e Responsabilidade, Vendas, Negociação e Soluções Comerciais | U37: =IFERROR(VLOOKUP(TRIM($A37),'Ações Não Finalizadas'!$A:$G,15,FALSE),"")
A38: Claudete Pinto Carmo Sousa | B38: claudete.carmo@to.sebrae.com.br | D38: Regional Vale do Araguaia | I38: Ativo | J38: Renata Moura Alves Simas | K38: Sim | L38: 5 | M38: 2025-08-27 | N38: 5 | O38: 0 | P38: 0 | Q38: 2 | R38: =IF(OR(L38="",L38=0)," ",IF(P38=L38,"Terminou","Não terminou")) -> Não terminou | S38: =IFERROR(P38/L38,0) -> 0 | T38: =IFERROR(VLOOKUP(TRIM($A38),'Ações Finalizadas'!$A:$O,15,FALSE),"") | U38: =IFERROR(VLOOKUP(TRIM($A38),'Ações Não Finalizadas'!$A:$G,15,FALSE),"")
A39: Claudia Narciso Sakai | B39: claudia.sakai@to.sebrae.com.br | D39: UAC-UNIDADE DE ARTICULAÇÃO E COMPETITIVIDADE | I39: Ativo | J39: Bruno Martins Vieira | K39: Sim | L39: 5 | M39: 2025-08-28 | N39: 0 | O39: 0 | P39: 5 | Q39: 4 | R39: =IF(OR(L39="",L39=0)," ",IF(P39=L39,"Terminou","Não terminou")) -> Terminou | S39: =IFERROR(P39/L39,0) -> 1 | T39: =IFERROR(VLOOKUP(TRIM($A39),'Ações Finalizadas'!$A:$O,15,FALSE),"") -> Atitude Inovadora com Visão de Futuro, Ética, Integridade e Responsabilidade, Planejamento, Foco e Resultados, Presença Executiva, Protagonismo, Autogestão e Tomada de Decisão | U39: =IFERROR(VLOOKUP(TRIM($A39),'Ações Não Finalizadas'!$A:$G,15,FALSE),"")
A40: Cristyane Fonseca Cardoso | B40: cristyane.cardoso@to.sebrae.com.br | D40: Regional Serras Gerais | I40: Ativo | J40: Antonio Louça Curcino | K40: Sim | L40: 6 | M40: 2025-08-27 | N40: 0 | O40: 2 | P40: 4 | Q40: 4 | R40: =IF(OR(L40="",L40=0)," ",IF(P40=L40,"Terminou","Não terminou")) -> Não terminou | S40: =(P40 + O40*0.65) / L40 -> 0.88333333 | T40: =IFERROR(VLOOKUP(TRIM($A40),'Ações Finalizadas'!$A:$O,15,FALSE),"") -> Ética, Integridade e Responsabilidade, Gestão do Conhecimento e Documentação Institucional, Inteligência Emocional e Autoconhecimento, Comunicação, Desenvolvimento Programa Integração | U40: =IFERROR(VLOOKUP(TRIM($A40),'Ações Não Finalizadas'!$A:$G,15,FALSE),"")
A41: Cynthia Nunes Alves Franca | B41: cynthia.franca@to.sebrae.com.br | D41: URI-UNIDADE DE RELACIONAMENTO INSTITUCIONAL | I41: Ativo | J41: Gilzane Pereira Amaral | K41: Sim | L41: 8 | M41: 2025-12-19 | N41: 0 | O41: 0 | P41: 8 | Q41: 4 | R41: =IF(OR(L41="",L41=0)," ",IF(P41=L41,"Terminou","Não terminou")) -> Terminou | S41: =IFERROR(P41/L41,0) -> 1 | T41: =IFERROR(VLOOKUP(TRIM($A41),'Ações Finalizadas'!$A:$O,15,FALSE),"") -> Planejamento, Foco e Resultados, Gestão do Conhecimento e Documentação Institucional, Inteligência Emocional e Autoconhecimento, Protagonismo, Autogestão e Tomada de Decisão, Comunicação, Desenvolvimento Programa Integração | U41: =IFERROR(VLOOKUP(TRIM($A41),'Ações Não Finalizadas'!$A:$G,15,FALSE),"")
A42: Daniel Caio Lemos Penno | B42: daniel.penno@to.sebrae.com.br | D42: UTIC-UNIDADE DE TECNOLOGIA DA INFORM. E COMUNICAÇÃO DE DADOS | I42: Ativo | J42: Leonardo Campelo Leite Guedes | K42: Sim | L42: 1 | M42: 2025-12-03 | N42: 0 | O42: 0 | P42: 1 | Q42: 2 | R42: =IF(OR(L42="",L42=0)," ",IF(P42=L42,"Terminou","Não terminou")) -> Terminou | S42: =IFERROR(P42/L42,0) -> 1 | T42: =IFERROR(VLOOKUP(TRIM($A42),'Ações Finalizadas'!$A:$O,15,FALSE),"") -> Ética, Integridade e Responsabilidade | U42: =IFERROR(VLOOKUP(TRIM($A42),'Ações Não Finalizadas'!$A:$G,15,FALSE),"")
A43: Daniel Nunes de Carvalho | B43: daniel.carvalho@to.sebrae.com.br | D43: CDE-ASSESSORIA | I43: Ativo | J43: Jackeline de Souza Lima | K43: Sim | L43: 7 | M43: 2025-11-09 | N43: 0 | O43: 0 | P43: 7 | Q43: 4 | R43: =IF(OR(L43="",L43=0)," ",IF(P43=L43,"Terminou","Não terminou")) -> Terminou | S43: =IFERROR(P43/L43,0) -> 1 | T43: =IFERROR(VLOOKUP(TRIM($A43),'Ações Finalizadas'!$A:$O,15,FALSE),"") -> Atitude Inovadora com Visão de Futuro, Ética, Integridade e Responsabilidade, Inteligência Emocional e Autoconhecimento, Planejamento, Foco e Resultados, Comunicação | U43: =IFERROR(VLOOKUP(TRIM($A43),'Ações Não Finalizadas'!$A:$G,15,FALSE),"")
A44: Deilane Rodrigues Vieira | B44: deilane.vieira@to.sebrae.com.br | D44: Regional Norte | I44: Ativo | J44: Marcus Vinicius Vieira Queiroz | K44: Sim | L44: 12 | M44: 2025-12-11 | N44: 0 | O44: 0 | P44: 12 | Q44: 4 | R44: =IF(OR(L44="",L44=0)," ",IF(P44=L44,"Terminou","Não terminou")) -> Terminou | S44: =IFERROR(P44/L44,0) -> 1 | T44: =IFERROR(VLOOKUP(TRIM($A44),'Ações Finalizadas'!$A:$O,15,FALSE),"") -> Ética, Integridade e Responsabilidade, Atitude Inovadora com Visão de Futuro, Gestão do Conhecimento e Documentação Institucional, Inteligência Emocional e Autoconhecimento, Liderança e Gestão de Pessoas, Planejamento, Foco e Resultados, Vendas, Negociação e Soluções Comerciais, Comunicação | U44: =IFERROR(VLOOKUP(TRIM($A44),'Ações Não Finalizadas'!$A:$G,15,FALSE),"")
A45: Denise da Silva Nunes | B45: denise.nunes@to.sebrae.com.br | D45: UGOC-UNIDADE DE GESTÃO ORÇ. CONTABILIDADE E FINANÇAS | I45: Ativo | J45: Andreia Rodrigues Facundes | K45: Sim | L45: 7 | M45: 2025-12-15 | N45: 0 | O45: 0 | P45: 7 | Q45: 4 | R45: =IF(OR(L45="",L45=0)," ",IF(P45=L45,"Terminou","Não terminou")) -> Terminou | S45: =IFERROR(P45/L45,0) -> 1 | T45: =IFERROR(VLOOKUP(TRIM($A45),'Ações Finalizadas'!$A:$O,15,FALSE),"") -> Ética, Integridade e Responsabilidade, Liderança e Gestão de Pessoas, Planejamento, Foco e Resultados, Protagonismo, Autogestão e Tomada de Decisão, Tecnologia, Dados e Transformação Digital, Comunicação | U45: =IFERROR(VLOOKUP(TRIM($A45),'Ações Não Finalizadas'!$A:$G,15,FALSE),"")
A46: Diogo Santos Barreto | B46: diogo.barreto@to.sebrae.com.br | D46: UAS-UNIDADE DE ADMINISTRAÇÃO E SUPRIMENTOS | I46: Ativo | J46: Ana Paula Alves Santos | K46: Sim | L46: 2 | M46: 2025-11-06 | N46: 0 | O46: 0 | P46: 2 | Q46: 3 | R46: =IF(OR(L46="",L46=0)," ",IF(P46=L46,"Terminou","Não terminou")) -> Terminou | S46: =IFERROR(P46/L46,0) -> 1 | T46: =IFERROR(VLOOKUP(TRIM($A46),'Ações Finalizadas'!$A:$O,15,FALSE),"") -> Desenvolvimento Programa Integração | U46: =IFERROR(VLOOKUP(TRIM($A46),'Ações Não Finalizadas'!$A:$G,15,FALSE),"")
A47: Djales dos Santos Oliveira | B47: djales.santos@to.sebrae.com.br | D47: Regional Sul | I47: Ativo | J47: Paula dos Reis Coelho Alencar Sousa | K47: Sim | L47: 12 | M47: 2025-12-02 | N47: 0 | O47: 0 | P47: 12 | Q47: 4 | R47: =IF(OR(L47="",L47=0)," ",IF(P47=L47,"Terminou","Não terminou")) -> Terminou | S47: =IFERROR(P47/L47,0) -> 1 | T47: =IFERROR(VLOOKUP(TRIM($A47),'Ações Finalizadas'!$A:$O,15,FALSE),"") -> Ética, Integridade e Responsabilidade, Atitude Inovadora com Visão de Futuro, Estratégia e Indicadores, Gestão do Conhecimento e Documentação Institucional, Inteligência Emocional e Autoconhecimento, Liderança e Gestão de Pessoas, Planejamento, Foco e Resultados, Vendas, Negociação e Soluções Comerciais | U47: =IFERROR(VLOOKUP(TRIM($A47),'Ações Não Finalizadas'!$A:$G,15,FALSE),"")
A48: Dorival Goncalves de Sousa Junior | B48: dorival.junior@to.sebrae.com.br | D48: UMC-UNIDADE DE MARKETING E COMUNICAÇÃO | I48: Ativo | J48: Nemias Gomes | K48: Sim | L48: 16 | M48: 2025-12-16 | N48: 0 | O48: 0 | P48: 16 | Q48: 4 | R48: =IF(OR(L48="",L48=0)," ",IF(P48=L48,"Terminou","Não terminou")) -> Terminou | S48: =IFERROR(P48/L48,0) -> 1 | T48: =IFERROR(VLOOKUP(TRIM($A48),'Ações Finalizadas'!$A:$O,15,FALSE),"") -> Atitude Inovadora com Visão de Futuro, Ética, Integridade e Responsabilidade, Gestão de Tempo, Inteligência Emocional e Autoconhecimento, Planejamento, Foco e Resultados, Presença Executiva, Comunicação, Conhecimentos Práticos e Acadêmicos em Marketing | U48: =IFERROR(VLOOKUP(TRIM($A48),'Ações Não Finalizadas'!$A:$G,15,FALSE),"")
A49: Durval Rego Nunes | B49: durval.nunes@to.sebrae.com.br | D49: SUPERINTENDENCIA | I49: Ativo | J49: Rerison Antonio Castro Leite | K49: Sim | L49: 8 | M49: 2025-12-03 | N49: 0 | O49: 0 | P49: 8 | Q49: 4 | R49: =IF(OR(L49="",L49=0)," ",IF(P49=L49,"Terminou","Não terminou")) -> Terminou | S49: =IFERROR(P49/L49,0) -> 1 | T49: =IFERROR(VLOOKUP(TRIM($A49),'Ações Finalizadas'!$A:$O,15,FALSE),"") -> Atendimento e Relacionamento com o Cliente, Atitude Inovadora com Visão de Futuro, Ética, Integridade e Responsabilidade, Inteligência Emocional e Autoconhecimento, Planejamento, Foco e Resultados, Presença Executiva, Tecnologia, Dados e Transformação Digital | U49: =IFERROR(VLOOKUP(TRIM($A49),'Ações Não Finalizadas'!$A:$G,15,FALSE),"")
A50: Edglei Dias Rodrigues | B50: edglei.rodrigues@to.sebrae.com.br | D50: UAC-UNIDADE DE ARTICULAÇÃO E COMPETITIVIDADE | I50: Ativo | J50: Bruno Martins Vieira | K50: Sim | L50: 10 | M50: 2025-09-08 | N50: 0 | O50: 0 | P50: 10 | Q50: 4 | R50: =IF(OR(L50="",L50=0)," ",IF(P50=L50,"Terminou","Não terminou")) -> Terminou | S50: =IFERROR(P50/L50,0) -> 1 | T50: =IFERROR(VLOOKUP(TRIM($A50),'Ações Finalizadas'!$A:$O,15,FALSE),"") -> Planejamento, Foco e Resultados, Atitude Inovadora com Visão de Futuro, Ética, Integridade e Responsabilidade, Gestão de Tempo, Inteligência Emocional e Autoconhecimento, Presença Executiva, Protagonismo, Autogestão e Tomada de Decisão, Comunicação | U50: =IFERROR(VLOOKUP(TRIM($A50),'Ações Não Finalizadas'!$A:$G,15,FALSE),"")
A51: Edvaldo Pereira Lima Júnior | B51: edvaldopljr86@gmail.com | D51: Regional Bico do Papagaio | I51: Ativo | J51: Edvaldo Pereira Lima Júnior | K51: Sim | L51: 7 | M51: 2025-12-10 | N51: 0 | O51: 1 | P51: 6 | Q51: 4 | R51: =IF(OR(L51="",L51=0)," ",IF(P51=L51,"Terminou","Não terminou")) -> Não terminou | S51: =(P51 + 0.5*O51) / L51 -> 0.92857143 | T51: =IFERROR(VLOOKUP(TRIM($A51),'Ações Finalizadas'!$A:$O,15,FALSE),"") -> Atendimento e Relacionamento com o Cliente, Atitude Inovadora com Visão de Futuro, Estratégia e Indicadores, Gestão do Conhecimento e Documentação Institucional, Liderança e Gestão de Pessoas, Relacionamento, Desenvolvimento Programa Integração | U51: =IFERROR(VLOOKUP(TRIM($A51),'Ações Não Finalizadas'!$A:$G,15,FALSE),"")
A52: Elienilson Goncalves da Conceicao | B52: elienilson.conceicao@to.sebrae.com.br | D52: UMC-UNIDADE DE MARKETING E COMUNICAÇÃO | I52: Ativo | J52: Nemias Gomes | K52: Sim | L52: 6 | M52: 2025-12-16 | N52: 0 | O52: 0 | P52: 6 | Q52: 4 | R52: =IF(OR(L52="",L52=0)," ",IF(P52=L52,"Terminou","Não terminou")) -> Terminou | S52: =IFERROR(P52/L52,0) -> 1 | T52: =IFERROR(VLOOKUP(TRIM($A52),'Ações Finalizadas'!$A:$O,15,FALSE),"") -> Planejamento, Foco e Resultados, Ética, Integridade e Responsabilidade, Gestão de Projetos e Processos, Inteligência Emocional e Autoconhecimento, Estratégia e Indicadores | U52: =IFERROR(VLOOKUP(TRIM($A52),'Ações Não Finalizadas'!$A:$G,15,FALSE),"")
A53: Eligeneth Resplandes Pimentel Gomes | B53: eligeneth@to.sebrae.com.br | D53: Regional Metropolitana | I53: Ativo | J53: Amaggeldo Barbosa | K53: Sim | L53: 10 | M53: 2025-12-19 | N53: 0 | O53: 0 | P53: 10 | Q53: 4 | R53: =IF(OR(L53="",L53=0)," ",IF(P53=L53,"Terminou","Não terminou")) -> Terminou | S53: =IFERROR(P53/L53,0) -> 1 | T53: =IFERROR(VLOOKUP(TRIM($A53),'Ações Finalizadas'!$A:$O,15,FALSE),"") -> Ética, Integridade e Responsabilidade, Inteligência Emocional e Autoconhecimento, Planejamento, Foco e Resultados, Vendas, Negociação e Soluções Comerciais, Comunicação | U53: =IFERROR(VLOOKUP(TRIM($A53),'Ações Não Finalizadas'!$A:$G,15,FALSE),"")
A54: Elisabete Lacerda Eustaquio | B54: elizabete@to.sebrae.com.br | D54: UGOC-UNIDADE DE GESTÃO ORÇ. CONTABILIDADE E FINANÇAS | I54: Ativo | J54: Andreia Rodrigues Facundes | K54: Sim | L54: 4 | M54: 2025-12-26 | N54: 0 | O54: 0 | P54: 4 | Q54: 4 | R54: =IF(OR(L54="",L54=0)," ",IF(P54=L54,"Terminou","Não terminou")) -> Terminou | S54: =IFERROR(P54/L54,0) -> 1 | T54: =IFERROR(VLOOKUP(TRIM($A54),'Ações Finalizadas'!$A:$O,15,FALSE),"") -> Ética, Integridade e Responsabilidade, Inteligência Emocional e Autoconhecimento, Protagonismo, Autogestão e Tomada de Decisão, Comunicação | U54: =IFERROR(VLOOKUP(TRIM($A54),'Ações Não Finalizadas'!$A:$G,15,FALSE),"")
A55: Elisangela Tavares Alves Varanda | B55: elisangela.varanda@to.sebrae.com.br | C55: 94111820115 | D55: UGP-UNIDADE DE GESTÃO DE PESSOAS | G55: Pessoas | H55: elisangela.varanda@to.sebrae.com.br | I55: Ativo | J55: Vera Lucia Teodoro Braga | K55: Sim | L55: 10 | M55: 2025-12-19 | N55: 0 | O55: 0 | P55: 10 | Q55: 4 | R55: =IF(OR(L55="",L55=0)," ",IF(P55=L55,"Terminou","Não terminou")) -> Terminou | S55: =IFERROR(P55/L55,0) -> 1 | T55: =IFERROR(VLOOKUP(TRIM($A55),'Ações Finalizadas'!$A:$O,15,FALSE),"") -> Desenvolvimento Integração, Gestão de Equipes, Gestão de Tempo, Inovação, Criatividade e Visão Estratégica, Inteligência Emocional e Autoconhecimento, Presença Executiva, Protagonismo, Autogestão e Tomada de Decisão, Estratégia e Indicadores, Comunicação | U55: =IFERROR(VLOOKUP(TRIM($A55),'Ações Não Finalizadas'!$A:$G,15,FALSE),"")
A56: Eliwania dos Santos Silva | B56: eliwania.santos@to.sebrae.com.br | D56: AUD-UNIDADE DE AUDITORIA INTERNA | I56: Ativo | J56: Eliwania dos Santos Silva | K56: Sim | L56: 8 | M56: 2025-12-09 | N56: 0 | O56: 0 | P56: 8 | Q56: 4 | R56: =IF(OR(L56="",L56=0)," ",IF(P56=L56,"Terminou","Não terminou")) -> Terminou | S56: =IFERROR(P56/L56,0) -> 1 | T56: =IFERROR(VLOOKUP(TRIM($A56),'Ações Finalizadas'!$A:$O,15,FALSE),"") -> Ética, Integridade e Responsabilidade, Gestão de Equipes, Gestão de Tempo, Planejamento, Foco e Resultados, Resolução de Problemas, Comunicação | U56: =IFERROR(VLOOKUP(TRIM($A56),'Ações Não Finalizadas'!$A:$G,15,FALSE),"")
A57: Elizeth Cristiane Coutinho Lima | B57: elizeth.cris1@gmail.com | D57: UGP-UNIDADE DE GESTÃO DE PESSOAS | I57: Ativo | J57: Vera Lucia Teodoro Braga | K57: Sim | L57: 5 | M57: 2025-12-03 | N57: 0 | O57: 0 | P57: 5 | Q57: 4 | R57: =IF(OR(L57="",L57=0)," ",IF(P57=L57,"Terminou","Não terminou")) -> Terminou | S57: =IFERROR(P57/L57,0) -> 1 | T57: =IFERROR(VLOOKUP(TRIM($A57),'Ações Finalizadas'!$A:$O,15,FALSE),"") -> Atendimento e Relacionamento com o Cliente, Ética, Integridade e Responsabilidade, Gestão de Tempo, Presença Executiva, Comunicação | U57: =IFERROR(VLOOKUP(TRIM($A57),'Ações Não Finalizadas'!$A:$G,15,FALSE),"")
A58: Ellen Custódio | B58: ellen.custodio@to.sebrae.com.br | D58: UTIC-UNIDADE DE TECNOLOGIA DA INFORM. E COMUNICAÇÃO DE DADOS | I58: Ativo | J58: Leonardo Campelo Leite Guedes | K58: Sim | L58: 2 | M58: 2025-10-01 | N58: 0 | O58: 0 | P58: 2 | Q58: 3 | R58: =IF(OR(L58="",L58=0)," ",IF(P58=L58,"Terminou","Não terminou")) -> Terminou | S58: =IFERROR(P58/L58,0) -> 1 | T58: =IFERROR(VLOOKUP(TRIM($A58),'Ações Finalizadas'!$A:$O,15,FALSE),"") -> Desenvolvimento Programa Integração | U58: =IFERROR(VLOOKUP(TRIM($A58),'Ações Não Finalizadas'!$A:$G,15,FALSE),"")
A59: Emerson Eduardo Aires Nunes | B59: emerson.nunes@to.sebrae.com.br | D59: UAS-UNIDADE DE ADMINISTRAÇÃO E SUPRIMENTOS | I59: Ativo | J59: Ana Paula Alves Santos | K59: Sim | L59: 5 | M59: 2025-12-16 | N59: 0 | O59: 0 | P59: 5 | Q59: 4 | R59: =IF(OR(L59="",L59=0)," ",IF(P59=L59,"Terminou","Não terminou")) -> Terminou | S59: =IFERROR(P59/L59,0) -> 1 | T59: =IFERROR(VLOOKUP(TRIM($A59),'Ações Finalizadas'!$A:$O,15,FALSE),"") -> Ética, Integridade e Responsabilidade, Competências Técnicas da Área, Gestão de Equipes, Gestão de Tempo, Resolução de Problemas | U59: =IFERROR(VLOOKUP(TRIM($A59),'Ações Não Finalizadas'!$A:$G,15,FALSE),"")
A60: Emerson Montenegro Lima | B60: emerson.lima@to.sebrae.com.br | D60: URC - UNIDADE DE RELACIONAMENTO COM O CLIENTE | I60: Ativo | J60: Emerson Montenegro Lima | K60: Sim | L60: 11 | M60: 2025-12-16 | N60: 0 | O60: 0 | P60: 11 | Q60: 4 | R60: =IF(OR(L60="",L60=0)," ",IF(P60=L60,"Terminou","Não terminou")) -> Terminou | S60: =IFERROR(P60/L60,0) -> 1 | T60: =IFERROR(VLOOKUP(TRIM($A60),'Ações Finalizadas'!$A:$O,15,FALSE),"") -> Ética, Integridade e Responsabilidade, Atitude Inovadora com Visão de Futuro, Gestão de Tempo, Planejamento, Foco e Resultados, Presença Executiva, Protagonismo, Autogestão e Tomada de Decisão, Resolução de Problemas, Tecnologia, Dados e Transformação Digital, Estratégia e Indicadores, Comunicação | U60: =IFERROR(VLOOKUP(TRIM($A60),'Ações Não Finalizadas'!$A:$G,15,FALSE),"")
A61: Euzebio Oliveira de Almeida | B61: euzebio.almeida@to.sebrae.com.br | D61: UGOC-UNIDADE DE GESTÃO ORÇ. CONTABILIDADE E FINANÇAS | I61: Ativo | J61: Andreia Rodrigues Facundes | K61: Sim | L61: 4 | M61: 2025-12-26 | N61: 0 | O61: 3 | P61: 1 | Q61: 3 | R61: =IF(OR(L61="",L61=0)," ",IF(P61=L61,"Terminou","Não terminou")) -> Não terminou | S61: =(P61 + O61*0.4666667) / L61 -> 0.60000002 | T61: =IFERROR(VLOOKUP(TRIM($A61),'Ações Finalizadas'!$A:$O,15,FALSE),"") -> Ética, Integridade e Responsabilidade, Planejamento, Foco e Resultados, Protagonismo, Autogestão e Tomada de Decisão, Comunicação | U61: =IFERROR(VLOOKUP(TRIM($A61),'Ações Não Finalizadas'!$A:$G,15,FALSE),"")
A62: Fabiane Cappellesso | B62: fabiane.cappellesso@to.sebrae.com.br | D62: Regional Portal do Jalapao | I62: Ativo | J62: Millena Pereira Lima Rodrigues | K62: Sim | L62: 8 | M62: 2025-12-11 | N62: 0 | O62: 0 | P62: 8 | Q62: 4 | R62: =IF(OR(L62="",L62=0)," ",IF(P62=L62,"Terminou","Não terminou")) -> Terminou | S62: =IFERROR(P62/L62,0) -> 1 | T62: =IFERROR(VLOOKUP(TRIM($A62),'Ações Finalizadas'!$A:$O,15,FALSE),"") -> Comunicação, Inovação, Criatividade e Visão Estratégica, Inteligência Emocional e Autoconhecimento, Liderança e Gestão de Pessoas, Planejamento, Foco e Resultados, Protagonismo, Autogestão e Tomada de Decisão, Resolução de Problemas, Tecnologia, Dados e Transformação Digital | U62: =IFERROR(VLOOKUP(TRIM($A62),'Ações Não Finalizadas'!$A:$G,15,FALSE),"")
A63: Fabio Henrique da Cruz | B63: fabio.cruz@to.sebrae.com.br | D63: Regional Vale do Araguaia | I63: Ativo | J63: Renata Moura Alves Simas | K63: Sim | L63: 6 | M63: 2025-10-01 | N63: 2 | O63: 0 | P63: 4 | Q63: 2 | R63: =IF(OR(L63="",L63=0)," ",IF(P63=L63,"Terminou","Não terminou")) -> Não terminou | S63: =IFERROR(P63/L63,0) -> 0.66666667 | T63: =IFERROR(VLOOKUP(TRIM($A63),'Ações Finalizadas'!$A:$O,15,FALSE),"") -> Vendas, Negociação e Soluções Comerciais | U63: =IFERROR(VLOOKUP(TRIM($A63),'Ações Não Finalizadas'!$A:$G,15,FALSE),"")
A64: Fabio Ribeiro Junior | B64: fabio.junior@to.sebrae.com.br | D64: Regional Metropolitana | I64: Ativo | J64: Amaggeldo Barbosa | K64: Sim | L64: 3 | M64: 2025-12-04 | N64: 0 | O64: 0 | P64: 3 | Q64: 4 | R64: =IF(OR(L64="",L64=0)," ",IF(P64=L64,"Terminou","Não terminou")) -> Terminou | S64: =IFERROR(P64/L64,0) -> 1 | T64: =IFERROR(VLOOKUP(TRIM($A64),'Ações Finalizadas'!$A:$O,15,FALSE),"") -> Desenvolvimento Programa Integração | U64: =IFERROR(VLOOKUP(TRIM($A64),'Ações Não Finalizadas'!$A:$G,15,FALSE),"")
A65: Fabricio Rodrigues da Silva Lustosa | B65: fabricio.lustosa@to.sebrae.com.br | D65: UGOC-UNIDADE DE GESTÃO ORÇ. CONTABILIDADE E FINANÇAS | I65: Ativo | J65: Andreia Rodrigues Facundes | K65: Sim | L65: 5 | M65: 2025-10-20 | N65: 0 | O65: 0 | P65: 5 | Q65: 4 | R65: =IF(OR(L65="",L65=0)," ",IF(P65=L65,"Terminou","Não terminou")) -> Terminou | S65: =IFERROR(P65/L65,0) -> 1 | T65: =IFERROR(VLOOKUP(TRIM($A65),'Ações Finalizadas'!$A:$O,15,FALSE),"") -> Inteligência Emocional e Autoconhecimento, Planejamento, Foco e Resultados, Tributária | U65: =IFERROR(VLOOKUP(TRIM($A65),'Ações Não Finalizadas'!$A:$G,15,FALSE),"")
A66: Francielly Quiteria Guimaraes Alves | B66: francielly.alves@to.sebrae.com.br | D66: Regional Sul | I66: Ativo | J66: Paula dos Reis Coelho Alencar Sousa | K66: Sim | L66: 12 | M66: 2025-12-10 | N66: 0 | O66: 0 | P66: 12 | Q66: 4 | R66: =IF(OR(L66="",L66=0)," ",IF(P66=L66,"Terminou","Não terminou")) -> Terminou | S66: =IFERROR(P66/L66,0) -> 1 | T66: =IFERROR(VLOOKUP(TRIM($A66),'Ações Finalizadas'!$A:$O,15,FALSE),"") -> Inteligência Emocional e Autoconhecimento, Liderança e Gestão de Pessoas, Planejamento, Foco e Resultados, Tecnologia, Dados e Transformação Digital, Vendas, Negociação e Soluções Comerciais, Comunicação, Desenvolvimento Programa Integração | U66: =IFERROR(VLOOKUP(TRIM($A66),'Ações Não Finalizadas'!$A:$G,15,FALSE),"")
A67: Francisco de Assis Dias Ramos | B67: francisco.ramos@to.sebrae.com.br | D67: UAC-UNIDADE DE ARTICULAÇÃO E COMPETITIVIDADE | I67: Ativo | J67: Bruno Martins Vieira | K67: Sim | L67: 5 | M67: 2025-12-09 | N67: 0 | O67: 0 | P67: 5 | Q67: 4 | R67: =IF(OR(L67="",L67=0)," ",IF(P67=L67,"Terminou","Não terminou")) -> Terminou | S67: =IFERROR(P67/L67,0) -> 1 | T67: =IFERROR(VLOOKUP(TRIM($A67),'Ações Finalizadas'!$A:$O,15,FALSE),"") -> Ética, Integridade e Responsabilidade, Gestão de Equipes, Gestão de Tempo, Comunicação | U67: =IFERROR(VLOOKUP(TRIM($A67),'Ações Não Finalizadas'!$A:$G,15,FALSE),"")
A68: Francismeire Ferreira Lima de Morais | B68: francismeire.morais@to.sebrae.com.br | D68: UGP-UNIDADE DE GESTÃO DE PESSOAS | I68: Ativo | J68: Vera Lucia Teodoro Braga | K68: Sim | L68: 9 | M68: 2025-12-03 | N68: 1 | O68: 0 | P68: 8 | Q68: 4 | R68: =IF(OR(L68="",L68=0)," ",IF(P68=L68,"Terminou","Não terminou")) -> Não terminou | S68: =(P68 + 0.5*O68) / L68 -> 0.88888889 | T68: =IFERROR(VLOOKUP(TRIM($A68),'Ações Finalizadas'!$A:$O,15,FALSE),"") -> Gestão de Projetos e Processos, Gestão de Tempo, Planejamento, Foco e Resultados, Presença Executiva, Protagonismo, Autogestão e Tomada de Decisão, Comunicação | U68: =IFERROR(VLOOKUP(TRIM($A68),'Ações Não Finalizadas'!$A:$G,15,FALSE),"")
A69: Gabriel Borges Araujo | B69: gabriel.araujo@to.sebrae.com.br | D69: UTIC-UNIDADE DE TECNOLOGIA DA INFORM. E COMUNICAÇÃO DE DADOS | I69: Ativo | J69: Leonardo Campelo Leite Guedes | K69: Sim | L69: 2 | M69: 2025-12-03 | N69: 2 | O69: 0 | P69: 0 | Q69: 2 | R69: =IF(OR(L69="",L69=0)," ",IF(P69=L69,"Terminou","Não terminou")) -> Não terminou | S69: =IFERROR(P69/L69,0) -> 0 | T69: =IFERROR(VLOOKUP(TRIM($A69),'Ações Finalizadas'!$A:$O,15,FALSE),"") | U69: =IFERROR(VLOOKUP(TRIM($A69),'Ações Não Finalizadas'!$A:$G,15,FALSE),"")
A70: Gabriel Martins Lira | B70: gabriel.lira@to.sebrae.com.br | D70: Regional Serras Gerais | I70: Ativo | J70: Antonio Louça Curcino | K70: Sim | L70: 8 | M70: 2025-12-17 | N70: 0 | O70: 0 | P70: 8 | Q70: 4 | R70: =IF(OR(L70="",L70=0)," ",IF(P70=L70,"Terminou","Não terminou")) -> Terminou | S70: =IFERROR(P70/L70,0) -> 1 | T70: =IFERROR(VLOOKUP(TRIM($A70),'Ações Finalizadas'!$A:$O,15,FALSE),"") -> Comunicação, Ética, Integridade e Responsabilidade, Gestão de Tempo, Inteligência Emocional e Autoconhecimento, Liderança e Gestão de Pessoas, Presença Executiva, Relacionamento, Vendas, Negociação e Soluções Comerciais | U70: =IFERROR(VLOOKUP(TRIM($A70),'Ações Não Finalizadas'!$A:$G,15,FALSE),"")
A71: Gabriela Tomasi | B71: gabriela.tomasi@to.sebrae.com.br | D71: URC - UNIDADE DE RELACIONAMENTO COM O CLIENTE | I71: Ativo | J71: Gabriela Tomasi | K71: Sim | L71: 10 | M71: 2025-12-09 | N71: 3 | O71: 0 | P71: 7 | Q71: 4 | R71: =IF(OR(L71="",L71=0)," ",IF(P71=L71,"Terminou","Não terminou")) -> Não terminou | S71: =IFERROR(P71/L71,0) -> 0.7 | T71: =IFERROR(VLOOKUP(TRIM($A71),'Ações Finalizadas'!$A:$O,15,FALSE),"") -> Conhecimentos Práticos e Acadêmicos em Marketing | U71: =IFERROR(VLOOKUP(TRIM($A71),'Ações Não Finalizadas'!$A:$G,15,FALSE),"")
A72: Geovane Almeida Nepomuceno | B72: falecomgeovane@gmail.com | D72: UMC-UNIDADE DE MARKETING E COMUNICAÇÃO | I72: Ativo | J72: Nemias Gomes | K72: Sim | L72: 14 | M72: 2025-12-11 | N72: 0 | O72: 0 | P72: 14 | Q72: 4 | R72: =IF(OR(L72="",L72=0)," ",IF(P72=L72,"Terminou","Não terminou")) -> Terminou | S72: =IFERROR(P72/L72,0) -> 1 | T72: =IFERROR(VLOOKUP(TRIM($A72),'Ações Finalizadas'!$A:$O,15,FALSE),"") -> Atitude Inovadora com Visão de Futuro, Conhecimentos Práticos e Acadêmicos em Marketing, Gestão de Projetos e Processos, Gestão de Tempo, Liderança e Gestão de Pessoas, Protagonismo, Autogestão e Tomada de Decisão, Tecnologia, Dados e Transformação Digital | U72: =IFERROR(VLOOKUP(TRIM($A72),'Ações Não Finalizadas'!$A:$G,15,FALSE),"")
A73: Getulio Rodrigues de Mendonca | B73: getulio.mendonca@to.sebrae.com.br | D73: UAS-UNIDADE DE ADMINISTRAÇÃO E SUPRIMENTOS | I73: Ativo | J73: Ana Paula Alves Santos | K73: Sim | L73: 5 | M73: 2025-10-31 | N73: 0 | O73: 0 | P73: 5 | Q73: 4 | R73: =IF(OR(L73="",L73=0)," ",IF(P73=L73,"Terminou","Não terminou")) -> Terminou | S73: =IFERROR(P73/L73,0) -> 1 | T73: =IFERROR(VLOOKUP(TRIM($A73),'Ações Finalizadas'!$A:$O,15,FALSE),"") -> Desenvolvimento de Ferramentas de Apoio na Execução, Ética, Integridade e Responsabilidade, Planejamento, Foco e Resultados, Comunicação | U73: =IFERROR(VLOOKUP(TRIM($A73),'Ações Não Finalizadas'!$A:$G,15,FALSE),"")
A74: Gilzane Pereira Amaral | B74: gilzane.pereira@to.sebrae.com.br | D74: URI-UNIDADE DE RELACIONAMENTO INSTITUCIONAL | I74: Ativo | J74: Gilzane Pereira Amaral | K74: Sim | L74: 8 | M74: 2025-12-09 | N74: 0 | O74: 0 | P74: 8 | Q74: 4 | R74: =IF(OR(L74="",L74=0)," ",IF(P74=L74,"Terminou","Não terminou")) -> Terminou | S74: =IFERROR(P74/L74,0) -> 1 | T74: =IFERROR(VLOOKUP(TRIM($A74),'Ações Finalizadas'!$A:$O,15,FALSE),"") -> Vendas, Negociação e Soluções Comerciais, Ética, Integridade e Responsabilidade, Inteligência Emocional e Autoconhecimento, Planejamento, Foco e Resultados, Protagonismo, Autogestão e Tomada de Decisão, Estratégia e Indicadores, Comunicação | U74: =IFERROR(VLOOKUP(TRIM($A74),'Ações Não Finalizadas'!$A:$G,15,FALSE),"")
A75: Glaucia de Godoi Souza Ferreira | B75: glaucia.ferreira@to.sebrae.com.br | D75: Regional Médio Norte Colinas | I75: Ativo | J75: Aldeni Batista Torres | K75: Sim | L75: 12 | M75: 2025-12-17 | N75: 0 | O75: 0 | P75: 12 | Q75: 4 | R75: =IF(OR(L75="",L75=0)," ",IF(P75=L75,"Terminou","Não terminou")) -> Terminou | S75: =IFERROR(P75/L75,0) -> 1 | T75: =IFERROR(VLOOKUP(TRIM($A75),'Ações Finalizadas'!$A:$O,15,FALSE),"") -> Adaptabilidade, Flexibilidade e Resiliência, Atendimento e Relacionamento com o Cliente, Gestão de Equipes, Inteligência Emocional e Autoconhecimento, Protagonismo, Autogestão e Tomada de Decisão, Vendas, Negociação e Soluções Comerciais, Relacionamento, Planejamento, Foco e Resultados | U75: =IFERROR(VLOOKUP(TRIM($A75),'Ações Não Finalizadas'!$A:$G,15,FALSE),"")
A76: Hide Senna de Sousa Soares | B76: hide.senna@to.sebrae.com.br | D76: SUPERINTENDENCIA | I76: Ativo | J76: Rerison Antonio Castro Leite | K76: Sim | L76: 5 | M76: 2025-12-09 | N76: 0 | O76: 0 | P76: 5 | Q76: 4 | R76: =IF(OR(L76="",L76=0)," ",IF(P76=L76,"Terminou","Não terminou")) -> Terminou | S76: =IFERROR(P76/L76,0) -> 1 | T76: =IFERROR(VLOOKUP(TRIM($A76),'Ações Finalizadas'!$A:$O,15,FALSE),"") -> Ética, Integridade e Responsabilidade, Gestão de Projetos e Processos, Inteligência Emocional e Autoconhecimento, Planejamento, Foco e Resultados, Comunicação | U76: =IFERROR(VLOOKUP(TRIM($A76),'Ações Não Finalizadas'!$A:$G,15,FALSE),"")
A77: Higor Nichollas de Oliveira | B77: higor.oliveira@to.sebrae.com.br | D77: UAS-UNIDADE DE ADMINISTRAÇÃO E SUPRIMENTOS | I77: Ativo | J77: Ana Paula Alves Santos | K77: Sim | L77: 6 | M77: 2025-12-12 | N77: 0 | O77: 0 | P77: 6 | Q77: 4 | R77: =IF(OR(L77="",L77=0)," ",IF(P77=L77,"Terminou","Não terminou")) -> Terminou | S77: =IFERROR(P77/L77,0) -> 1 | T77: =IFERROR(VLOOKUP(TRIM($A77),'Ações Finalizadas'!$A:$O,15,FALSE),"") -> Atendimento e Relacionamento com o Cliente, Compras, Facilities e Gestão Contratual, Ética, Integridade e Responsabilidade, Gestão de Projetos e Processos, Inteligência Emocional e Autoconhecimento, Comunicação | U77: =IFERROR(VLOOKUP(TRIM($A77),'Ações Não Finalizadas'!$A:$G,15,FALSE),"")
A78: Ilma Lopes da Silva | B78: ilma@to.sebrae.com.br | D78: Regional Norte | I78: Ativo | J78: Marcus Vinicius Vieira Queiroz | K78: Sim | L78: 5 | M78: 2025-11-24 | N78: 0 | O78: 0 | P78: 5 | Q78: 4 | R78: =IF(OR(L78="",L78=0)," ",IF(P78=L78,"Terminou","Não terminou")) -> Terminou | S78: =IFERROR(P78/L78,0) -> 1 | T78: =IFERROR(VLOOKUP(TRIM($A78),'Ações Finalizadas'!$A:$O,15,FALSE),"") -> Gestão do Conhecimento e Documentação Institucional, Atitude Inovadora com Visão de Futuro, Ética, Integridade e Responsabilidade, Inteligência Emocional e Autoconhecimento | U78: =IFERROR(VLOOKUP(TRIM($A78),'Ações Não Finalizadas'!$A:$G,15,FALSE),"")
A79: Ingrid Pamela Alves Amorim | B79: ingrid.amorim@to.sebrae.com.br | D79: Regional Norte | I79: Ativo | J79: Marcus Vinicius Vieira Queiroz | K79: Sim | L79: 12 | M79: 2025-12-16 | N79: 0 | O79: 0 | P79: 12 | Q79: 4 | R79: =IF(OR(L79="",L79=0)," ",IF(P79=L79,"Terminou","Não terminou")) -> Terminou | S79: =IFERROR(P79/L79,0) -> 1 | T79: =IFERROR(VLOOKUP(TRIM($A79),'Ações Finalizadas'!$A:$O,15,FALSE),"") -> Ética, Integridade e Responsabilidade, Comunicação, Estratégia e Indicadores, Gestão de Projetos e Processos, Inteligência Emocional e Autoconhecimento, Liderança e Gestão de Pessoas, Planejamento, Foco e Resultados, Vendas, Negociação e Soluções Comerciais | U79: =IFERROR(VLOOKUP(TRIM($A79),'Ações Não Finalizadas'!$A:$G,15,FALSE),"")
A80: Itallo Brandão Ferreira | B80: itallo.ferreira@to.sebrae.com.br | D80: Regional Médio Norte Colinas | I80: Ativo | J80: Aldeni Batista Torres | K80: Sim | L80: 2 | M80: 2025-12-11 | N80: 0 | O80: 0 | P80: 2 | Q80: 3 | R80: =IF(OR(L80="",L80=0)," ",IF(P80=L80,"Terminou","Não terminou")) -> Terminou | S80: =IFERROR(P80/L80,0) -> 1 | T80: =IFERROR(VLOOKUP(TRIM($A80),'Ações Finalizadas'!$A:$O,15,FALSE),"") -> Desenvolvimento Programa Integração | U80: =IFERROR(VLOOKUP(TRIM($A80),'Ações Não Finalizadas'!$A:$G,15,FALSE),"")
... A92: Juarez Quirino de Oliveira | B92: juarez.oliveira@to.sebrae.com.br | D92: UGOC-UNIDADE DE GESTÃO ORÇ. CONTABILIDADE E FINANÇAS | I92: Ativo | J92: Andreia Rodrigues Facundes | K92: Sim | L92: 6 | M92: 2025-12-12 | N92: 0 | O92: 0 | P92: 6 | Q92: 4 | R92: =IF(OR(L92="",L92=0)," ",IF(P92=L92,"Terminou","Não terminou")) -> Terminou | S92: =IFERROR(P92/L92,0) -> 1 | T92: =IFERROR(VLOOKUP(TRIM($A92),'Ações Finalizadas'!$A:$O,15,FALSE),"") -> Atitude Inovadora com Visão de Futuro, Planejamento, Foco e Resultados, Protagonismo, Autogestão e Tomada de Decisão, Estratégia e Indicadores, Relacionamento | U92: =IFERROR(VLOOKUP(TRIM($A92),'Ações Não Finalizadas'!$A:$G,15,FALSE),"")
A93: Juliana Masson Prediger | B93: juliana.prediger@to.sebrae.com.br | D93: Regional Serras Gerais | I93: Ativo | J93: Antonio Louça Curcino | K93: Sim | L93: 13 | M93: 2025-12-09 | N93: 0 | O93: 1 | P93: 12 | Q93: 4 | R93: =IF(OR(L93="",L93=0)," ",IF(P93=L93,"Terminou","Não terminou")) -> Não terminou | S93: =(P93 + 0.5*O93) / L93 -> 0.96153846 | T93: =IFERROR(VLOOKUP(TRIM($A93),'Ações Finalizadas'!$A:$O,15,FALSE),"") -> Ética, Integridade e Responsabilidade, Estratégia e Indicadores, Gestão de Projetos e Processos, Gestão do Conhecimento e Documentação Institucional, Inteligência Emocional e Autoconhecimento, Liderança e Gestão de Pessoas, Vendas, Negociação e Soluções Comerciais, Comunicação | U93: =IFERROR(VLOOKUP(TRIM($A93),'Ações Não Finalizadas'!$A:$G,15,FALSE),"")
A94: Kivia Raquel Pereira Leite | B94: kivia.leite@to.sebrae.com.br | D94: UGP-UNIDADE DE GESTÃO DE PESSOAS | I94: Ativo | J94: Vera Lucia Teodoro Braga | K94: Sim | L94: 6 | M94: 2025-12-03 | N94: 0 | O94: 1 | P94: 5 | Q94: 4 | R94: =IF(OR(L94="",L94=0)," ",IF(P94=L94,"Terminou","Não terminou")) -> Não terminou | S94: =(P94 + 0.5*O94) / L94 -> 0.91666667 | T94: =IFERROR(VLOOKUP(TRIM($A94),'Ações Finalizadas'!$A:$O,15,FALSE),"") -> Competências Técnicas da Área, Gestão de Tempo, Planejamento, Foco e Resultados, Presença Executiva, Comunicação, Desenvolvimento Programa Integração | U94: =IFERROR(VLOOKUP(TRIM($A94),'Ações Não Finalizadas'!$A:$G,15,FALSE),"")
A95: Laurenice Coelho Mesquita Castilho | B95: laurenice.mesquita@gmail.com | D95: URC - UNIDADE DE RELACIONAMENTO COM O CLIENTE | I95: Ativo | J95: Emerson Montenegro Lima | K95: Sim | L95: 4 | M95: 2025-12-03 | N95: 0 | O95: 0 | P95: 4 | Q95: 4 | R95: =IF(OR(L95="",L95=0)," ",IF(P95=L95,"Terminou","Não terminou")) -> Terminou | S95: =IFERROR(P95/L95,0) -> 1 | T95: =IFERROR(VLOOKUP(TRIM($A95),'Ações Finalizadas'!$A:$O,15,FALSE),"") -> Ética, Integridade e Responsabilidade, Gestão de Tempo, Planejamento, Foco e Resultados, Tecnologia, Dados e Transformação Digital | U95: =IFERROR(VLOOKUP(TRIM($A95),'Ações Não Finalizadas'!$A:$G,15,FALSE),"")
A96: Layala Cardoso da Silva Istofel | B96: layala.cardoso@to.sebrae.com.br | D96: URC - UNIDADE DE RELACIONAMENTO COM O CLIENTE | I96: Ativo | J96: Emerson Montenegro Lima | K96: Sim | L96: 9 | M96: 2025-12-09 | N96: 0 | O96: 0 | P96: 9 | Q96: 4 | R96: =IF(OR(L96="",L96=0)," ",IF(P96=L96,"Terminou","Não terminou")) -> Terminou | S96: =IFERROR(P96/L96,0) -> 1 | T96: =IFERROR(VLOOKUP(TRIM($A96),'Ações Finalizadas'!$A:$O,15,FALSE),"") -> Conhecimentos Práticos e Acadêmicos em Marketing, Ética, Integridade e Responsabilidade, Vendas, Negociação e Soluções Comerciais | U96: =IFERROR(VLOOKUP(TRIM($A96),'Ações Não Finalizadas'!$A:$G,15,FALSE),"")
A97: Leonardo Campelo Leite Guedes | B97: leonardo.campelo@to.sebrae.com.br | D97: UTIC-UNIDADE DE TECNOLOGIA DA INFORM. E COMUNICAÇÃO DE DADOS | I97: Ativo | J97: Leonardo Campelo Leite Guedes | K97: Sim | L97: 7 | M97: 2025-12-09 | N97: 7 | O97: 0 | P97: 0 | Q97: 2 | R97: =IF(OR(L97="",L97=0)," ",IF(P97=L97,"Terminou","Não terminou")) -> Não terminou | S97: =IFERROR(P97/L97,0) -> 0 | T97: =IFERROR(VLOOKUP(TRIM($A97),'Ações Finalizadas'!$A:$O,15,FALSE),"") | U97: =IFERROR(VLOOKUP(TRIM($A97),'Ações Não Finalizadas'!$A:$G,15,FALSE),"")
A98: Livia Pedreira Simões | B98: livia.simoes@to.sebrae.com.br | D98: UGOC-UNIDADE DE GESTÃO ORÇ. CONTABILIDADE E FINANÇAS | I98: Ativo | J98: Andreia Rodrigues Facundes | K98: Sim | L98: 10 | M98: 2025-11-07 | N98: 0 | O98: 0 | P98: 10 | Q98: 4 | R98: =IF(OR(L98="",L98=0)," ",IF(P98=L98,"Terminou","Não terminou")) -> Terminou | S98: =IFERROR(P98/L98,0) -> 1 | T98: =IFERROR(VLOOKUP(TRIM($A98),'Ações Finalizadas'!$A:$O,15,FALSE),"") -> Adaptabilidade, Flexibilidade e Resiliência, Atitude Inovadora com Visão de Futuro, Ética, Integridade e Responsabilidade, Gestão de Projetos e Processos, Inteligência Emocional e Autoconhecimento, Planejamento, Foco e Resultados, Protagonismo, Autogestão e Tomada de Decisão, Estratégia e Indicadores, Comunicação | U98: =IFERROR(VLOOKUP(TRIM($A98),'Ações Não Finalizadas'!$A:$G,15,FALSE),"")
A99: Livia Tenorio de Souza Leao | B99: livia.leao@to.sebrae.com.br | D99: UGOC-UNIDADE DE GESTÃO ORÇ. CONTABILIDADE E FINANÇAS | I99: Ativo | J99: Andreia Rodrigues Facundes | K99: Sim | L99: 7 | M99: 2025-10-09 | N99: 0 | O99: 0 | P99: 7 | Q99: 4 | R99: =IF(OR(L99="",L99=0)," ",IF(P99=L99,"Terminou","Não terminou")) -> Terminou | S99: =IFERROR(P99/L99,0) -> 1 | T99: =IFERROR(VLOOKUP(TRIM($A99),'Ações Finalizadas'!$A:$O,15,FALSE),"") -> Gestão de Tempo, Inteligência Emocional e Autoconhecimento, Planejamento, Foco e Resultados, Estratégia e Indicadores, Relacionamento, Desenvolvimento Programa Integração | U99: =IFERROR(VLOOKUP(TRIM($A99),'Ações Não Finalizadas'!$A:$G,15,FALSE),"")
A100: Luana Fernanda Rosa Martins | B100: luana.martins@to.sebrae.com.br | D100: UMC-UNIDADE DE MARKETING E COMUNICAÇÃO | I100: Ativo | J100: Nemias Gomes | K100: Sim | L100: 11 | M100: 2025-12-18 | N100: 0 | O100: 0 | P100: 11 | Q100: 4 | R100: =IF(OR(L100="",L100=0)," ",IF(P100=L100,"Terminou","Não terminou")) -> Terminou | S100: =IFERROR(P100/L100,0) -> 1 | T100: =IFERROR(VLOOKUP(TRIM($A100),'Ações Finalizadas'!$A:$O,15,FALSE),"") -> Atitude Inovadora com Visão de Futuro, Ética, Integridade e Responsabilidade, Gestão de Projetos e Processos, Gestão de Tempo, Inteligência Emocional e Autoconhecimento, Planejamento, Foco e Resultados, Presença Executiva, Comunicação | U100: =IFERROR(VLOOKUP(TRIM($A100),'Ações Não Finalizadas'!$A:$G,15,FALSE),"")
A101: Luciana Carvalho de Aguiar | B101: luciana@to.sebrae.com.br | D101: UGE-UNIDADE DE GESTÃO ESTRATÉGICA E INTEGRIDADE | I101: Ativo | J101: Pedro Junior da Rocha Silva | K101: Sim | L101: 2 | M101: 2025-12-09 | N101: 0 | O101: 0 | P101: 2 | Q101: 3 | R101: =IF(OR(L101="",L101=0)," ",IF(P101=L101,"Terminou","Não terminou")) -> Terminou | S101: =IFERROR(P101/L101,0) -> 1 | T101: =IFERROR(VLOOKUP(TRIM($A101),'Ações Finalizadas'!$A:$O,15,FALSE),"") -> Protagonismo, Autogestão e Tomada de Decisão, Comunicação | U101: =IFERROR(VLOOKUP(TRIM($A101),'Ações Não Finalizadas'!$A:$G,15,FALSE),"")
A102: Luciana Soares Pires Retes | B102: luciana.retes@to.sebrae.com.br | D102: URI-UNIDADE DE RELACIONAMENTO INSTITUCIONAL | I102: Ativo | J102: Gilzane Pereira Amaral | K102: Sim | L102: 8 | M102: 2025-12-12 | N102: 0 | O102: 0 | P102: 8 | Q102: 4 | R102: =IF(OR(L102="",L102=0)," ",IF(P102=L102,"Terminou","Não terminou")) -> Terminou | S102: =IFERROR(P102/L102,0) -> 1 | T102: =IFERROR(VLOOKUP(TRIM($A102),'Ações Finalizadas'!$A:$O,15,FALSE),"") -> Atitude Inovadora com Visão de Futuro, Finanças, Orçamento e Contabilidade Pública, Gestão de Equipes, Inteligência Emocional e Autoconhecimento, Planejamento, Foco e Resultados, Protagonismo, Autogestão e Tomada de Decisão, Comunicação | U102: =IFERROR(VLOOKUP(TRIM($A102),'Ações Não Finalizadas'!$A:$G,15,FALSE),"")
A103: Ludmila Santana Barbosa | B103: ludmila.santana@to.sebrae.com.br | D103: UAS-UNIDADE DE ADMINISTRAÇÃO E SUPRIMENTOS | I103: Ativo | J103: Ana Paula Alves Santos | K103: Sim | L103: 4 | M103: 2025-12-02 | N103: 0 | O103: 0 | P103: 4 | Q103: 4 | R103: =IF(OR(L103="",L103=0)," ",IF(P103=L103,"Terminou","Não terminou")) -> Terminou | S103: =IFERROR(P103/L103,0) -> 1 | T103: =IFERROR(VLOOKUP(TRIM($A103),'Ações Finalizadas'!$A:$O,15,FALSE),"") -> Ética, Integridade e Responsabilidade, Gestão de Tempo, Inteligência Emocional e Autoconhecimento, Políticas Públicas e Desenvolvimento Territorial | U103: =IFERROR(VLOOKUP(TRIM($A103),'Ações Não Finalizadas'!$A:$G,15,FALSE),"")
A104: Mailene Alencar Rodrigues Torres | B104: mailene.torres@to.sebrae.com.br | D104: Regional Médio Norte Colinas | I104: Ativo | J104: Aldeni Batista Torres | K104: Sim | L104: 11 | M104: 2025-10-09 | N104: 0 | O104: 0 | P104: 11 | Q104: 4 | R104: =IF(OR(L104="",L104=0)," ",IF(P104=L104,"Terminou","Não terminou")) -> Terminou | S104: =IFERROR(P104/L104,0) -> 1 | T104: =IFERROR(VLOOKUP(TRIM($A104),'Ações Finalizadas'!$A:$O,15,FALSE),"") -> Ética, Integridade e Responsabilidade, Vendas, Negociação e Soluções Comerciais, Atendimento e Relacionamento com o Cliente, Comunicação, Gestão de Projetos e Processos, Gestão de Tempo | U104: =IFERROR(VLOOKUP(TRIM($A104),'Ações Não Finalizadas'!$A:$G,15,FALSE),"")
A105: Maisa Fernandes Ribeiro | B105: maisa.ribeiro@to.sebrae.com.br | D105: URI-UNIDADE DE RELACIONAMENTO INSTITUCIONAL | I105: Ativo | J105: Gilzane Pereira Amaral | K105: Sim | L105: 9 | M105: 2025-12-03 | N105: 0 | O105: 0 | P105: 9 | Q105: 4 | R105: =IF(OR(L105="",L105=0)," ",IF(P105=L105,"Terminou","Não terminou")) -> Terminou | S105: =IFERROR(P105/L105,0) -> 1 | T105: =IFERROR(VLOOKUP(TRIM($A105),'Ações Finalizadas'!$A:$O,15,FALSE),"") -> Atitude Inovadora com Visão de Futuro, Ética, Integridade e Responsabilidade, Gestão de Tempo, Inteligência Emocional e Autoconhecimento, Protagonismo, Autogestão e Tomada de Decisão, Estratégia e Indicadores, Relacionamento | U105: =IFERROR(VLOOKUP(TRIM($A105),'Ações Não Finalizadas'!$A:$G,15,FALSE),"")
A106: Marcelle Soares Felix | B106: marcelle.felix@to.sebrae.com.br | D106: UMC-UNIDADE DE MARKETING E COMUNICAÇÃO | I106: Ativo | J106: Nemias Gomes | K106: Sim | L106: 4 | M106: 2025-11-24 | N106: 0 | O106: 0 | P106: 4 | Q106: 4 | R106: =IF(OR(L106="",L106=0)," ",IF(P106=L106,"Terminou","Não terminou")) -> Terminou | S106: =IFERROR(P106/L106,0) -> 1 | T106: =IFERROR(VLOOKUP(TRIM($A106),'Ações Finalizadas'!$A:$O,15,FALSE),"") -> Conhecimentos Práticos e Acadêmicos em Marketing | U106: =IFERROR(VLOOKUP(TRIM($A106),'Ações Não Finalizadas'!$A:$G,15,FALSE),"")
... A126: Rennan Jacinto da Silva Menezes | B126: rennan.menezes@to.sebrae.com.br | D126: UGOC-UNIDADE DE GESTÃO ORÇ. CONTABILIDADE E FINANÇAS | I126: Ativo | J126: Andreia Rodrigues Facundes | K126: Sim | L126: 9 | M126: 2025-08-27 | N126: 0 | O126: 0 | P126: 9 | Q126: 4 | R126: =IF(OR(L126="",L126=0)," ",IF(P126=L126,"Terminou","Não terminou")) -> Terminou | S126: =IFERROR(P126/L126,0) -> 1 | T126: =IFERROR(VLOOKUP(TRIM($A126),'Ações Finalizadas'!$A:$O,15,FALSE),"") -> Ética, Integridade e Responsabilidade, Gestão de Tempo, Inteligência Emocional e Autoconhecimento, Planejamento, Foco e Resultados, Estratégia e Indicadores, Comunicação, Tributária | U126: =IFERROR(VLOOKUP(TRIM($A126),'Ações Não Finalizadas'!$A:$G,15,FALSE),"")
A127: Rodrigo Alves dos Santos | B127: rodrigo.santos@to.sebrae.com.br | D127: Regional Serras Gerais | I127: Ativo | J127: Antonio Louça Curcino | K127: Sim | L127: 12 | M127: 2025-12-18 | N127: 1 | O127: 1 | P127: 10 | Q127: 4 | R127: =IF(OR(L127="",L127=0)," ",IF(P127=L127,"Terminou","Não terminou")) -> Não terminou | S127: =(P127 + O127*(-0.5)) / L127 -> 0.79166667 | T127: =IFERROR(VLOOKUP(TRIM($A127),'Ações Finalizadas'!$A:$O,15,FALSE),"") -> Ética, Integridade e Responsabilidade, Estratégia e Indicadores, Inteligência Emocional e Autoconhecimento, Planejamento, Foco e Resultados, Vendas, Negociação e Soluções Comerciais, Desenvolvimento Programa Integração | U127: =IFERROR(VLOOKUP(TRIM($A127),'Ações Não Finalizadas'!$A:$G,15,FALSE),"")
A128: Rodrigo Gaspar Pedroso Coelho | B128: rodrigo.coelho@to.sebrae.com.br | D128: URI-UNIDADE DE RELACIONAMENTO INSTITUCIONAL | I128: Ativo | J128: Gilzane Pereira Amaral | K128: Sim | L128: 2 | M128: 2025-11-28 | N128: 0 | O128: 0 | P128: 2 | Q128: 3 | R128: =IF(OR(L128="",L128=0)," ",IF(P128=L128,"Terminou","Não terminou")) -> Terminou | S128: =IFERROR(P128/L128,0) -> 1 | T128: =IFERROR(VLOOKUP(TRIM($A128),'Ações Finalizadas'!$A:$O,15,FALSE),"") -> Desenvolvimento Programa Integração | U128: =IFERROR(VLOOKUP(TRIM($A128),'Ações Não Finalizadas'!$A:$G,15,FALSE),"")
A129: Romisson Matias Santos | B129: romisson.santos@to.sebrae.com.br | D129: Regional Bico do Papagaio | I129: Ativo | J129: Edvaldo Pereira Lima Júnior | K129: Sim | L129: 14 | M129: 2025-12-19 | N129: 0 | O129: 0 | P129: 14 | Q129: 4 | R129: =IF(OR(L129="",L129=0)," ",IF(P129=L129,"Terminou","Não terminou")) -> Terminou | S129: =IFERROR(P129/L129,0) -> 1 | T129: =IFERROR(VLOOKUP(TRIM($A129),'Ações Finalizadas'!$A:$O,15,FALSE),"") -> Atitude Inovadora com Visão de Futuro, Estratégia e Indicadores, Gestão de Projetos e Processos, Gestão do Conhecimento e Documentação Institucional, Inteligência Emocional e Autoconhecimento, Liderança e Gestão de Pessoas, Planejamento, Foco e Resultados, Vendas, Negociação e Soluções Comerciais, Comunicação | U129: =IFERROR(VLOOKUP(TRIM($A129),'Ações Não Finalizadas'!$A:$G,15,FALSE),"")
A130: Sebastiao Geraldo de Oliveira | B130: sebastiaogeraldo34@gmail.com | D130: UAS-UNIDADE DE ADMINISTRAÇÃO E SUPRIMENTOS | I130: Ativo | J130: Ana Paula Alves Santos | K130: Sim | L130: 6 | M130: 2025-12-15 | N130: 0 | O130: 0 | P130: 6 | Q130: 4 | R130: =IF(OR(L130="",L130=0)," ",IF(P130=L130,"Terminou","Não terminou")) -> Terminou | S130: =IFERROR(P130/L130,0) -> 1 | T130: =IFERROR(VLOOKUP(TRIM($A130),'Ações Finalizadas'!$A:$O,15,FALSE),"") -> Desenvolvimento Programa Integração, Protagonismo, Autogestão e Tomada de Decisão, Relacionamento, Inteligência Emocional e Autoconhecimento, Legislação, Normas e Conformidade Jurídica, Planejamento, Foco e Resultados | U130: =IFERROR(VLOOKUP(TRIM($A130),'Ações Não Finalizadas'!$A:$G,15,FALSE),"")
...

Sheet Dinâmica % Finalizado por Time
A1: Contagem | B1: Rótulos de Coluna
A2: Áreas/Times | B2: Não terminou | C2: Terminou | D2: Total Geral | E2: PDIs TOTALMENTE Finalizados | F2: Média de Conclusão de Áreas por Time
A3: AUD-UNIDADE DE AUDITORIA INTERNA | C3: 2 | D3: 2 | E3: =IFERROR(C3/D3,0) -> 1 | F3: 1
A4: CDE-ASSESSORIA | C4: 3 | D4: 3 | E4: =IFERROR(C4/D4,0) -> 1 | F4: 1
A5: Regional Portal do Jalapao | B5: 2 | C5: 5 | D5: 7 | E5: =IFERROR(C5/D5,0) -> 0.71428571 | F5: 0.89455306
A6: Regional Bico do Papagaio | B6: 2 | C6: 4 | D6: 6 | E6: =IFERROR(C6/D6,0) -> 0.66666667 | F6: 0.98115079
A7: Regional Médio Norte Colinas | B7: 1 | C7: 7 | D7: 8 | E7: =IFERROR(C7/D7,0) -> 0.875 | F7: 0.99107143
A8: Regional Metropolitana | B8: 4 | C8: 10 | D8: 14 | E8: =IFERROR(C8/D8,0) -> 0.71428571 | F8: 0.9047619
A9: Regional Norte | C9: 8 | D9: 8 | E9: =IFERROR(C9/D9,0) -> 1 | F9: 1
A10: Regional Serras Gerais | B10: 4 | C10: 3 | D10: 7 | E10: =IFERROR(C10/D10,0) -> 0.42857143 | F10: 0.85113815
A11: Regional Sul | B11: 1 | C11: 7 | D11: 8 | E11: =IFERROR(C11/D11,0) -> 0.875 | F11: 0.93055556
A12: Regional Vale do Araguaia | B12: 6 | C12: 1 | D12: 7 | E12: =IFERROR(C12/D12,0) -> 0.14285714 | F12: 0.48888889
A13: SUPERINTENDENCIA | C13: 2 | D13: 2 | E13: =IFERROR(C13/D13,0) -> 1 | F13: 1
A14: UAC-UNIDADE DE ARTICULAÇÃO E COMPETITIVIDADE | C14: 9 | D14: 9 | E14: =IFERROR(C14/D14,0) -> 1 | F14: 1
A15: UAS-UNIDADE DE ADMINISTRAÇÃO E SUPRIMENTOS | C15: 10 | D15: 10 | E15: =IFERROR(C15/D15,0) -> 1 | F15: 1
A16: UGE-UNIDADE DE GESTÃO ESTRATÉGICA E INTEGRIDADE | B16: 1 | C16: 8 | D16: 9 | E16: =IFERROR(C16/D16,0) -> 0.88888889 | F16: 0.88888889
A17: UGOC-UNIDADE DE GESTÃO ORÇ. CONTABILIDADE E FINANÇAS | B17: 2 | C17: 12 | D17: 14 | E17: =IFERROR(C17/D17,0) -> 0.85714286 | F17: 0.9
A18: UGP-UNIDADE DE GESTÃO DE PESSOAS | B18: 3 | C18: 4 | D18: 7 | E18: =IFERROR(C18/D18,0) -> 0.57142857 | F18: 0.96123321
A19: UMC-UNIDADE DE MARKETING E COMUNICAÇÃO | C19: 8 | D19: 8 | E19: =IFERROR(C19/D19,0) -> 1 | F19: 1
A20: URC - UNIDADE DE RELACIONAMENTO COM O CLIENTE | B20: 1 | C20: 10 | D20: 11 | E20: =IFERROR(C20/D20,0) -> 0.90909091 | F20: 0.97272727
A21: URI-UNIDADE DE RELACIONAMENTO INSTITUCIONAL | C21: 8 | D21: 8 | E21: =IFERROR(C21/D21,0) -> 1 | F21: 1
A22: UTIC-UNIDADE DE TECNOLOGIA DA INFORM. E COMUNICAÇÃO DE DADOS | B22: 4 | C22: 4 | D22: 8 | E22: =IFERROR(C22/D22,0) -> 0.5 | F22: 0.703125
A23: Total Geral | B23: 31 | C23: 125 | D23: 156 | E23: =PDI!R158 -> 0.80128205 | F23: =AVERAGE(F3:F22) -> 0.92340471

Sheet Planilha4
A1: Time | B1: Total Pessoas | C1: Finalizaram | D1: % Finalizaram | E1: Média % Conclusão
A2: AUD-UNIDADE DE AUDITORIA INTERNA | B2: =COUNTIF(PDI!D:D,A2) -> 2 | C2: =COUNTIFS(PDI!D:D,A2,PDI!R:R,"Terminou") -> 2 | D2: =IFERROR(C2/B2,0) -> 1 | E2: =AVERAGEIF(PDI!D:D,A2,PDI!S:S) -> 1
A3: CDE-ASSESSORIA | B3: =COUNTIF(PDI!D:D,A3) -> 3 | C3: =COUNTIFS(PDI!D:D,A3,PDI!R:R,"Terminou") -> 3 | D3: =IFERROR(C3/B3,0) -> 1 | E3: =AVERAGEIF(PDI!D:D,A3,PDI!S:S) -> 1
A4: Regional Portal do Jalapao | B4: =COUNTIF(PDI!D:D,A4) -> 7 | C4: =COUNTIFS(PDI!D:D,A4,PDI!R:R,"Terminou") -> 5 | D4: =IFERROR(C4/B4,0) -> 0.71428571 | E4: =AVERAGEIF(PDI!D:D,A4,PDI!S:S) -> 0.89455306
A5: Regional Bico do Papagaio | B5: =COUNTIF(PDI!D:D,A5) -> 6 | C5: =COUNTIFS(PDI!D:D,A5,PDI!R:R,"Terminou") -> 4 | D5: =IFERROR(C5/B5,0) -> 0.66666667 | E5: =AVERAGEIF(PDI!D:D,A5,PDI!S:S) -> 0.98115079
A6: Regional Médio Norte Colinas | B6: =COUNTIF(PDI!D:D,A6) -> 8 | C6: =COUNTIFS(PDI!D:D,A6,PDI!R:R,"Terminou") -> 7 | D6: =IFERROR(C6/B6,0) -> 0.875 | E6: =AVERAGEIF(PDI!D:D,A6,PDI!S:S) -> 0.99107143
A7: Regional Metropolitana | B7: =COUNTIF(PDI!D:D,A7) -> 14 | C7: =COUNTIFS(PDI!D:D,A7,PDI!R:R,"Terminou") -> 10 | D7: =IFERROR(C7/B7,0) -> 0.71428571 | E7: =AVERAGEIF(PDI!D:D,A7,PDI!S:S) -> 0.9047619
A8: Regional Norte | B8: =COUNTIF(PDI!D:D,A8) -> 8 | C8: =COUNTIFS(PDI!D:D,A8,PDI!R:R,"Terminou") -> 8 | D8: =IFERROR(C8/B8,0) -> 1 | E8: =AVERAGEIF(PDI!D:D,A8,PDI!S:S) -> 1
A9: Regional Serras Gerais | B9: =COUNTIF(PDI!D:D,A9) -> 7 | C9: =COUNTIFS(PDI!D:D,A9,PDI!R:R,"Terminou") -> 3 | D9: =IFERROR(C9/B9,0) -> 0.42857143 | E9: =AVERAGEIF(PDI!D:D,A9,PDI!S:S) -> 0.85113815
A10: Regional Sul | B10: =COUNTIF(PDI!D:D,A10) -> 8 | C10: =COUNTIFS(PDI!D:D,A10,PDI!R:R,"Terminou") -> 7 | D10: =IFERROR(C10/B10,0) -> 0.875 | E10: =AVERAGEIF(PDI!D:D,A10,PDI!S:S) -> 0.93055556
A11: Regional Vale do Araguaia | B11: =COUNTIF(PDI!D:D,A11) -> 7 | C11: =COUNTIFS(PDI!D:D,A11,PDI!R:R,"Terminou") -> 1 | D11: =IFERROR(C11/B11,0) -> 0.14285714 | E11: =AVERAGEIF(PDI!D:D,A11,PDI!S:S) -> 0.48888889
A12: SUPERINTENDENCIA | B12: =COUNTIF(PDI!D:D,A12) -> 2 | C12: =COUNTIFS(PDI!D:D,A12,PDI!R:R,"Terminou") -> 2 | D12: =IFERROR(C12/B12,0) -> 1 | E12: =AVERAGEIF(PDI!D:D,A12,PDI!S:S) -> 1
A13: UAC-UNIDADE DE ARTICULAÇÃO E COMPETITIVIDADE | B13: =COUNTIF(PDI!D:D,A13) -> 9 | C13: =COUNTIFS(PDI!D:D,A13,PDI!R:R,"Terminou") -> 9 | D13: =IFERROR(C13/B13,0) -> 1 | E13: =AVERAGEIF(PDI!D:D,A13,PDI!S:S) -> 1
... A22: UTIC-UNIDADE DE TECNOLOGIA DA INFORM. E COMUNICAÇÃO DE DADOS | B22: =COUNTIF(PDI!D:D,A22) -> 8 | C22: =COUNTIFS(PDI!D:D,A22,PDI!R:R,"Terminou") -> 4 | D22: =IFERROR(C22/B22,0) -> 0.5 | E22: =AVERAGEIF(PDI!D:D,A22,PDI!S:S) -> 0.703125

Sheet Áreas de desenvolvimento
A1: Nome | B1: Email | C1: Cpf | D1: Times | E1: Tags Privadas | F1: Tags Públicas | G1: Área | H1: Identificador | I1: status | J1: Líder | K1: Área de desenvolvimento | L1: Descrição | M1: Categoria | N1: Criado em (yyyy-mm-dd) | O1: Atualizado em (yyyy-mm-dd) | P1: Progresso | Q1: Total de ações | R1: Finalizada
A2: Adelice Thomaz Soares Novak | B2: adelice@to.sebrae.com.br | D2: UAC-UNIDADE DE ARTICULAÇÃO E COMPETITIVIDADE | I2: Ativo | J2: Bruno Martins Vieira | K2: Macro Área do Comportamento: Liderança e Gestão de Pessoas | L2: Melhora a assertividade e análise na escolha de caminhos. | M2: Potencializar | N2: 2025-05-29 | O2: 2025-07-28 | P2: Finalizada | Q2: 1 | R2: 1
A3: Adelice Thomaz Soares Novak | B3: adelice@to.sebrae.com.br | D3: UAC-UNIDADE DE ARTICULAÇÃO E COMPETITIVIDADE | I3: Ativo | J3: Bruno Martins Vieira | K3: Macro Área do Comportamento: Ética, Integridade e Responsabilidade | L3: Fortalecer a conduta ética e o alinhamento aos princípios institucionais do Sebrae. | M3: Potencializar | N3: 2025-05-19 | O3: 2025-07-29 | P3: Finalizada | Q3: 1 | R3: 1
A4: Adelice Thomaz Soares Novak | B4: adelice@to.sebrae.com.br | D4: UAC-UNIDADE DE ARTICULAÇÃO E COMPETITIVIDADE | I4: Ativo | J4: Bruno Martins Vieira | K4: Macro Área do Comportamento: Comunicação e Relacionamento | L4: Fortalece a capacidade de expressar ideias com clareza, objetividade e respeito. | M4: Potencializar | N4: 2025-05-29 | O4: 2025-07-28 | P4: Finalizada | Q4: 1 | R4: 1
A5: Adelice Thomaz Soares Novak | B5: adelice@to.sebrae.com.br | D5: UAC-UNIDADE DE ARTICULAÇÃO E COMPETITIVIDADE | I5: Ativo | J5: Bruno Martins Vieira | K5: Macro Área do Comportamento: Planejamento, Foco e Resultados | L5: Desenvolve disciplina e visão de curto, médio e longo prazo. | M5: Potencializar | N5: 2025-05-29 | O5: 2025-08-14 | P5: Finalizada | Q5: 1 | R5: 1
A6: Adelice Thomaz Soares Novak | B6: adelice@to.sebrae.com.br | D6: UAC-UNIDADE DE ARTICULAÇÃO E COMPETITIVIDADE | I6: Ativo | J6: Bruno Martins Vieira | K6: Macro Área do Comportamento: Planejamento, Foco e Resultados | L6: Constrói reputação e direcionamento profissional estratégico. | M6: Potencializar | N6: 2025-05-29 | O6: 2025-07-29 | P6: Finalizada | Q6: 1 | R6: 1
A7: Adelice Thomaz Soares Novak | B7: adelice@to.sebrae.com.br | D7: UAC-UNIDADE DE ARTICULAÇÃO E COMPETITIVIDADE | I7: Ativo | J7: Bruno Martins Vieira | K7: Macro Área do Comportamento: Networking e Parcerias Estratégicas | L7: Expande oportunidades por meio de conexões relevantes. | M7: Potencializar | N7: 2025-05-29 | O7: 2025-08-19 | P7: Finalizada | Q7: 1 | R7: 1
A8: Adelice Thomaz Soares Novak | B8: adelice@to.sebrae.com.br | D8: UAC-UNIDADE DE ARTICULAÇÃO E COMPETITIVIDADE | I8: Ativo | J8: Bruno Martins Vieira | K8: Macro Área do Comportamento: Trabalho em Equipe e Colaboração | L8: Desenvolve a capacidade de atuar de forma eficaz, respeitosa e integrada com os colegas. | M8: Potencializar | N8: 2025-05-29 | O8: 2025-07-28 | P8: Finalizada | Q8: 2 | R8: 2
A9: Adelice Thomaz Soares Novak | B9: adelice@to.sebrae.com.br | D9: UAC-UNIDADE DE ARTICULAÇÃO E COMPETITIVIDADE | I9: Ativo | J9: Bruno Martins Vieira | K9: Macro Área Técnica: Tecnologia, Dados e Transformação Digital | L9: Promove aperfeiçoamento constante e adaptação a mudanças. | M9: Potencializar | N9: 2025-05-29 | O9: 2025-09-12 | P9: Finalizada | Q9: 1 | R9: 1
A10: Ademir Whitman Gomes Rego | B10: ademir@to.sebrae.com.br | D10: Regional Vale do Araguaia | I10: Ativo | J10: Renata Moura Alves Simas | K10: Macro Área do Comportamento: Comunicação e Relacionamento | L10: Aprimorar habilidades de comunicação clara e empática | M10: Potencializar | N10: 2025-04-17 | O10: 2025-07-25 | P10: Não iniciada | Q10: 1 | R10: 0
A11: Ademir Whitman Gomes Rego | B11: ademir@to.sebrae.com.br | D11: Regional Vale do Araguaia | I11: Ativo | J11: Renata Moura Alves Simas | K11: Macro Área Técnica: Tecnologia, Dados e Transformação Digital | L11: Inovação e soluções aplicáveis ao setor público | M11: Potencializar | N11: 2025-04-17 | O11: 2025-07-25 | P11: Não iniciada | Q11: 1 | R11: 0
A12: Ademir Whitman Gomes Rego | B12: ademir@to.sebrae.com.br | D12: Regional Vale do Araguaia | I12: Ativo | J12: Renata Moura Alves Simas | K12: Macro Área Técnica: Compras, Facilities e Gestão Contratual | L12: Gestão Pública Políticas públicas e desenvolvimento territorial Curso online | M12: Potencializar | N12: 2025-04-17 | O12: 2025-07-25 | P12: Não iniciada | Q12: 1 | R12: 0
A13: Ademir Whitman Gomes Rego | B13: ademir@to.sebrae.com.br | D13: Regional Vale do Araguaia | I13: Ativo | J13: Renata Moura Alves Simas | K13: Macro Área Técnica: Tecnologia, Dados e Transformação Digital | L13: Uso de Inteligência Artificial aplicada ao atendimento | M13: Potencializar | N13: 2025-04-17 | O13: 2025-07-25 | P13: Não iniciada | Q13: 1 | R13: 0
... A29: Admary Monteiro Barbosa | B29: admary.monteiro@to.sebrae.com.br | D29: Regional Portal do Jalapao | I29: Ativo | J29: Millena Pereira Lima Rodrigues | K29: Macro Área: Vendas, Negociação e Soluções Comerciais | L29: Negociação Institucional | M29: Potencializar | N29: 2025-03-31 | O29: 2025-12-19 | P29: Finalizada | Q29: 1 | R29: 1
A30: Adrielle Andrade | B30: adrielle.andrade@to.sebrae.com.br | D30: Regional Sul | I30: Ativo | J30: Paula dos Reis Coelho Alencar Sousa | K30: PDI - Onboarding (Competências Comportamentais) | M30: Potencializar | N30: 2025-11-07 | O30: 2025-12-19 | P30: Finalizada | Q30: 3 | R30: 3
A31: Adrielle Andrade | B31: adrielle.andrade@to.sebrae.com.br | D31: Regional Sul | I31: Ativo | J31: Paula dos Reis Coelho Alencar Sousa | K31: PDI - Onboarding (Tarefas da sua Gestão) | M31: Potencializar | N31: 2025-11-07 | O31: 2025-12-18 | P31: Finalizada | Q31: 4 | R31: 4
A32: Aldeni Batista Torres | B32: aldeni.torres@to.sebrae.com.br | D32: Regional Médio Norte Colinas | I32: Ativo | K32: Macro Área: Gestão de Projetos e Processos | L32: Competência Técnica: Gestão de Projetos e Processos Aprimoramento de conhecimentos específicos e ferramentas técnicas para otimizar a performance em funções estratégicas. | M32: Potencializar | N32: 2025-03-25 | O32: 2025-12-18 | P32: Finalizada | Q32: 1 | R32: 1
A33: Aldeni Batista Torres | B33: aldeni.torres@to.sebrae.com.br | D33: Regional Médio Norte Colinas | I33: Ativo | K33: Macro Área: Inteligência Emocional e Autoconhecimento | L33: Competência Comportamental: Desenvolvimento de Marca Pessoal Estratégias para fortalecimento da marca pessoal, planejamento profissional e ampliação de oportunidades de crescimento. | M33: Potencializar | N33: 2025-03-25 | O33: 2025-08-14 | P33: Finalizada | Q33: 1 | R33: 1
A34: Aldeni Batista Torres | B34: aldeni.torres@to.sebrae.com.br | D34: Regional Médio Norte Colinas | I34: Ativo | K34: Macro Área: Atendimento e Relacionamento com o Cliente | L34: Competência Comportamental: Networking e Parcerias Estratégicas | M34: Potencializar | N34: 2025-03-25 | O34: 2025-11-17 | P34: Finalizada | Q34: 1 | R34: 1
A35: Aldeni Batista Torres | B35: aldeni.torres@to.sebrae.com.br | D35: Regional Médio Norte Colinas | I35: Ativo | K35: Macro Área: Atendimento e Relacionamento com o Cliente | L35: Competência Comportamental: Negociação e Relacionamento com Clientes Capacidade de analisar cenários, tomar decisões e estabelecer conexões estratégicas para melhorar o impacto organizacional. | M35: Potencializar | N35: 2025-03-25 | O35: 2025-08-14 | P35: Não iniciada | Q35: 1 | R35: 0
A36: Aldeni Batista Torres | B36: aldeni.torres@to.sebrae.com.br | D36: Regional Médio Norte Colinas | I36: Ativo | K36: Macro Área: Gestão de Equipes | L36: Competência Comportamental: Liderança e Gestão de Equipes Aprimoramento da capacidade de influenciar, motivar e desenvolver equipes. Essencial para um ambiente organizacional produtivo. | M36: Potencializar | N36: 2025-03-25 | O36: 2025-12-02 | P36: Em progresso | Q36: 2 | R36: 1
A37: Aldeni Batista Torres | B37: aldeni.torres@to.sebrae.com.br | D37: Regional Médio Norte Colinas | I37: Ativo | K37: Macro Área: Protagonismo, Autogestão e Tomada de Decisão | L37: Competência Comportamental: Análise de Dados e Tomada de Decisão Capacidade de analisar cenários, tomar decisões e estabelecer conexões estratégicas para melhorar o impacto organizacional. | M37: Potencializar | N37: 2025-03-25 | O37: 2025-12-18 | P37: Finalizada | Q37: 1 | R37: 1
A38: Aldeni Batista Torres | B38: aldeni.torres@to.sebrae.com.br | D38: Regional Médio Norte Colinas | I38: Ativo | K38: Macro Área: Inteligência Emocional e Autoconhecimento | L38: Competência Comportamental: Desenvolvimento Pessoal e Inteligência Emocional Capacidade de se comunicar, interagir e colaborar com outras pessoas de forma eficaz. Ajuda a construir relacionamentos, resolver conflitos e fortalecer a influência. | M38: Potencializar | N38: 2025-03-25 | O38: 2025-08-14 | P38: Finalizada | Q38: 1 | R38: 1
A39: Alencar Hubner Borelli | B39: alencar.borelli@to.sebrae.com.br | D39: UAS-UNIDADE DE ADMINISTRAÇÃO E SUPRIMENTOS | I39: Ativo | J39: Ana Paula Alves Santos | K39: Macro Área: Ética, Integridade e Responsabilidade | L39: Competência Técnica: Ética e Conformidade Fortalecer a conduta ética e o alinhamento aos princípios institucionais do Sebrae. | M39: Potencializar | N39: 2025-05-19 | O39: 2025-12-01 | P39: Finalizada | Q39: 1 | R39: 1
A40: Alencar Hubner Borelli | B40: alencar.borelli@to.sebrae.com.br | D40: UAS-UNIDADE DE ADMINISTRAÇÃO E SUPRIMENTOS | I40: Ativo | J40: Ana Paula Alves Santos | K40: Macro Área: Desenvolvimento de Ferramentas de Apoio na Execução | L40: Competência Técnica: Ferramentas Digitais para Facilities e Compras Desenvolver habilidades práticas e conhecimentos avançados sobre ferramentas digitais que podem otimizar o gerenciamento de facilities e compras, trazendo mais agilidade e controle. | M40: Potencializar | N40: 2025-06-03 | O40: 2025-12-04 | P40: Finalizada | Q40: 1 | R40: 1
A41: Alex Veras Dias | B41: alex.dias@to.sebrae.com.br | D41: URI-UNIDADE DE RELACIONAMENTO INSTITUCIONAL | I41: Ativo | J41: Gilzane Pereira Amaral | K41: Macro Área: Políticas Públicas e Desenvolvimento Territorial | L41: Competência Técnica: Desenvolvimento Territorial e Economia Regional Ampliar o conhecimento sobre as dinâmicas do desenvolvimento territorial e da economia regional, com foco específico na realidade do Tocantins, para embasar estratégias e articulações. (Fonte: Questionário - Temas, Cargo) | M41: Potencializar | N41: 2025-05-29 | O41: 2025-11-27 | P41: Finalizada | Q41: 1 | R41: 1
A42: Alex Veras Dias | B42: alex.dias@to.sebrae.com.br | D42: URI-UNIDADE DE RELACIONAMENTO INSTITUCIONAL | I42: Ativo | J42: Gilzane Pereira Amaral | K42: Macro Área: Planejamento, Foco e Resultados | L42: Competência Comportamental: Gestão da Ansiedade e Foco Desenvolver estratégias para gerenciar a ansiedade e a inquietude, melhorando o foco e a tranquilidade na execução das tarefas e tomada de decisão. (Fonte: PDI Anterior - Fraquezas, DISC) | M42: Potencializar | N42: 2025-05-29 | O42: 2025-11-27 | P42: Finalizada | Q42: 1 | R42: 1
A43: Alex Veras Dias | B43: alex.dias@to.sebrae.com.br | D43: URI-UNIDADE DE RELACIONAMENTO INSTITUCIONAL | I43: Ativo | J43: Gilzane Pereira Amaral | K43: Macro Área: Gestão de Tempo | L43: Competência Técnica: Gestão do Tempo e Priorização de Demandas Otimizar a gestão do tempo e a capacidade de priorização para lidar com o volume de demandas de forma eficaz, garantindo a entrega de resultados estratégicos. (Fonte: Questionário - Desafios) | M43: Potencializar | N43: 2025-05-29 | O43: 2025-12-19 | P43: Finalizada | Q43: 1 | R43: 1
A44: Alex Veras Dias | B44: alex.dias@to.sebrae.com.br | D44: URI-UNIDADE DE RELACIONAMENTO INSTITUCIONAL | I44: Ativo | J44: Gilzane Pereira Amaral | K44: Macro Área: Visão Sistêmica com foco em Indicadores Estratégicos | L44: Competência Técnica: Liderança Estratégica e Visão Sistêmica Fortalecer a capacidade de pensar e agir estrategicamente, desenvolvendo uma visão sistêmica do negócio e do território para liderar iniciativas de maior impacto. (Fonte: Questionário - Competências, Avaliação - C, DISC - Talento Facilitador/Articulador) | M44: Potencializar | N44: 2025-05-29 | O44: 2025-12-16 | P44: Finalizada | Q44: 1 | R44: 1
A45: Alex Veras Dias | B45: alex.dias@to.sebrae.com.br | D45: URI-UNIDADE DE RELACIONAMENTO INSTITUCIONAL | I45: Ativo | J45: Gilzane Pereira Amaral | K45: Macro Área: Ética, Integridade e Responsabilidade | L45: Competência Técnica: Ética e Conformidade Fortalecer a conduta ética e o alinhamento aos princípios institucionais do Sebrae. | M45: Potencializar | N45: 2025-05-19 | O45: 2025-08-27 | P45: Finalizada | Q45: 1 | R45: 1
A46: Alex Veras Dias | B46: alex.dias@to.sebrae.com.br | D46: URI-UNIDADE DE RELACIONAMENTO INSTITUCIONAL | I46: Ativo | J46: Gilzane Pereira Amaral | K46: Macro Área: Comunicação Estratégica e Influente | L46: Competência Comportamental: Comunicação Eficaz e Feedback Construtivo Aprimorar a clareza, a escuta ativa e a assertividade na comunicação interpessoal e ao fornecer/receber feedback, visando interações mais fluidas e construtivas. (Fonte: Questionário, Avaliação de Competências - B, PDI Anterior, DISC) | M46: Potencializar | N46: 2025-05-29 | O46: 2025-10-30 | P46: Finalizada | Q46: 1 | R46: 1
A47: Alex Veras Dias | B47: alex.dias@to.sebrae.com.br | D47: URI-UNIDADE DE RELACIONAMENTO INSTITUCIONAL | I47: Ativo | J47: Gilzane Pereira Amaral | K47: Macro Área: Finanças, Orçamento e Contabilidade Pública | L47: Competência Técnica:: Gestão de Convênios para colaboradores do Sistema Sebrae O curso Gestão de Convênios para colaboradores do Sistema Sebrae foi projetado para fornecer a você as ferramentas e o conhecimento necessários para navegar com segurança e eficiência pelos processos, diretrizes e práticas de gestão de convênios. | M47: Potencializar | N47: 2025-06-10 | O47: 2025-10-30 | P47: Finalizada | Q47: 1 | R47: 1
A48: Alex Veras Dias | B48: alex.dias@to.sebrae.com.br | D48: URI-UNIDADE DE RELACIONAMENTO INSTITUCIONAL | I48: Ativo | J48: Gilzane Pereira Amaral | K48: Macro Área: Estratégia focada em Indicadores | L48: Competência Técnica: Análise e Formulação de Políticas Públicas para Pequenos Negócios Aprofundar o conhecimento técnico sobre o ciclo de políticas públicas, metodologias de análise e formulação, com foco nas necessidades dos pequenos negócios. (Fonte: Questionário - Temas, Cargo) | M48: Potencializar | N48: 2025-05-29 | O48: 2025-11-27 | P48: Finalizada | Q48: 1 | R48: 1
A49: Alex Veras Dias | B49: alex.dias@to.sebrae.com.br | D49: URI-UNIDADE DE RELACIONAMENTO INSTITUCIONAL | I49: Ativo | J49: Gilzane Pereira Amaral | K49: Macro Área: Liderança e Gestão de Pessoas | L49: Competência Comportamental: Delegação Eficaz e Gestão da Centralização- Desenvolver a habilidade de delegar tarefas de forma clara e confiante, superando a tendência à centralização, para otimizar o tempo e potencializar a equipe. (Fonte: PDI Anterior - Fraquezas) | M49: Potencializar | N49: 2025-05-29 | O49: 2025-12-19 | P49: Finalizada | Q49: 1 | R49: 1
A50: Alice Sousa Santos Costa | B50: alice.costa@to.sebrae.com.br | D50: Regional Sul | I50: Ativo | J50: Paula dos Reis Coelho Alencar Sousa | K50: Macro Área: Comunicação e Relacionamento | L50: Competência Comportamental: Empatia & Relacionamento Interpessoal Sensibilidade para lidar com diferentes perfis. | M50: Potencializar | N50: 2025-03-28 | O50: 2025-09-03 | P50: Finalizada | Q50: 2 | R50: 2
... A56: Alice Sousa Santos Costa | B56: alice.costa@to.sebrae.com.br | D56: Regional Sul | I56: Ativo | J56: Paula dos Reis Coelho Alencar Sousa | K56: Macro Área: Gestão do Conhecimento e Documentação Institucional | L56: Competência Técnica: Conhecimento Técnico Domínio sobre o portfólio Sebrae e adaptação ao público | M56: Potencializar | N56: 2025-03-28 | O56: 2025-12-01 | P56: Finalizada | Q56: 3 | R56: 3
A57: Aline Almeida | B57: aline.almeida@to.sebrae.com.br | D57: Regional Médio Norte Colinas | I57: Ativo | J57: Aldeni Batista Torres | K57: PDI - Onboarding (Competências Comportamentais) | M57: Potencializar | N57: 2025-10-03 | O57: 2025-12-15 | P57: Finalizada | Q57: 10 | R57: 10
A58: Aline Almeida | B58: aline.almeida@to.sebrae.com.br | D58: Regional Médio Norte Colinas | I58: Ativo | J58: Aldeni Batista Torres | K58: PDI - Onboarding (Tarefas da sua Gestão) | M58: Potencializar | N58: 2025-10-03 | O58: 2025-12-08 | P58: Finalizada | Q58: 3 | R58: 3
A59: Alorran de Freitas Barbosa | B59: alorran.barbosa@to.sebrae.com.br | D59: UTIC-UNIDADE DE TECNOLOGIA DA INFORM. E COMUNICAÇÃO DE DADOS | I59: Ativo | J59: Leonardo Campelo Leite Guedes | K59: Macro Área: Ética, Integridade e Responsabilidade | L59: Competência Técnica: Ética e Conformidade Fortalecer a conduta ética e o alinhamento aos princípios institucionais do Sebrae. | M59: Potencializar | N59: 2025-05-19 | O59: 2025-08-27 | P59: Não iniciada | Q59: 1 | R59: 0
A60: Alorran de Freitas Barbosa | B60: alorran.barbosa@to.sebrae.com.br | D60: UTIC-UNIDADE DE TECNOLOGIA DA INFORM. E COMUNICAÇÃO DE DADOS | I60: Ativo | J60: Leonardo Campelo Leite Guedes | K60: Macro Área: Tecnologia, Dados e Transformação Digital | L60: Competência Técnica: Análise de Dados e Visualização com Power BI Desenvolver capacidade de transformar dados em informações visuais e estratégicas por meio de ferramentas como Power BI. | M60: Potencializar | N60: 2025-05-12 | O60: 2025-08-19 | P60: Não iniciada | Q60: 1 | R60: 0
A61: Alorran de Freitas Barbosa | B61: alorran.barbosa@to.sebrae.com.br | D61: UTIC-UNIDADE DE TECNOLOGIA DA INFORM. E COMUNICAÇÃO DE DADOS | I61: Ativo | J61: Leonardo Campelo Leite Guedes | K61: Macro Área: Comunicação Relacional | L61: Competência Comportamental: Feedback Reverso Aprimorar a capacidade de escuta e autodesenvolvimento por meio da solicitação estruturada de feedback de colegas e pares. | M61: Potencializar | N61: 2025-05-12 | O61: 2025-08-12 | P61: Não iniciada | Q61: 1 | R61: 0
A62: Alorran de Freitas Barbosa | B62: alorran.barbosa@to.sebrae.com.br | D62: UTIC-UNIDADE DE TECNOLOGIA DA INFORM. E COMUNICAÇÃO DE DADOS | I62: Ativo | J62: Leonardo Campelo Leite Guedes | K62: Macro Área: Inteligência Emocional e Autoconhecimento | L62: Competência Comportamental: Inteligência Emocional e Gestão de Pressão Desenvolver equilíbrio emocional para lidar com críticas, pressão por resultados e situações de conflito no ambiente de trabalho. | M62: Potencializar | N62: 2025-05-12 | O62: 2025-12-11 | P62: Em progresso | Q62: 1 | R62: 0
A63: Alorran de Freitas Barbosa | B63: alorran.barbosa@to.sebrae.com.br | D63: UTIC-UNIDADE DE TECNOLOGIA DA INFORM. E COMUNICAÇÃO DE DADOS | I63: Ativo | J63: Leonardo Campelo Leite Guedes | K63: Macro Área: Gestão de Tempo | L63: Competência Comportamental: Gestão do Tempo Aprimorar o planejamento pessoal, controle de demandas e uso eficiente do tempo no contexto da URC. | M63: Potencializar | N63: 2025-05-12 | O63: 2025-12-11 | P63: Em progresso | Q63: 1 | R63: 0
A64: Alorran de Freitas Barbosa | B64: alorran.barbosa@to.sebrae.com.br | D64: UTIC-UNIDADE DE TECNOLOGIA DA INFORM. E COMUNICAÇÃO DE DADOS | I64: Ativo | J64: Leonardo Campelo Leite Guedes | K64: Macro Área: Planejamento, Foco e Resultados | L64: Competência Técnica: Planejamento de Ações e Prioridades Estruturar a organização do trabalho com base em metas, prioridades e entregas, promovendo clareza e eficiência na execução. | M64: Potencializar | N64: 2025-05-12 | O64: 2025-12-16 | P64: Finalizada | Q64: 1 | R64: 1
A65: Alorran de Freitas Barbosa | B65: alorran.barbosa@to.sebrae.com.br | D65: UTIC-UNIDADE DE TECNOLOGIA DA INFORM. E COMUNICAÇÃO DE DADOS | I65: Ativo | J65: Leonardo Campelo Leite Guedes | K65: Macro Área: Planejamento, Foco e Resultados | L65: Competência Técnica: Planejamento Estratégico e Gestão de Projetos Aprimorar a capacidade de estruturar ações, definir prioridades e acompanhar entregas com método e visão de resultado. | M65: Potencializar | N65: 2025-05-12 | O65: 2025-12-12 | P65: Finalizada | Q65: 1 | R65: 1
A66: Alorran de Freitas Barbosa | B66: alorran.barbosa@to.sebrae.com.br | D66: UTIC-UNIDADE DE TECNOLOGIA DA INFORM. E COMUNICAÇÃO DE DADOS | I66: Ativo | J66: Leonardo Campelo Leite Guedes | K66: Macro Área: Capacitações Específicas Para O Cargo | L66: Participação em evento de Tecnologia e Inovação: Startup Summit 2025 Prezados, venho através deste solicitar a inclusão no meu PDI, a participação no evento de Tecnologia e Inovação Startup Summit 2025 em Florianópolis - SC, nos dias 27 a 29 de Agosto de 2025, sob a seguinte justificativa abaixo: A participação no Startup Summit 2025 pelo colaborador da UTIC Alorran, representa uma oportunidade estratégica para o fortalecimento das competências técnicas e institucionais do Sebrae Tocantins nas áreas de Inovação, Inteligência Artificial e Novas Tecnologias, alinhando-se ao planejamento estratégico da UTIC e ao compromisso do Sebrae com a transformação digital e a inovação, áreas estas que o colaborador tem sob sua responsabilidade e demanda na unidade. O evento reunirá startups, empresas de tecnologia, investidores e especialistas em inovação, proporcionando acesso às tendências emergentes e soluções práticas que podem ser avaliadas para adoção em processos internos e programas de atendimento ao cliente. Além disso, será possível realizar benchmarking de iniciativas de inovação em IA, coleta de insights sobre automação de processos, ferramentas de gestão de dados e novos modelos de negócios aplicáveis ao ecossistema de micro e pequenas empresas atendidas pelo Sebrae. Objetivos da Participação: 1. Mapear soluções em Inteligência Artificial e novas tecnologias que possam ser aplicadas nos processos internos e projetos de inovação do Sebrae Tocantins. 2. Identificar tendências e práticas inovadoras que possam apoiar a evolução dos serviços digitais e a eficiência operacional no âmbito da UTIC. 3. Estabelecer conexões estratégicas com startups e instituições de referência, possibilitando futuros projetos de inovação aberta e parcerias tecnológicas. 4. Levantar dados e cases para apresentação interna visando a capacitação de outros colaboradores e disseminação de conhecimento adquirido. 5. Apoiar o Sebrae Tocantins na construção de estratégias de transformação digital, alinhando as tecnologias emergentes às necessidades dos pequenos negócios do estado. Relevância para a UTIC: • A participação fortalece a capacidade técnica do analista na curadoria e implantação de soluções inovadoras, acelerando os processos de transformação digital. • Contribui diretamente para a atualização de conhecimentos em Inteligência Artificial, área prioritária no planejamento de inovação da UTIC. • Possibilita identificar tecnologias que possam reduzir custos operacionais, aumentar a segurança da informação e agilizar o atendimento ao cliente. • Permite a multiplicação do conhecimento para outros colaboradores em reuniões e workshops internos. Diante do exposto, solicito a inclusão no meu PDI para que eu possa participar da missão técnica do Sebrae Tocantins ao Startup Summit 2025, assegurando o compromisso de elaborar relatório técnico com os principais aprendizados, contatos e oportunidades mapeadas, visando a aplicação prática no ambiente institucional. | M66: Potencializar | N66: 2025-07-29 | O66: 2025-12-12 | P66: Finalizada | Q66: 1 | R66: 1
A67: Amaggeldo Barbosa | B67: amaggeldo@to.sebrae.com.br | D67: Regional Metropolitana | I67: Ativo | K67: Macro Área: Ética, Integridade e Responsabilidade | L67: Competência Técnica: Ética e Conformidade Fortalecer a conduta ética e o alinhamento aos princípios institucionais do Sebrae. | M67: Potencializar | N67: 2025-05-19 | O67: 2025-08-27 | P67: Finalizada | Q67: 1 | R67: 1
A68: Amaggeldo Barbosa | B68: amaggeldo@to.sebrae.com.br | D68: Regional Metropolitana | I68: Ativo | K68: Macro Área: Tecnologia, Dados e Transformação Digital | L68: Competência Técnica: Digital e Tecnologia Engajamento com Plataforma de Desenvolvimento | M68: Potencializar | N68: 2025-04-09 | O68: 2025-08-11 | P68: Finalizada | Q68: 1 | R68: 1
A69: Amaggeldo Barbosa | B69: amaggeldo@to.sebrae.com.br | D69: Regional Metropolitana | I69: Ativo | K69: Macro Área: Estratégia focada em Indicadores | L69: Competência Técnica: Estratégia & Visão de Negócios Oratória e Comunicação Estratégica | M69: Potencializar | N69: 2025-04-09 | O69: 2025-12-11 | P69: Finalizada | Q69: 2 | R69: 2
A70: Amaggeldo Barbosa | B70: amaggeldo@to.sebrae.com.br | D70: Regional Metropolitana | I70: Ativo | K70: Macro Área: Estratégia focada em Indicadores | L70: Competência Comportamental: Estratégia & Visão de Negócios Planejamento com base em indicadores | M70: Potencializar | N70: 2025-04-09 | O70: 2025-08-19 | P70: Finalizada | Q70: 1 | R70: 1
A71: Amaggeldo Barbosa | B71: amaggeldo@to.sebrae.com.br | D71: Regional Metropolitana | I71: Ativo | K71: Macro Área: Atitude Inovadora com visão de futuro | L71: Competência Comportamental: Inovação & Criatividade Finanças para Pequenos Negócios | M71: Potencializar | N71: 2025-04-09 | O71: 2025-08-11 | P71: Finalizada | Q71: 1 | R71: 1
A72: Amaggeldo Barbosa | B72: amaggeldo@to.sebrae.com.br | D72: Regional Metropolitana | I72: Ativo | K72: Macro Área: Comunicação Oral | L72: Competência Comportamental: Comunicação & Relacionamento Interpessoal Preencher conforme cada ação | M72: Potencializar | N72: 2025-04-09 | O72: 2025-09-15 | P72: Finalizada | Q72: 2 | R72: 2
A73: Amanda Soares Santos | B73: amanda.santos@to.sebrae.com.br | D73: UGOC-UNIDADE DE GESTÃO ORÇ. CONTABILIDADE E FINANÇAS | I73: Ativo | J73: Andreia Rodrigues Facundes | K73: Macro Área: Estratégia focada em Indicadores | L73: Competência Técnica: Estratégia e Visão de Negócios Ampliar sua visão estratégica para conectar suas entregas às metas e resultados institucionais. | M73: Potencializar | N73: 2025-05-12 | O73: 2025-08-11 | P73: Finalizada | Q73: 1 | R73: 1
A74: Amanda Soares Santos | B74: amanda.santos@to.sebrae.com.br | D74: UGOC-UNIDADE DE GESTÃO ORÇ. CONTABILIDADE E FINANÇAS | I74: Ativo | J74: Andreia Rodrigues Facundes | K74: Macro Área: Protagonismo, Autogestão e Tomada de Decisão | L74: Competência Comportamental: Gestão e Tomada de Decisão Melhorar sua agilidade e segurança em decisões no dia a dia, mesmo sob pressão. | M74: Potencializar | N74: 2025-05-12 | O74: 2025-12-16 | P74: Finalizada | Q74: 1 | R74: 1
A75: Amanda Soares Santos | B75: amanda.santos@to.sebrae.com.br | D75: UGOC-UNIDADE DE GESTÃO ORÇ. CONTABILIDADE E FINANÇAS | I75: Ativo | J75: Andreia Rodrigues Facundes | K75: Macro Área: Visão Sistêmica com foco em Indicadores Estratégicos | L75: Competência Técnica: OKRs e Metodologias Ágeis Compreender e aplicar de forma prática conceitos de definição de metas, entregas por ciclos e adaptação contínua. | M75: Potencializar | N75: 2025-05-12 | O75: 2025-08-11 | P75: Finalizada | Q75: 1 | R75: 1
A76: Amanda Soares Santos | B76: amanda.santos@to.sebrae.com.br | D76: UGOC-UNIDADE DE GESTÃO ORÇ. CONTABILIDADE E FINANÇAS | I76: Ativo | J76: Andreia Rodrigues Facundes | K76: Macro Área: Ética, Integridade e Responsabilidade | L76: Competência Técnica: Ética e Conformidade Fortalecer a conduta ética e o alinhamento aos princípios institucionais do Sebrae. | M76: Potencializar | N76: 2025-05-19 | O76: 2025-08-27 | P76: Finalizada | Q76: 1 | R76: 1
A77: Amanda Soares Santos | B77: amanda.santos@to.sebrae.com.br | D77: UGOC-UNIDADE DE GESTÃO ORÇ. CONTABILIDADE E FINANÇAS | I77: Ativo | J77: Andreia Rodrigues Facundes | K77: Macro Área: Gestão de Tempo | L77: Competência Comportamental: Gestão de Tempo e Produtividade Aprimorar o uso do tempo com foco em entregas, reduzindo sobrecarga e melhorando a clareza sobre prioridades diárias. | M77: Potencializar | N77: 2025-05-12 | O77: 2025-08-11 | P77: Finalizada | Q77: 1 | R77: 1
A78: Amanda Soares Santos | B78: amanda.santos@to.sebrae.com.br | D78: UGOC-UNIDADE DE GESTÃO ORÇ. CONTABILIDADE E FINANÇAS | I78: Ativo | J78: Andreia Rodrigues Facundes | K78: Macro Área: Comunicação Relacional | L78: Competência Comportamental: Comunicação Fortalecer sua clareza, objetividade e confiança nas trocas profissionais e interações com pares e gestores. | M78: Potencializar | N78: 2025-05-12 | O78: 2025-08-12 | P78: Finalizada | Q78: 1 | R78: 1
A79: Amanda Soares Santos | B79: amanda.santos@to.sebrae.com.br | D79: UGOC-UNIDADE DE GESTÃO ORÇ. CONTABILIDADE E FINANÇAS | I79: Ativo | J79: Andreia Rodrigues Facundes | K79: Macro Área: Protagonismo, Autogestão e Tomada de Decisão | L79: Competência Comportamental: Desenvolvimento Pessoal e Autoconfiança Reforçar sua autoconfiança e segurança interna para lidar com críticas, erros e exposições. | M79: Potencializar | N79: 2025-05-12 | O79: 2025-12-19 | P79: Finalizada | Q79: 1 | R79: 1
A80: Amanda Soares Santos | B80: amanda.santos@to.sebrae.com.br | D80: UGOC-UNIDADE DE GESTÃO ORÇ. CONTABILIDADE E FINANÇAS | I80: Ativo | J80: Andreia Rodrigues Facundes | K80: Macro Área: Planejamento, Foco e Resultados | L80: Competência Comportamental: Organização e Produtividade Aprimorar sua capacidade de planejamento e organização de tarefas para lidar melhor com prazos e demandas. | M80: Potencializar | N80: 2025-05-12 | O80: 2025-08-11 | P80: Finalizada | Q80: 1 | R80: 1
A81: Amanda Soares Santos | B81: amanda.santos@to.sebrae.com.br | D81: UGOC-UNIDADE DE GESTÃO ORÇ. CONTABILIDADE E FINANÇAS | I81: Ativo | J81: Andreia Rodrigues Facundes | K81: Macro Área: Inteligência Emocional e Autoconhecimento | L81: Competência Comportamental: Inteligência Emocional & Autogestão Desenvolver mais equilíbrio emocional no trabalho e fortalecer sua autoconfiança diante de desafios. | M81: Potencializar | N81: 2025-05-12 | O81: 2025-11-28 | P81: Finalizada | Q81: 1 | R81: 1
A82: Amanda Soares Santos | B82: amanda.santos@to.sebrae.com.br | D82: UGOC-UNIDADE DE GESTÃO ORÇ. CONTABILIDADE E FINANÇAS | I82: Ativo | J82: Andreia Rodrigues Facundes | K82: Macro Área: Gestão do Conhecimento e Documentação Institucional | L82: Competência Técnica: Conhecimento Técnico Fortalecer sua base de conhecimentos práticos e teóricos aplicáveis à sua área de atuação contábil e orçamentária. | M82: Potencializar | N82: 2025-05-12 | O82: 2025-10-09 | P82: Finalizada | Q82: 1 | R82: 1
A83: Amanda Soares Santos | B83: amanda.santos@to.sebrae.com.br | D83: UGOC-UNIDADE DE GESTÃO ORÇ. CONTABILIDADE E FINANÇAS | I83: Ativo | J83: Andreia Rodrigues Facundes | K83: Macro Área: Inovação, Criatividade e Visão Estratégica | L83: Competência Comportamental: Aprendizado com Erros e Melhoria Contínua Desenvolver uma atitude mais leve e construtiva diante dos erros e aprendizados do cotidiano. | M83: Potencializar | N83: 2025-05-12 | O83: 2025-12-17 | P83: Finalizada | Q83: 1 | R83: 1
A84: Ana Cassia de Oliveira Costa | B84: ana.costa@to.sebrae.com.br | D84: UMC-UNIDADE DE MARKETING E COMUNICAÇÃO | I84: Ativo | J84: Nemias Gomes | K84: Macro Área: Ética, Integridade e Responsabilidade | L84: Competência Técnica: Ética e Conformidade Fortalecer a conduta ética e o alinhamento aos princípios institucionais do Sebrae. | M84: Potencializar | N84: 2025-05-19 | O84: 2025-08-27 | P84: Finalizada | Q84: 1 | R84: 1
... A91: Ana Cassia de Oliveira Costa | B91: ana.costa@to.sebrae.com.br | D91: UMC-UNIDADE DE MARKETING E COMUNICAÇÃO | I91: Ativo | J91: Nemias Gomes | K91: Macro Área: Atitude Inovadora com visão de futuro | L91: Competência Técnica: Inovação Aplicada à Experiência em Eventos Capacidade de incorporar novas tecnologias, formatos e soluções criativas para elevar a qualidade e o impacto da experiência dos públicos em eventos institucionais. | M91: Potencializar | N91: 2025-05-15 | O91: 2025-12-08 | P91: Finalizada | Q91: 2 | R91: 2
A92: Ana Estela Goetten | B92: ana.goetten@to.sebrae.com.br | D92: Regional Metropolitana | I92: Ativo | J92: Amaggeldo Barbosa | K92: PDI - Onboarding (Competências Comportamentais) | M92: Potencializar | N92: 2025-06-18 | O92: 2025-10-03 | P92: Finalizada | Q92: 8 | R92: 8
A93: Ana Estela Goetten | B93: ana.goetten@to.sebrae.com.br | D93: Regional Metropolitana | I93: Ativo | J93: Amaggeldo Barbosa | K93: PDI - Demandas do Mercado e Função | M93: Desenvolver | N93: 2025-11-27 | O93: 2025-12-03 | P93: Finalizada | Q93: 2 | R93: 2
A94: Ana Estela Goetten | B94: ana.goetten@to.sebrae.com.br | D94: Regional Metropolitana | I94: Ativo | J94: Amaggeldo Barbosa | K94: PDI - Onboarding (Tarefas da sua Gestão) | M94: Desenvolver | N94: 2025-06-18 | O94: 2025-09-30 | P94: Finalizada | Q94: 4 | R94: 4
A95: Ana Flávia Mendes Borges | B95: ana.borges@to.sebrae.com.br | D95: UAC-UNIDADE DE ARTICULAÇÃO E COMPETITIVIDADE | I95: Ativo | J95: Bruno Martins Vieira | K95: Macro Área: Ética, Integridade e Responsabilidade | L95: Competência Técnica: Ética e Conformidade Fortalecer a conduta ética e o alinhamento aos princípios institucionais do Sebrae. | M95: Potencializar | N95: 2025-05-19 | O95: 2025-09-02 | P95: Finalizada | Q95: 2 | R95: 2
A96: Ana Flávia Mendes Borges | B96: ana.borges@to.sebrae.com.br | D96: UAC-UNIDADE DE ARTICULAÇÃO E COMPETITIVIDADE | I96: Ativo | J96: Bruno Martins Vieira | K96: Macro Área: Gestão de Tempo | L96: Competência Comportamental: Gestão do Tempo Capacidade de organizar e priorizar atividades para maximizar a produtividade e o equilíbrio. Gap identificado no Questionário como 'Falta de tempo para realizar todas as atividades necessárias'. | M96: Potencializar | N96: 2025-05-25 | O96: 2025-09-11 | P96: Finalizada | Q96: 1 | R96: 1
A97: Ana Flávia Mendes Borges | B97: ana.borges@to.sebrae.com.br | D97: UAC-UNIDADE DE ARTICULAÇÃO E COMPETITIVIDADE | I97: Ativo | J97: Bruno Martins Vieira | K97: Macro Área: Ética, Integridade e Responsabilidade | L97: Competência Técnica: Integração entre Unidades Capacidade de promover colaboração e sinergia entre diferentes áreas e equipes. Gap identificado no Questionário como 'Resistência a integração e o trabalho dinâmico entre as unidades'. | M97: Potencializar | N97: 2025-05-25 | O97: 2025-09-23 | P97: Finalizada | Q97: 1 | R97: 1
A98: Ana Flávia Mendes Borges | B98: ana.borges@to.sebrae.com.br | D98: UAC-UNIDADE DE ARTICULAÇÃO E COMPETITIVIDADE | I98: Ativo | J98: Bruno Martins Vieira | K98: Macro Área: Comunicação Estratégica e Influente | L98: Competência Comportamental: Comunicação Eficaz Partilha seletivamente informações, ideias e sentimentos de forma clara, objetiva e oportuna, verificando a compreensão das mensagens transmitidas e recebidas. Gap identificado no Questionário como 'Comunicação ineficaz entre equipes ou setores'. | M98: Potencializar | N98: 2025-05-25 | O98: 2025-09-17 | P98: Finalizada | Q98: 1 | R98: 1
A99: Ana Flávia Mendes Borges | B99: ana.borges@to.sebrae.com.br | D99: UAC-UNIDADE DE ARTICULAÇÃO E COMPETITIVIDADE | I99: Ativo | J99: Bruno Martins Vieira | K99: Macro Área: Atitude Inovadora com visão de futuro | L99: Competência Comportamental: Olhar Empreendedor Olhar sistêmico para identificar oportunidades e propor soluções inovadoras. Competência mencionada no Questionário como tema que não poderia faltar em um programa de desenvolvimento. | M99: Potencializar | N99: 2025-05-25 | O99: 2025-09-21 | P99: Finalizada | Q99: 1 | R99: 1
A100: Ana Maria Leal Cunha de Freitas | B100: ana.freitas@to.sebrae.com.br | D100: Regional Médio Norte Colinas | I100: Ativo | J100: Aldeni Batista Torres | K100: Macro Área: Comunicação Relacional | L100: Competência Técnica: Comunicação e Relacionamento Capacidade de se comunicar, interagir e colaborar com outras pessoas de forma eficaz. Ajuda a construir relacionamentos, resolver conflitos e fortalecer a influência. | M100: Potencializar | N100: 2025-03-24 | O100: 2025-08-25 | P100: Finalizada | Q100: 1 | R100: 1
A101: Ana Maria Leal Cunha de Freitas | B101: ana.freitas@to.sebrae.com.br | D101: Regional Médio Norte Colinas | I101: Ativo | J101: Aldeni Batista Torres | K101: Macro Área: Vendas, Negociação e Soluções Comerciais - Tema 2 | L101: Competência Técnica: Técnicas de Vendas Consultivas - Tema 2 Desenvolver competências específicas relacionadas ao processo de venda consultiva, incluindo abordagem, qualificação, follow-up, fechamento e relacionamento com o cliente. | M101: Potencializar | N101: 2025-05-19 | O101: 2025-08-27 | P101: Finalizada | Q101: 1 | R101: 1
A102: Ana Maria Leal Cunha de Freitas | B102: ana.freitas@to.sebrae.com.br | D102: Regional Médio Norte Colinas | I102: Ativo | J102: Aldeni Batista Torres | K102: Macro Área: Vendas, Negociação e Soluções Comerciais - Tema 4 | L102: Competência Técnica: Técnicas de Vendas Consultivas - Tema 4 Desenvolver competências específicas relacionadas ao processo de venda consultiva, incluindo abordagem, qualificação, follow-up, fechamento e relacionamento com o cliente. | M102: Potencializar | N102: 2025-05-19 | O102: 2025-08-27 | P102: Finalizada | Q102: 1 | R102: 1
A103: Ana Maria Leal Cunha de Freitas | B103: ana.freitas@to.sebrae.com.br | D103: Regional Médio Norte Colinas | I103: Ativo | J103: Aldeni Batista Torres | K103: Macro Área: Capacitações Específicas para o Cargo | L103: Competência Comportamental: Leitura e Consumo de Conteúdo Inspirador Capacidade de se comunicar, interagir e colaborar com outras pessoas de forma eficaz. Ajuda a construir relacionamentos, resolver conflitos e fortalecer a influência. | M103: Potencializar | N103: 2025-03-24 | O103: 2025-08-28 | P103: Finalizada | Q103: 1 | R103: 1
A104: Ana Maria Leal Cunha de Freitas | B104: ana.freitas@to.sebrae.com.br | D104: Regional Médio Norte Colinas | I104: Ativo | J104: Aldeni Batista Torres | K104: Macro Área: Gestão de Projetos e Processos | L104: Competência Técnica: Gestão de Projetos e Processos Aprimoramento de conhecimentos específicos e ferramentas técnicas para otimizar a performance em funções estratégicas. | M104: Potencializar | N104: 2025-03-24 | O104: 2025-12-16 | P104: Finalizada | Q104: 1 | R104: 1
A105: Ana Maria Leal Cunha de Freitas | B105: ana.freitas@to.sebrae.com.br | D105: Regional Médio Norte Colinas | I105: Ativo | J105: Aldeni Batista Torres | K105: Macro Área: Ética, Integridade e Responsabilidade | L105: Competência Técnica: Ética e Conformidade Fortalecer a conduta ética e o alinhamento aos princípios institucionais do Sebrae. | M105: Potencializar | N105: 2025-05-19 | O105: 2025-08-28 | P105: Finalizada | Q105: 1 | R105: 1
A106: Ana Maria Leal Cunha de Freitas | B106: ana.freitas@to.sebrae.com.br | D106: Regional Médio Norte Colinas | I106: Ativo | J106: Aldeni Batista Torres | K106: Macro Área: Gestão de Tempo | L106: Competência Comportamental: Gestão de Tempo e Produtividade Habilidades relacionadas à produtividade, gestão do tempo e eficiência no trabalho. Essencial para melhorar a performance individual. | M106: Potencializar | N106: 2025-03-24 | O106: 2025-08-12 | P106: Finalizada | Q106: 1 | R106: 1
A107: Ana Maria Leal Cunha de Freitas | B107: ana.freitas@to.sebrae.com.br | D107: Regional Médio Norte Colinas | I107: Ativo | J107: Aldeni Batista Torres | K107: Macro Área: Vendas, Negociação e Soluções Comerciais - Tema 1 | L107: Competência Técnica: Técnicas de Vendas Consultivas - Tema 1 Desenvolver competências específicas relacionadas ao processo de venda consultiva, incluindo abordagem, qualificação, follow-up, fechamento e relacionamento com o cliente. | M107: Potencializar | N107: 2025-05-19 | O107: 2025-08-27 | P107: Finalizada | Q107: 1 | R107: 1
A108: Ana Maria Leal Cunha de Freitas | B108: ana.freitas@to.sebrae.com.br | D108: Regional Médio Norte Colinas | I108: Ativo | J108: Aldeni Batista Torres | K108: PDI - Crossboarding | M108: Potencializar | N108: 2025-04-10 | O108: 2025-06-05 | P108: Finalizada | Q108: 1 | R108: 1
A109: Ana Maria Leal Cunha de Freitas | B109: ana.freitas@to.sebrae.com.br | D109: Regional Médio Norte Colinas | I109: Ativo | J109: Aldeni Batista Torres | K109: Macro Área: Vendas, Negociação e Soluções Comerciais - Tema 3 | L109: Competência Técnica: Técnicas de Vendas Consultivas - Tema 3 Desenvolver competências específicas relacionadas ao processo de venda consultiva, incluindo abordagem, qualificação, follow-up, fechamento e relacionamento com o cliente. | M109: Potencializar | N109: 2025-05-19 | O109: 2025-08-27 | P109: Finalizada | Q109: 1 | R109: 1
A110: Ana Maria Leal Cunha de Freitas | B110: ana.freitas@to.sebrae.com.br | D110: Regional Médio Norte Colinas | I110: Ativo | J110: Aldeni Batista Torres | K110: Macro Área: Finanças, Orçamento e Contabilidade Pública | L110: Competência Técnica: Gestão Financeira e Orçamentária Aprimoramento de conhecimentos específicos e ferramentas técnicas para otimizar a performance em funções estratégicas. | M110: Potencializar | N110: 2025-03-24 | O110: 2025-12-17 | P110: Finalizada | Q110: 2 | R110: 2
A111: Ana Maria Leal Cunha de Freitas | B111: ana.freitas@to.sebrae.com.br | D111: Regional Médio Norte Colinas | I111: Ativo | J111: Aldeni Batista Torres | K111: Macro Área: Tomada de Decisão com Análise de Dados | L111: Competência Técnica: Análise de Dados e Tomada de Decisão Capacidade de analisar cenários, tomar decisões e estabelecer conexões estratégicas para melhorar o impacto organizacional. | M111: Potencializar | N111: 2025-03-24 | O111: 2025-12-16 | P111: Finalizada | Q111: 2 | R111: 2
A112: Ana Maria Leal Cunha de Freitas | B112: ana.freitas@to.sebrae.com.br | D112: Regional Médio Norte Colinas | I112: Ativo | J112: Aldeni Batista Torres | K112: Macro Área: Atitude Inovadora com visão de futuro | L112: Competência Técnica: Tecnologia e Inovação Exploração de novas tecnologias e ferramentas digitais para modernizar processos e aumentar a competitividade.Competência Técnica: Tecnologia e Inovação | M112: Potencializar | N112: 2025-03-24 | O112: 2025-12-17 | P112: Finalizada | Q112: 4 | R112: 4
A113: Ana Paula Alves de Lima Rocha | B113: anapaula.lima@to.sebrae.com.br | D113: UTIC-UNIDADE DE TECNOLOGIA DA INFORM. E COMUNICAÇÃO DE DADOS | I113: Ativo | J113: Leonardo Campelo Leite Guedes | K113: EMBASAMENTO DAS AÇÕES DO PDI - Clique neste botão e depois abra a aba: Detalhamento. | L113: Carta de Apresentação – Plano de Desenvolvimento Individual (PDI) Colaboradora: Ana Paula Alves de Lima Rocha Prezada Ana Paula, Com base na análise integrada da sua Avaliação de Desempenho , perfil DISC , respostas ao questionário individual e histórico de atuação, elaboramos seu novo Plano de Desenvolvimento Individual (PDI), respeitando suas preferências, desafios identificados e interesses de crescimento. Foram identificadas 16 áreas de desenvolvimento que contemplam tanto competências comportamentais quanto competências técnicas , conforme as diretrizes do Programa EVOLUIR. A construção do plano respeitou a regra de proporcionalidade: 60% das ações foram direcionadas a gaps de desempenho ou perfil identificados nos instrumentos analisados; 40% das ações foram propostas com base em interesses pessoais, potencialidades e áreas que você deseja fortalecer . As áreas trabalhadas foram: COMPORTAMENTAL: Tomada de Decisão Estratégica e com Discernimento COMPORTAMENTAL: Disciplina e Autodireção COMPORTAMENTAL: Exatidão e Detalhamento COMPORTAMENTAL: Planejamento e Organização Pessoal TÉCNICA: Capacidade Analítica e Interpretação de Dados Técnicos COMPORTAMENTAL: Comunicação Estratégica e Posicionamento Técnico COMPORTAMENTAL: Visibilidade e Valorização das Entregas Técnicas TÉCNICA: Domínio sobre Sistemas e Processos Internos COMPORTAMENTAL: Inteligência Emocional em Ambientes de Pressão TÉCNICA: Aplicação de Ferramentas de Gestão para Apoio à Decisão COMPORTAMENTAL: Protagonismo Colaborativo e Iniciativa Institucional TÉCNICA: Inovação com Base em Tecnologia e Automação COMPORTAMENTAL: Gestão do Tempo COMPORTAMENTAL: Inteligência Emocional TÉCNICA: OKRs e Metodologias Ágeis TÉCNICA: Mapeamento de Processos Cada linha do plano foi construída com duas sugestões de ação: Ação 1 (principal) : pensada como prioritária, de aplicação direta e estruturada; Ação 2 (alternativa) : uma sugestão opcional que atende à mesma área de desenvolvimento, permitindo a escolha entre uma ou ambas, de acordo com sua preferência e disponibilidade. As ações são diversas, aplicáveis e contextualizadas à sua realidade na UTIC. Incluem cursos, desafios práticos, elaboração de materiais, análise de casos, propostas de melhoria, mapeamentos e simulações. Todos os conteúdos estão acompanhados de: Passo a passo detalhado de como realizar a ação Materiais de apoio (cursos, vídeos, artigos, livros) Instruções claras de como comprovar a realização e validar com sua liderança. Orientações para execução do PDI : Assista ao vídeo orientador enviado com este material. Leia todas as ações com atenção e selecione aquelas que mais fizerem sentido para você neste momento . Negocie os prazos com sua liderança e adapte a execução conforme sua rotina. Lembre-se: não é necessário realizar todas as ações de uma só vez . O plano foi desenhado para ser vivido ao longo de todo o ano. Se desejar realizar tanto a ação 1 quanto a ação 2 em algumas áreas, isso representará um ganho ainda maior para seu desenvolvimento. Caso alguma proposta não faça sentido para sua realidade, você pode ajustar com seu gestor ou sugerir alternativas . O PDI é uma ferramenta poderosa de aprendizado, visibilidade e protagonismo. Aproveite cada ação como uma oportunidade para crescer, fortalecer sua atuação técnica e gerar ainda mais valor para sua equipe e para o Sebrae TO. Atenciosamente, Equipe de Desenvolvimento de Pessoas – Sebrae TO Programa EVOLUIR | M113: Desenvolver | N113: 2025-05-16 | O113: 2025-05-16 | P113: Não iniciada | Q113: 0 | R113: 0
A114: Ana Paula Alves de Lima Rocha | B114: anapaula.lima@to.sebrae.com.br | D114: UTIC-UNIDADE DE TECNOLOGIA DA INFORM. E COMUNICAÇÃO DE DADOS | I114: Ativo | J114: Leonardo Campelo Leite Guedes | K114: Macro Área: Inteligência Emocional e Autoconhecimento | L114: Competência Comportamental: Disciplina e Autodireção Capacidade de manter foco constante, cumprir prazos de forma independente, executar tarefas com constância, mesmo sem reforço externo, e finalizar entregas com qualidade e organização. | M114: Potencializar | N114: 2025-05-15 | O114: 2025-09-03 | P114: Finalizada | Q114: 1 | R114: 1
A115: Ana Paula Alves Santos | B115: paula.alves@to.sebrae.com.br | D115: UAS-UNIDADE DE ADMINISTRAÇÃO E SUPRIMENTOS | H115: ANA PAULA ALVES SANTOS | I115: Ativo | K115: Macro Área: Inteligência Emocional e Autoconhecimento | L115: Competência Comportamental: Inteligência Emocional e Autogestão Desenvolver habilidades de autoconhecimento, controle emocional e empatia no ambiente profissional, promovendo maior equilíbrio e foco nas entregas. Gap identificado na avaliação comportamental e feedback institucional. | M115: Potencializar | N115: 2025-05-29 | O115: 2025-10-03 | P115: Finalizada | Q115: 1 | R115: 1
A116: Ana Paula Alves Santos | B116: paula.alves@to.sebrae.com.br | D116: UAS-UNIDADE DE ADMINISTRAÇÃO E SUPRIMENTOS | H116: ANA PAULA ALVES SANTOS | I116: Ativo | K116: Macro Área: Inovação, Criatividade e Visão Estratégica | L116: Competência Comportamental: Gestão de Mudanças Desenvolver habilidades para liderar e adaptar-se eficazmente a mudanças organizacionais, promovendo uma cultura de inovação e melhoria contínua. Gap identificado na avaliação de competências comportamentais. | M116: Potencializar | N116: 2025-05-29 | O116: 2025-10-03 | P116: Finalizada | Q116: 1 | R116: 1
A117: Ana Paula Alves Santos | B117: paula.alves@to.sebrae.com.br | D117: UAS-UNIDADE DE ADMINISTRAÇÃO E SUPRIMENTOS | H117: ANA PAULA ALVES SANTOS | I117: Ativo | K117: Macro Área: Ética, Integridade e Responsabilidade | L117: Competência Técnica: Ética e Conformidade Fortalecer a conduta ética e o alinhamento aos princípios institucionais do Sebrae. | M117: Potencializar | N117: 2025-05-19 | O117: 2025-10-03 | P117: Finalizada | Q117: 1 | R117: 1
A118: Ana Paula Alves Santos | B118: paula.alves@to.sebrae.com.br | D118: UAS-UNIDADE DE ADMINISTRAÇÃO E SUPRIMENTOS | H118: ANA PAULA ALVES SANTOS | I118: Ativo | K118: Macro Área: Gestão de Equipes | L118: Competência Comportamental: Liderança de Equipe Desenvolver habilidades de liderança para conduzir equipes de forma eficaz, promovendo um ambiente colaborativo e orientado para resultados. Gap identificado na avaliação de competências e feedbacks recebidos. | M118: Potencializar | N118: 2025-05-29 | O118: 2025-12-11 | P118: Finalizada | Q118: 1 | R118: 1
A119: Ana Paula Carvalho Desconsi | B119: anapaula.desconsi@to.sebrae.com.br | D119: Regional Bico do Papagaio | I119: Ativo | J119: Edvaldo Pereira Lima Júnior | K119: PDI - Onboarding (Tarefas da sua Gestão) | M119: Desenvolver | N119: 2025-11-19 | O119: 2025-12-12 | P119: Finalizada | Q119: 4 | R119: 4
A120: Ana Paula Carvalho Desconsi | B120: anapaula.desconsi@to.sebrae.com.br | D120: Regional Bico do Papagaio | I120: Ativo | J120: Edvaldo Pereira Lima Júnior | K120: Marcro Área: Mentalidade Empreendedora e Atitude Protagonista | M120: Desenvolver | N120: 2025-12-19 | O120: 2025-12-19 | P120: Finalizada | Q120: 1 | R120: 1
A121: Ana Paula Carvalho Desconsi | B121: anapaula.desconsi@to.sebrae.com.br | D121: Regional Bico do Papagaio | I121: Ativo | J121: Edvaldo Pereira Lima Júnior | K121: PDI - Onboarding (Competências Comportamentais) | M121: Desenvolver | N121: 2025-11-19 | O121: 2025-12-16 | P121: Finalizada | Q121: 3 | R121: 3
A122: Ana Paula Cunha Soares | B122: paula.soares@to.sebrae.com.br | D122: UAS-UNIDADE DE ADMINISTRAÇÃO E SUPRIMENTOS | I122: Ativo | J122: Ana Paula Alves Santos | K122: Macro Área: Presença Executiva | L122: Competência Comportamental: Proatividade e Protagonismo | M122: Potencializar | N122: 2025-08-01 | O122: 2025-08-11 | P122: Finalizada | Q122: 1 | R122: 1
A123: Ana Paula Cunha Soares | B123: paula.soares@to.sebrae.com.br | D123: UAS-UNIDADE DE ADMINISTRAÇÃO E SUPRIMENTOS | I123: Ativo | J123: Ana Paula Alves Santos | K123: Macro Área: Planejamento, Foco e Resultados | L123: Competência Técnica: Processos e Qualidade Desenvolve habilidades para mapear e melhorar fluxos de trabalho, identificar gargalos e padronizar atividades. | M123: Potencializar | N123: 2025-05-26 | O123: 2025-11-13 | P123: Finalizada | Q123: 1 | R123: 1
A124: Ana Paula Cunha Soares | B124: paula.soares@to.sebrae.com.br | D124: UAS-UNIDADE DE ADMINISTRAÇÃO E SUPRIMENTOS | I124: Ativo | J124: Ana Paula Alves Santos | K124: Macro Área: Compras, Facilities e Gestão Contratual | L124: Competência Técnica: Gestão de Contratos e Conformidade Aprimora conhecimentos sobre legislação e práticas de gestão contratual, fortalecendo a prevenção de riscos. | M124: Potencializar | N124: 2025-05-26 | O124: 2025-08-11 | P124: Finalizada | Q124: 1 | R124: 1
A125: Ana Paula Cunha Soares | B125: paula.soares@to.sebrae.com.br | D125: UAS-UNIDADE DE ADMINISTRAÇÃO E SUPRIMENTOS | I125: Ativo | J125: Ana Paula Alves Santos | K125: Macro Área: Comunicação Essencial | L125: Competência Comportamental: Comunicação Assertiva Desenvolve a expressão clara de opiniões com respeito e objetividade, reduzindo ruídos e hesitações ao se posicionar. | M125: Potencializar | N125: 2025-05-26 | O125: 2025-08-12 | P125: Finalizada | Q125: 1 | R125: 1
A126: Ana Paula Cunha Soares | B126: paula.soares@to.sebrae.com.br | D126: UAS-UNIDADE DE ADMINISTRAÇÃO E SUPRIMENTOS | I126: Ativo | J126: Ana Paula Alves Santos | K126: Competência Técnica: Ética e Integridade | L126: Garante condutas baseadas em princípios morais e responsabilidade profissional no trato com documentos e pessoas. | M126: Potencializar | N126: 2025-05-26 | O126: 2025-10-31 | P126: Finalizada | Q126: 1 | R126: 1
...

Sheet Ações Finalizadas
A1: Nome | B1: Email | C1: Times | D1: status | E1: Líder | F1: Área de desenvolvimento | G1: Padronização | H1: Descrição | I1: Categoria | J1: Ação | K1: Descrição | L1: Categoria | M1: Data de entrega (yyyy-mm-dd) | N1: Concluído em (yyyy-mm-dd) | O1: Todas as MacroÁreas
A2: Ana Maria Leal Cunha de Freitas | B2: ana.freitas@to.sebrae.com.br | C2: Regional Médio Norte Colinas | D2: Ativo | E2: Aldeni Batista Torres | F2: Macro Área: Ética, Integridade e Responsabilidade | G2: Macro Área: Ética, Integridade e Responsabilidade | H2: Competência Técnica: Ética e Conformidade Fortalecer a conduta ética e o alinhamento aos princípios institucionais do Sebrae. | I2: Potencializar | J2: AÇÃO: Concluir o Programa de Integridade – UC Sebrae | K2: SEGUE A AÇÃO: A ação foi indicada para o seu desenvolvimento e que entendemos podem lhe ajudar neste desafio de aprimorar suas competências. Caso deseje propor outra ação diferente desta opção, converse com sua liderança e registre a opção alternativa nos comentários para que possamos incluí-la no seu plano. Não há necessidade de apagar a que já consta — qualquer uma que concluir será considerada como AÇÃO REALIZADA. AÇÃO – Concluir o curso “Programa de Integridade” do Sistema Sebrae JUSTIFICATIVA: Esta ação integra o Programa de Integridade do Sistema Sebrae e é essencial para o fortalecimento da cultura organizacional baseada em ética e responsabilidade. A realização do curso é obrigatória para todos os colaboradores, garantindo alinhamento às diretrizes institucionais e promovendo práticas transparentes e responsáveis no ambiente de trabalho. COMO REALIZAR A AÇÃO: Acesse a Plataforma UC Sebrae. Pesquise pelo curso “Programa de Integridade”. Conclua todos os módulos obrigatórios. Reflita sobre os conteúdos apresentados e registre suas percepções quanto à aplicação prática no dia a dia profissional. ONDE FAZER: Plataforma UC Sebrae (pesquisar por: Programa de Integridade) Estas são apenas sugestões — a escolha deve ser alinhada com sua liderança. MATERIAL DE APOIO: Curso completo: Programa de Integridade – UC Sebrae Materiais complementares disponíveis na plataforma Documentos institucionais sobre ética, conduta profissional e integridade Pesquise por materiais ou cursos adicionais que reforcem a compreensão sobre compliance e cultura ética, preferencialmente na Universidade Sebrae e Degreed COMO COMPROVAR: Certificado de conclusão emitido pela Plataforma UC Sebrae Validação da liderança, se necessário, conforme os procedimentos internos | L2: Treinamento e estudo | M2: 2025-09-18 | N2: 2025-08-28 | O2: Ética, Integridade e Responsabilidade, Atitude Inovadora com Visão de Futuro, Finanças, Orçamento e Contabilidade Pública, Gestão de Projetos e Processos, Gestão de Tempo, Protagonismo, Autogestão e Tomada de Decisão, Vendas, Negociação e Soluções Comerciais, Competências Técnicas da Área, Comunicação, Desenvolvimento Programa Integração
A3: Clarice da Rosa Correa Soares | B3: clarice@to.sebrae.com.br | C3: Regional Metropolitana | D3: Ativo | E3: Amaggeldo Barbosa | F3: Macro Área: Ética, Integridade e Responsabilidade | G3: Macro Área: Ética, Integridade e Responsabilidade | H3: Competência Técnica: Ética e Conformidade Fortalecer a conduta ética e o alinhamento aos princípios institucionais do Sebrae. | I3: Potencializar | J3: Concluir o Programa de Integridade – UC Sebrae | K3: JUSTIFICATIVA: Esta ação faz parte do Programa de Integridade do Sistema Sebrae e é fundamental para o fortalecimento da cultura organizacional baseada em ética e responsabilidade . A realização do curso é obrigatória para todos os colaboradores . COMO REALIZAR A AÇÃO: Acesse a Plataforma UC Sebrae , localize o curso “Programa de Integridade” e conclua todos os módulos obrigatórios . Durante o curso, reflita sobre os conteúdos e registre suas percepções . ONDE FAZER: Plataforma UC Sebrae COMO COMPROVAR: Certificado de conclusão ou captura da tela com o curso finalizado (print) . | L3: Treinamento e estudo | M3: 2025-05-20 | N3: 2025-10-08 | O3: Ética, Integridade e Responsabilidade, Vendas, Negociação e Soluções Comerciais
A4: Eligeneth Resplandes Pimentel Gomes | B4: eligeneth@to.sebrae.com.br | C4: Regional Metropolitana | D4: Ativo | E4: Amaggeldo Barbosa | F4: Macro Área: Ética, Integridade e Responsabilidade | G4: Macro Área: Ética, Integridade e Responsabilidade | H4: Competência Técnica: Ética e Conformidade Fortalecer a conduta ética e o alinhamento aos princípios institucionais do Sebrae. | I4: Potencializar | J4: Concluir o Programa de Integridade – UC Sebrae | K4: Título da Ação: Curso "Programa de Integridade" – UC Sebrae Justificativa: Esta ação integra o Programa de Integridade do Sistema Sebrae e é essencial para o fortalecimento da cultura organizacional baseada em ética e responsabilidade. É exigida a realização do curso por todos os colaboradores . Como Realizar a Ação: Acesse a Plataforma UC Sebrae , localize o curso "Programa de Integridade" e conclua todos os módulos obrigatórios. Reflita sobre os conteúdos e registre suas percepções. Onde Fazer: Plataforma UC Sebrae (pesquisar por: Programa de Integridade ). Como Comprovar: Certificado de conclusão emitido pela plataforma. | L4: Treinamento e estudo | M4: 2025-12-15 | N4: 2025-08-15 | O4: Ética, Integridade e Responsabilidade, Inteligência Emocional e Autoconhecimento, Planejamento, Foco e Resultados, Vendas, Negociação e Soluções Comerciais, Comunicação
A5: Raquel Montelo Moura Carvalho | B5: raquel.carvalho@to.sebrae.com.br | C5: URC - UNIDADE DE RELACIONAMENTO COM O CLIENTE | D5: Ativo | E5: Emerson Montenegro Lima | F5: Macro Área: Ética, Integridade e Responsabilidade | G5: Macro Área: Ética, Integridade e Responsabilidade | H5: Competência Técnica: Ética e Conformidade Fortalecer a conduta ética e o alinhamento aos princípios institucionais do Sebrae. | I5: Potencializar | J5: Concluir o Programa de Integridade – UC Sebrae | K5: JUSTIFICATIVA: Esta ação integra o Programa de Integridade do Sistema Sebrae e é essencial para o fortalecimento da cultura organizacional baseada em ética e responsabilidade. É exigida a realização do curso por todos os colaboradores. COMO REALIZAR A AÇÃO: Acesse a Plataforma UC Sebrae, localize o curso "Programa de Integridade" e conclua todos os módulos obrigatórios. Reflita sobre os conteúdos e registre suas percepções. ONDE FAZER: Plataforma UC Sebrae (pesquisar por: Programa de Integridade) COMO COMPROVAR: Certificado de conclusão emitido pela plataforma. | L5: Treinamento e estudo | M5: 2025-12-02 | N5: 2025-12-03 | O5: Ética, Integridade e Responsabilidade, Atendimento e Relacionamento com o Cliente, Atitude Inovadora com Visão de Futuro, Conhecimentos Práticos e Acadêmicos em Marketing, Gestão de Tempo
A6: Deilane Rodrigues Vieira | B6: deilane.vieira@to.sebrae.com.br | C6: Regional Norte | D6: Ativo | E6: Marcus Vinicius Vieira Queiroz | F6: Macro Área: Ética, Integridade e Responsabilidade | G6: Macro Área: Ética, Integridade e Responsabilidade | H6: Competência Técnica: Ética e Conformidade Fortalecer a conduta ética e o alinhamento aos princípios institucionais do Sebrae. | I6: Potencializar | J6: Concluir o Programa de Integridade – UC Sebrae | K6: JUSTIFICATIVA Esta ação integra o Programa de Integridade do Sistema Sebrae e é essencial para o fortalecimento de uma cultura organizacional pautada na ética, transparência e responsabilidade . A realização do curso é obrigatória para todos os colaboradores , contribuindo para o alinhamento institucional e a consolidação de práticas éticas no dia a dia. COMO REALIZAR A AÇÃO Acesse a Plataforma UC Sebrae ; Localize o curso "Programa de Integridade" por meio da busca; Conclua todos os módulos obrigatórios do curso; Reflita sobre os conteúdos abordados e registre suas percepções , conforme orientações internas (se aplicável). ONDE FAZER Na Plataforma UC Sebrae (pesquisar por: Programa de Integridade ). COMO COMPROVAR Certificado de conclusão emitido diretamente pela plataforma após a finalização do curso. | L6: Treinamento e estudo | M6: 2025-07-31 | N6: 2025-07-07 | O6: Ética, Integridade e Responsabilidade, Atitude Inovadora com Visão de Futuro, Gestão do Conhecimento e Documentação Institucional, Inteligência Emocional e Autoconhecimento, Liderança e Gestão de Pessoas, Planejamento, Foco e Resultados, Vendas, Negociação e Soluções Comerciais, Comunicação
A7: Emerson Montenegro Lima | B7: emerson.lima@to.sebrae.com.br | C7: URC - UNIDADE DE RELACIONAMENTO COM O CLIENTE | D7: Ativo | F7: Macro Área: Ética, Integridade e Responsabilidade | G7: Macro Área: Ética, Integridade e Responsabilidade | H7: Competência Técnica: Ética e Conformidade Fortalecer a conduta ética e o alinhamento aos princípios institucionais do Sebrae. | I7: Potencializar | J7: Concluir o Programa de Integridade – UC Sebrae | K7: Concluir curso Código de Ética JUSTIFICATIVA: Esta ação visa garantir que todos os colaboradores estejam em conformidade com as diretrizes éticas institucionais do Sistema Sebrae, conforme exigência do Programa de Integridade. O curso é obrigatório para todos os empregados ativos. COMO REALIZAR A AÇÃO: Acesse a Plataforma UC Sebrae. Pesquise e localize o curso "Código de Ética 2024". Reserve um tempo para leitura atenta do conteúdo. Reflita sobre a aplicação prática das diretrizes apresentadas. Conclua todas as etapas do curso. ONDE FAZER: Plataforma UC Sebrae (pesquisar por: Código de Ética 2024). Estas são apenas sugestões — a escolha deve ser alinhada com sua liderança e validada pela UGP. MATERIAL DE APOIO: Curso "Código de Ética 2024" disponível na Plataforma UC Sebrae Materiais institucionais do Programa de Integridade, se disponíveis COMO COMPROVAR: Certificado de conclusão emitido pela plataforma. | L7: Treinamento e estudo | M7: 2025-07-15 | N7: 2025-07-16 | O7: Ética, Integridade e Responsabilidade, Atitude Inovadora com Visão de Futuro, Gestão de Tempo, Planejamento, Foco e Resultados, Presença Executiva, Protagonismo, Autogestão e Tomada de Decisão, Resolução de Problemas, Tecnologia, Dados e Transformação Digital, Estratégia e Indicadores, Comunicação
A8: Joseane Rodrigues Leite | B8: joseane@to.sebrae.com.br | C8: UGP-UNIDADE DE GESTÃO DE PESSOAS | D8: Ativo | E8: Vera Lucia Teodoro Braga | F8: Macro Área: Ética, Integridade e Responsabilidade | G8: Macro Área: Ética, Integridade e Responsabilidade | H8: Competência Técnica: Ética e Conformidade Fortalecer a conduta ética e o alinhamento aos princípios institucionais do Sebrae. | I8: Potencializar | J8: Concluir o Programa de Integridade – UC Sebrae | K8: AÇÃO 1 – Realizar o curso “Programa de Integridade” na Plataforma UC Sebrae JUSTIFICATIVA: Esta ação integra o Programa de Integridade do Sistema Sebrae e é essencial para o fortalecimento da cultura organizacional baseada em ética e responsabilidade. A realização do curso é obrigatória para todos os colaboradores. COMO REALIZAR A AÇÃO: Acesse a Plataforma UC Sebrae. Localize o curso “Programa de Integridade” utilizando a barra de pesquisa. Conclua todos os módulos obrigatórios do curso. Reflita sobre os conteúdos abordados e registre suas principais percepções e aprendizados. ONDE FAZER: Plataforma UC Sebrae (pesquisar por: Programa de Integridade) Estas são apenas sugestões — a escolha deve ser alinhada com sua liderança e validada pela UGP. MATERIAL DE APOIO: Curso “Programa de Integridade” na UC Sebrae Documentos institucionais sobre o Código de Conduta, políticas e diretrizes de integridade Vídeos ou artigos complementares sobre ética organizacional e responsabilidade institucional COMO COMPROVAR: Certificado de conclusão emitido pela Plataforma UC Sebrae | L8: Treinamento e estudo | M8: 2025-11-09 | N8: 2025-10-24 | O8: Ética, Integridade e Responsabilidade, Estratégia e Indicadores, Gestão de Projetos e Processos, Gestão de Tempo, Inteligência Emocional e Autoconhecimento, Liderança e Gestão de Pessoas, Presença Executiva, Protagonismo, Autogestão e Tomada de Decisão, Gestão de Equipes, Relacionamento
A9: Rodrigo Alves dos Santos | B9: rodrigo.santos@to.sebrae.com.br | C9: Regional Serras Gerais | D9: Ativo | E9: Antonio Louça Curcino | F9: Macro Área: Ética, Integridade e Responsabilidade | G9: Macro Área: Ética, Integridade e Responsabilidade | H9: Competência Técnica: Ética e Conformidade Fortalecer a conduta ética e o alinhamento aos princípios institucionais do Sebrae. | I9: Potencializar | J9: AÇÃO: Realizar o curso Código de Ética 2024 – UC Sebrae | K9: AÇÃO OBRIGATÓRIA: Realizar o Curso "Código de Ética 2024" Justificativa: Esta ação visa garantir que todos os colaboradores estejam em conformidade com as diretrizes éticas institucionais do Sistema Sebrae, conforme exigência do Programa de Integridade. O curso é obrigatório para todos os empregados ativos e reforça a importância de atitudes responsáveis, transparentes e alinhadas aos valores organizacionais. Como realizar a ação: Acesse a Plataforma UC Sebrae. Utilize a busca para localizar o curso “Código de Ética 2024”. Conclua todas as etapas do curso com atenção aos conteúdos. Reserve um momento para leitura atenta do material e reflexão sobre sua aplicação no dia a dia profissional. Onde fazer: Plataforma UC Sebrae (pesquisar por: Código de Ética 2024). Como comprovar: Envio do certificado de conclusão emitido automaticamente pela plataforma após finalização do curso. | L9: Treinamento e estudo | M9: 2025-05-20 | N9: 2025-06-09 | O9: Ética, Integridade e Responsabilidade, Estratégia e Indicadores, Inteligência Emocional e Autoconhecimento, Planejamento, Foco e Resultados, Vendas, Negociação e Soluções Comerciais, Desenvolvimento Programa Integração
A10: Rodrigo Alves dos Santos | B10: rodrigo.santos@to.sebrae.com.br | C10: Regional Serras Gerais | D10: Ativo | E10: Antonio Louça Curcino | F10: Macro Área: Ética, Integridade e Responsabilidade | G10: Macro Área: Ética, Integridade e Responsabilidade | H10: Competência Técnica: Ética e Conformidade Fortalecer a conduta ética e o alinhamento aos princípios institucionais do Sebrae. | I10: Potencializar | J10: AÇÃO: Concluir o Programa de Integridade – UC Sebrae | K10: AÇÃO OBRIGATÓRIA: Realizar o Curso "Programa de Integridade" Justificativa: Esta ação integra o Programa de Integridade do Sistema Sebrae e é essencial para o fortalecimento de uma cultura organizacional baseada em ética, transparência e responsabilidade. A realização do curso é obrigatória para todos os colaboradores e contribui diretamente para o alinhamento de comportamentos e decisões com os princípios institucionais. Como realizar a ação: Acesse a Plataforma UC Sebrae. Utilize a busca para localizar o curso “Programa de Integridade”. Conclua todos os módulos obrigatórios disponíveis. Reflita sobre os conteúdos apresentados e registre suas principais percepções ou aprendizados. Onde fazer: Plataforma UC Sebrae (acessível pelo navegador; pesquisar pelo nome do curso). Como comprovar: Envio do certificado de conclusão emitido automaticamente pela plataforma UC Sebrae após finalização do curso. | L10: Treinamento e estudo | M10: 2025-05-20 | N10: 2025-06-09 | O10: Ética, Integridade e Responsabilidade, Estratégia e Indicadores, Inteligência Emocional e Autoconhecimento, Planejamento, Foco e Resultados, Vendas, Negociação e Soluções Comerciais, Desenvolvimento Programa Integração
A11: Ingrid Pamela Alves Amorim | B11: ingrid.amorim@to.sebrae.com.br | C11: Regional Norte | D11: Ativo | E11: Marcus Vinicius Vieira Queiroz | F11: Macro Área: Ética, Integridade e Responsabilidade | G11: Macro Área: Ética, Integridade e Responsabilidade | H11: Competência Técnica: Ética e Conformidade Fortalecer a conduta ética e o alinhamento aos princípios institucionais do Sebrae. | I11: Desenvolver | J11: AÇÃO: Concluir o Programa de Integridade – UC Sebrae | K11: JUSTIFICATIVA:** Esta ação integra o Programa de Integridade do Sistema Sebrae e é essencial para o fortalecimento da cultura organizacional baseada em ética e responsabilidade. É exigida a realização do curso por todos os colaboradores. **COMO REALIZAR A AÇÃO:** Acesse a Plataforma UC Sebrae, localize o curso 'Programa de Integridade' e conclua todos os módulos obrigatórios. Reflita sobre os conteúdos e registre suas percepções. **ONDE FAZER:** Plataforma UC Sebrae (pesquisar por: Programa de Integridade) **COMO COMPROVAR:** Certificado de conclusão emitido pela plataforma. | L11: Treinamento e estudo | M11: 2025-12-05 | N11: 2025-12-16 | O11: Ética, Integridade e Responsabilidade, Comunicação, Estratégia e Indicadores, Gestão de Projetos e Processos, Inteligência Emocional e Autoconhecimento, Liderança e Gestão de Pessoas, Planejamento, Foco e Resultados, Vendas, Negociação e Soluções Comerciais
A12: Millena Pereira Lima Rodrigues | B12: millena.rodrigues@to.sebrae.com.br | C12: Regional Portal do Jalapao | D12: Ativo | F12: Macro Área: Ética, Integridade e Responsabilidade | G12: Macro Área: Ética, Integridade e Responsabilidade | H12: Competência Técnica: Ética e Conformidade Fortalecer a conduta ética e o alinhamento aos princípios institucionais do Sebrae. | I12: Potencializar | J12: Concluir o Programa de Integridade – UC Sebrae | K12: AÇÃO: Curso “Programa de Integridade” – UC Sebrae JUSTIFICATIVA: Esta ação integra o Programa de Integridade do Sistema Sebrae e é essencial para o fortalecimento da cultura organizacional baseada em ética, responsabilidade e conformidade. A participação é obrigatória para todos os colaboradores, reforçando o compromisso com práticas transparentes, íntegras e alinhadas aos valores institucionais. COMO REALIZAR A AÇÃO: Acessar a Plataforma UC Sebrae. Pesquisar e localizar o curso “Programa de Integridade”. Concluir todos os módulos obrigatórios. Refletir sobre os conteúdos abordados e registrar suas percepções em formato livre (texto, mapa mental ou resumo reflexivo). ONDE FAZER: Plataforma UC Sebrae (https://uc.sebrae.com.br) – buscar por “Programa de Integridade”. COMO COMPROVAR: Certificado de conclusão emitido pela plataforma. | L12: Treinamento e estudo | M12: 2025-12-15 | N12: 2025-12-15 | O12: Ética, Integridade e Responsabilidade, Estratégia e Indicadores, Inteligência Emocional e Autoconhecimento, Liderança e Gestão de Pessoas, Relacionamento
A13: Rafael Camelo Ayres | B13: rafael.ayres@to.sebrae.com.br | C13: Regional Portal do Jalapao | D13: Ativo | E13: Millena Pereira Lima Rodrigues | F13: Macro Área: Ética, Integridade e Responsabilidade | G13: Macro Área: Ética, Integridade e Responsabilidade | H13: Competência Técnica: Ética e Conformidade Fortalecer a conduta ética e o alinhamento aos princípios institucionais do Sebrae. | I13: Potencializar | J13: AÇÃO: Concluir o Programa de Integridade – UC Sebrae | K13: JUSTIFICATIVA Esta ação integra o Programa de Integridade do Sistema Sebrae e é essencial para o fortalecimento da cultura organizacional baseada em ética e responsabilidade. É exigida a realização do curso por todos os colaboradores. COMO REALIZAR A AÇÃO Acesse a Plataforma UC Sebrae, localize o curso 'Programa de Integridade' e conclua todos os módulos obrigatórios. Reflita sobre os conteúdos e registre suas percepções. ONDE FAZER Plataforma UC Sebrae (pesquisar por: Programa de Integridade) COMO COMPROVAR Certificado de conclusão emitido pela plataforma. | L13: Treinamento e estudo | M13: 2025-05-20 | N13: 2025-06-16 | O13: Ética, Integridade e Responsabilidade, Protagonismo, Autogestão e Tomada de Decisão, Atendimento e Relacionamento com o Cliente, Atitude Inovadora com Visão de Futuro, Estratégia e Indicadores, Gestão de Projetos e Processos, Inteligência Emocional e Autoconhecimento, Liderança e Gestão de Pessoas, Planejamento, Foco e Resultados, Tecnologia, Dados e Transformação Digital, Comunicação
A14: Dorival Goncalves de Sousa Junior | B14: dorival.junior@to.sebrae.com.br | C14: UMC-UNIDADE DE MARKETING E COMUNICAÇÃO | D14: Ativo | E14: Nemias Gomes | F14: Macro Área: Atitude Inovadora com visão de futuro | G14: Macro Área: Atitude Inovadora com Visão de Futuro | H14: Competência Comportamental: Inovação e Criatividade Estimula a geração de ideias e soluções originais. | I14: Potencializar | J14: Desenvolver Inovação e Criatividade | K14: SEGUEM TRÊS AÇÕES: Ambas as ações são indicações para o seu desenvolvimento e que entendemos podem lhe ajudar neste desafio de aprimorar suas competências. Todas são opcionais, não há a necessidade de fazer todas, mas ao menos uma deve ser realizada para marcar como concluído o plano. Se optar por fazer mais de uma, será um grande ganho para seu desenvolvimento. Importante: Mesmo após escolher uma das opções, todas permanecerão registradas no plano, para caso deseje fazer as outras posteriormente ou para fins de acompanhamento. Não é necessário solicitar exclusão das ações não escolhidas. AÇÃO 1 – Curso Sebrae + Proposta de Melhoria Criativa Justificativa: Seu perfil mostra alto potencial criativo e comunicacional. Estruturar essa criatividade em propostas inovadoras fortalece sua atuação como agente de mudança. Como realizar a ação: Faça o curso gratuito “Inovação como Estratégia Competitiva” disponível na Universidade Sebrae. Após concluir o curso, observe um processo, entrega ou rotina da UMC que possa ser melhorado. Crie uma proposta de solução inovadora baseada nos aprendizados do curso. Registre a proposta em formato de apresentação curta ou documento descritivo. Onde fazer: Universidade Sebrae: https://sebrae.com.br Material de apoio: Curso mencionado, ferramentas de apresentação (PowerPoint, Google Slides etc.) Como comprovar: Certificado do curso e entrega da proposta de melhoria criativa documentada. AÇÃO 2 – Leitura + Inspiração Visual e Caderno de Referências Justificativa: Para quem se inspira por observação e referências visuais, essa ação permite alimentar o repertório criativo com aplicação prática. Como realizar a ação: Leia o livro “A Arte da Imperfeição” de Brené Brown (disponível na Biblioteca Sebrae)Lista de Livros. Crie um “caderno de referências” com recortes visuais, prints, ideias ou exemplos criativos que admire. Escolha uma dessas referências e aplique o conceito em uma pequena entrega do seu trabalho (por exemplo: peça gráfica, texto, layout de briefing). Escreva uma breve reflexão sobre o processo de adaptação e criação. Onde fazer: Biblioteca Sebrae e ambiente de trabalho Material de apoio: Livro citado, caderno físico ou aplicativo digital para anotações visuais. Como comprovar: Registro do caderno de referências e entrega com inspiração aplicada documentada, acompanhada da reflexão escrita. AÇÃO 3 – Participar do RD Summit 2025 Justificativa: Participar do RD Summit 2025 é uma oportunidade única de absorver tendências em marketing, inovação, tecnologia e vendas com os maiores especialistas da América Latina. A troca de experiências e a vivência do ecossistema criativo estimulam novas ideias aplicáveis ao ambiente do Sebrae, ampliando seu repertório inovador e suas conexões profissionais. Como realizar a ação: Garanta sua inscrição no evento: https://rdsummit.com.br – Data oficial: 5 a 7 de novembro de 2025, em Florianópolis-SC. Escolha ao menos cinco palestras com foco em inovação, criatividade ou marketing estratégico. Durante ou após o evento, registre os principais aprendizados em um documento-resumo ou painel visual. Aplique um dos aprendizados em uma pequena ação de melhoria ou proposta dentro do seu setor. Registre também uma autoavaliação sobre como a experiência contribuiu para sua criatividade no trabalho. Onde fazer: Evento presencial – Florianópolis, de 5 a 7 de novembro de 2025 Material de apoio: Site oficial do evento, caderno ou aplicativo de anotações, ferramentas visuais (Canva, Miro, entre outros) Como comprovar: Comprovante de participação no evento (credencial, nota fiscal ou certificado) e entrega de resumo dos aprendizados, proposta ou aplicação prática, e reflexão escrita. Sugestões práticas para o dia a dia Mantenha um mural físico ou digital com ideias criativas coletadas ao longo do mês Crie um desafio mensal de criatividade com colegas da equipe Use técnicas como “brainwriting” para gerar ideias antes das reuniões Explore referências externas semanalmente para estimular o repertório Aviso importante As três opções apresentadas são complementares. O participante poderá realizar uma ou mais delas, sendo necessário entregar ao menos uma para considerar a ação como concluída. Registros que envolvem custo estão sujeitos à avaliação da UGP para validação. Resumo final Investir em inovação e criatividade amplia sua capacidade de gerar valor e transformar ideias em soluções práticas com impacto real na organização. | L14: Treinamento e estudo | M14: 2025-11-07 | N14: 2025-12-03 | O14: Atitude Inovadora com Visão de Futuro, Ética, Integridade e Responsabilidade, Gestão de Tempo, Inteligência Emocional e Autoconhecimento, Planejamento, Foco e Resultados, Presença Executiva, Comunicação, Conhecimentos Práticos e Acadêmicos em Marketing
A15: Janaina Miranda Xavier | B15: janaina.miranda@to.sebrae.com.br | C15: Regional Metropolitana | D15: Ativo | E15: Amaggeldo Barbosa | F15: Macro Área: Atitude Inovadora com visão de futuro | G15: Macro Área: Atitude Inovadora com Visão de Futuro | H15: Competência Comportamental: Empreendedorismo Eventos técnicos e atualização temática | I15: Potencializar | J15: Participar do Empretec para Fortalecimento do Perfil Empreendedor- Curto Prazo | K15: Plano de Desenvolvimento Profissional - Empretec para Fortalecimento do Perfil Empreendedor JUSTIFICATIVA: Esta ação visa fortalecer características empreendedoras como autonomia, resiliência e iniciativa, alinhadas ao desejo manifestado por Janaina e às competências de liderança. Desenvolver características empreendedoras vai muito além de abrir um negócio. Para Janaina, esta ação será transformadora porque: • Autonomia lhe dará confiança para tomar decisões estratégicas sem depender de validações constantes • Resiliência será seu escudo para enfrentar desafios sem desistir diante das primeiras dificuldades • Iniciativa posicionará você como referência em propostas de melhorias e soluções inovadoras Estas competências são o alicerce de líderes inspiradores e profissionais que se destacam em qualquer carreira. O Empretec, metodologia reconhecida pela ONU, é a ferramenta ideal para esse desenvolvimento por trabalhar com simulações reais que ativam seu potencial empreendedor na prática. COMO REALIZAR 1. Preparação (2 semanas antes do curso) ✔ Faça o teste de perfil empreendedor gratuito do Sebrae ✔ Assista aos vídeos de ex-participantes no YouTube ✔ Liste 3 desafios atuais que gostaria de superar com o curso 2. Durante o Empretec ✔ Participe ativamente de todas as dinâmicas (elas simulam situações reais de negócios) ✔ Anote seus "insights" em um caderno dedicado ✔ Conecte-se com pelo menos 3 colegas participantes 3. Aplicação Pós-Curso ✔ Implemente um projeto piloto na sua área usando as técnicas aprendidas ✔ Compartilhe aprendizados em uma reunião de equipe ✔ Crie um "diário empreendedor" para registrar desafios e conquistas Dica Extra: Forme um grupo de estudo com colegas que também fizeram o Empretec para trocar experiências mensalmente. ONDE FAZER Sebrae EAD: Link: https://sebrae.com.br/sites/PortalSebrae/empretec RECURSOS COMPLEMENTARES Vídeo- ESSA É A MENTALIDADE DOS EMPREENDEDORES DE SUCESSO: https://youtu.be/UKShDLn-M74?si=rRhBFH8d0HhHzT1E Ebook : visão geral do livro- Vai lá e faz: como empreender na era digital e tirar ideias do papel -Tiago Mattos https://gamma.app/docs/Empreendendo-na-Era-Digital-Transformando-Ideias-em-Acao-y6zsugday0wrwjf Planilha : Mapa de Desenvolvimento Empreendedor COMO COMPROVAR: Certificado Empretec (emitido pelo Sebrae) Relatório de Aplicação : Descrição de 1 projeto implementado Resultados mensuráveis (ex.: "Redução de 20% no tempo de um processo") Depoimento em Vídeo (1-2 min): "Minha maior transformação após o Empretec foi [X] e aplico isso no trabalho através de [Y]" Modelo de Declaração: "O Empretec me proporcionou [habilidade desenvolvida], que apliquei com sucesso em [situação concreta], gerando [resultado positivo] para a equipe." | L15: Treinamento e estudo | M15: 2025-11-30 | N15: 2025-11-14 | O15: Atitude Inovadora com Visão de Futuro, Inovação, Criatividade e Visão Estratégica, Protagonismo, Autogestão e Tomada de Decisão, Comunicação, Gestão de Projetos e Processos
A16: Janaina Miranda Xavier | B16: janaina.miranda@to.sebrae.com.br | C16: Regional Metropolitana | D16: Ativo | E16: Amaggeldo Barbosa | F16: Macro Área: Atitude Inovadora com visão de futuro | G16: Macro Área: Atitude Inovadora com Visão de Futuro | H16: Competência Comportamental: Inovação Protagonismo e Autonomia | I16: Potencializar | J16: Fortalecer a Capacidade de Pensar Inovadoramente- Médio Prazo | K16: Fortalecer a Capacidade de Pensar Inovadoramente- Médio Prazo OBS - Esta ação foi transferida para o Ciclo 2-1º sem de 2026 - por causa da data inserida de 20/01/2026- Devendo ser excluida do Ciclo1 2ºsemestre de 2025 em ate 30 dias . | L16: Desafio profissional | M16: 2025-12-31 | N16: 2025-09-25 | O16: Atitude Inovadora com Visão de Futuro, Inovação, Criatividade e Visão Estratégica, Protagonismo, Autogestão e Tomada de Decisão, Comunicação, Gestão de Projetos e Processos
A17: Thamara Rodrigues de Freitas Facundes | B17: thamara.rodrigues@to.sebrae.com.br | C17: UGOC-UNIDADE DE GESTÃO ORÇ. CONTABILIDADE E FINANÇAS | D17: Ativo | E17: Andreia Rodrigues Facundes | F17: Macro Área: Atitude Inovadora com visão de futuro | G17: Macro Área: Atitude Inovadora com Visão de Futuro | H17: Competência Comportamental: Orientação à Inovação e Olhar Empreendedor Baixa pontuação em Orientação à Inovação (Avaliação G) e Olhar Empreendedor (Avaliação C), dificuldade em adaptar-se a novos contextos e propor inovações. Necessidade de desenvolver visão sistêmica e abertura a novas ideias. (Fonte: Avaliação, PDI Anterior) | I17: Potencializar | J17: Exploração de Novas Práticas e Ferramentas | K17: SEGUEM TRÊS AÇÕES: As ações abaixo são indicações para o seu desenvolvimento e que entendemos podem lhe ajudar neste desafio de aprimorar suas competências. ELAS SÃO OPCIONAIS , não há a necessidade de fazer todas, mas se optar por fazer será um grande ganho no seu desenvolvimento. Caso deseje propor outra ação diferente destas opções, converse com sua liderança e registre a opção alternativa nos comentários para que possamos incluí-la no seu plano. Não há necessidade de apagar as que já constam — qualquer uma que concluir será considerada como AÇÃO REALIZADA. AÇÃO 1 – Exploração de Novas Práticas e Ferramentas JUSTIFICATIVA: A baixa orientação à inovação (Avaliação G, PDI Anterior) pode ser estimulada pela exposição a novas abordagens e tecnologias aplicáveis ao trabalho, fomentando um olhar mais crítico e empreendedor (Avaliação C). (Fonte: Avaliação, PDI Anterior). COMO REALIZAR A AÇÃO: Dedique 1 hora por semana para pesquisar tendências, novas ferramentas ou melhores práticas na sua área de atuação (Contabilidade, Orçamento, Faturamento). Siga 2-3 fontes de informação relevantes (blogs, newsletters, perfis profissionais no LinkedIn) sobre inovação em gestão financeira/contábil. Experimente uma nova funcionalidade de uma ferramenta que já utiliza (Excel, ERP, etc.) ou uma ferramenta gratuita simples relacionada ao seu trabalho (exemplo: Trello para organizar tarefas, Canva para um relatório visualmente diferente). Anote ideias que surgirem dessas explorações, mesmo que pareçam inviáveis no momento. Compartilhe uma descoberta interessante (artigo, ferramenta, prática) com um colega ou com a equipe. Participe de um webinar ou palestra online gratuita sobre inovação ou transformação digital na área financeira/contábil. ONDE FAZER: Internet (blogs, LinkedIn, newsletters). Ferramentas de trabalho. Plataformas de webinars. Estas são apenas sugestões — a escolha deve ser alinhada com sua liderança e validada pela UGP. MATERIAL DE APOIO: Blogs de referência (exemplo: Contábeis, IOB Online). Perfis de especialistas no LinkedIn. Plataformas de webinars (Sympla, Eventbrite – buscar eventos gratuitos). Tutoriais de ferramentas (YouTube). COMO COMPROVAR: Lista de fontes de informação acompanhadas. Registro das ideias anotadas. Resumo do webinar assistido. Feedback sobre a descoberta compartilhada. AÇÃO 2 – Análise de Contexto e Proposição de Melhorias JUSTIFICATIVA: Desenvolver o Olhar Empreendedor (Avaliação C) envolve conectar o trabalho diário ao contexto maior da organização e do mercado, identificando oportunidades de melhoria ou adaptação, superando a dificuldade de adaptação a novos contextos (Avaliação G4). (Fonte: Avaliação). COMO REALIZAR A AÇÃO: Leia o planejamento estratégico do Sebrae-TO (ou da sua unidade) para entender os objetivos gerais. Converse com seu gestor para entender os principais desafios e prioridades da UGOC no momento. Analise um processo sob sua responsabilidade e pense: como ele contribui para os objetivos da unidade/Sebrae? Onde ele poderia ser mais eficiente ou gerar mais valor? Identifique um problema recorrente (mesmo pequeno) na sua rotina ou da equipe e brainstorme 2-3 possíveis causas ou soluções. Pesquise como outras organizações (ou outras unidades do Sebrae) lidam com um desafio similar ao que você enfrenta. Elabore uma pequena proposta de melhoria (1 parágrafo) baseada em sua análise e apresente ao seu gestor para discussão. ONDE FAZER: Intranet/documentos internos do Sebrae. Conversas com gestor e colegas. Pesquisa online. Reflexão sobre o próprio trabalho. Estas são apenas sugestões — a escolha deve ser alinhada com sua liderança e validada pela UGP. MATERIAL DE APOIO: Planejamento Estratégico Sebrae-TO. Relatórios da área. Ferramentas de análise simples (exemplo: Diagrama de Ishikawa para causas de problemas – buscar modelos online). Benchmarking online. COMO COMPROVAR: Resumo da análise de conexão do processo aos objetivos. Brainstorm das soluções para o problema. Proposta de melhoria elaborada. Feedback do gestor sobre a proposta. AÇÃO 3 – Curso: “Competências da Era Digital - O Mundo Digital: Inovação e Empreendedorismo Digital” JUSTIFICATIVA: Este curso é uma excelente oportunidade para aprofundar o entendimento sobre as mudanças que o mundo digital impõe ao mercado, especialmente no contexto da inovação e do empreendedorismo digital. A participação nesse curso contribui diretamente para o desenvolvimento de um olhar mais estratégico, inovador e adaptável — competências cada vez mais necessárias no cenário atual de transformação digital nas organizações. COMO REALIZAR A AÇÃO: Acesse a plataforma Universidade Sebrae. Procure pelo curso "Competências da Era Digital - O Mundo Digital: Inovação e Empreendedorismo Digital" . Realize a inscrição gratuita e acompanhe os módulos conforme sua disponibilidade. Faça anotações dos principais aprendizados. Ao final, gere e salve o certificado de conclusão. COMO COMPROVAR: Envio do certificado de conclusão ou captura de dela do curso realizado na Universidade Sebrae. Resumo Final: Seu desenvolvimento está em suas mãos! Escolha a ação que mais conversa com seus objetivos atuais e transforme aprendizado em resultado. | L17: Treinamento e estudo | M17: 2025-11-28 | N17: 2025-12-19 | O17: Atitude Inovadora com Visão de Futuro, Presença Executiva, Ética, Integridade e Responsabilidade, Protagonismo, Autogestão e Tomada de Decisão, Tecnologia, Dados e Transformação Digital
A18: Amaggeldo Barbosa | B18: amaggeldo@to.sebrae.com.br | C18: Regional Metropolitana | D18: Ativo | F18: Macro Área: Ética, Integridade e Responsabilidade | G18: Macro Área: Ética, Integridade e Responsabilidade | H18: Competência Técnica: Ética e Conformidade Fortalecer a conduta ética e o alinhamento aos princípios institucionais do Sebrae. | I18: Potencializar | J18: AÇÃO: Concluir o Programa de Integridade – UC Sebrae | K18: JUSTIFICATIVA:** Esta ação integra o Programa de Integridade do Sistema Sebrae e é essencial para o fortalecimento da cultura organizacional baseada em ética e responsabilidade. É exigida a realização do curso por todos os colaboradores. **COMO REALIZAR A AÇÃO:** Acesse a Plataforma UC Sebrae, localize o curso 'Programa de Integridade' e conclua todos os módulos obrigatórios. Reflita sobre os conteúdos e registre suas percepções. **ONDE FAZER:** Plataforma UC Sebrae (pesquisar por: Programa de Integridade) **COMO COMPROVAR:** Certificado de conclusão emitido pela plataforma. | L18: Treinamento e estudo | M18: 2025-10-31 | N18: 2025-07-10 | O18: Ética, Integridade e Responsabilidade, Atitude Inovadora com Visão de Futuro, Estratégia e Indicadores, Tecnologia, Dados e Transformação Digital, Comunicação
A19: Djales dos Santos Oliveira | B19: djales.santos@to.sebrae.com.br | C19: Regional Sul | D19: Ativo | E19: Paula dos Reis Coelho Alencar Sousa | F19: Macro Área: Ética, Integridade e Responsabilidade | G19: Macro Área: Ética, Integridade e Responsabilidade | H19: Competência Técnica: Ética e Conformidade Fortalecer a conduta ética e o alinhamento aos princípios institucionais do Sebrae. | I19: Desenvolver | J19: AÇÃO: Concluir o Programa de Integridade – UC Sebrae | K19: JUSTIFICATIVA:** Esta ação integra o Programa de Integridade do Sistema Sebrae e é essencial para o fortalecimento da cultura organizacional baseada em ética e responsabilidade. É exigida a realização do curso por todos os colaboradores. **COMO REALIZAR A AÇÃO:** Acesse a Plataforma UC Sebrae, localize o curso 'Programa de Integridade' e conclua todos os módulos obrigatórios. Reflita sobre os conteúdos e registre suas percepções. **ONDE FAZER:** Plataforma UC Sebrae (pesquisar por: Programa de Integridade) **COMO COMPROVAR:** Certificado de conclusão emitido pela plataforma. | L19: Treinamento e estudo | M19: 2025-08-31 | N19: 2025-05-30 | O19: Ética, Integridade e Responsabilidade, Atitude Inovadora com Visão de Futuro, Estratégia e Indicadores, Gestão do Conhecimento e Documentação Institucional, Inteligência Emocional e Autoconhecimento, Liderança e Gestão de Pessoas, Planejamento, Foco e Resultados, Vendas, Negociação e Soluções Comerciais
A20: Dorival Goncalves de Sousa Junior | B20: dorival.junior@to.sebrae.com.br | C20: UMC-UNIDADE DE MARKETING E COMUNICAÇÃO | D20: Ativo | E20: Nemias Gomes | F20: Macro Área: Ética, Integridade e Responsabilidade | G20: Macro Área: Ética, Integridade e Responsabilidade | H20: Competência Técnica: Ética e Conformidade Fortalecer a conduta ética e o alinhamento aos princípios institucionais do Sebrae. | I20: Potencializar | J20: Concluir o Programa de Integridade – UC Sebrae - curto prazo | K20: Programa de Integridade - Sistema Sebrae JUSTIFICATIVA: Esta ação integra o Programa de Integridade do Sistema Sebrae e é essencial para o fortalecimento da cultura organizacional baseada em ética e responsabilidade. A realização do curso é obrigatória para todos os colaboradores. COMO REALIZAR A AÇÃO: Acesse a Plataforma UC Sebrae. Localize o curso 'Programa de Integridade' . Conclua todos os módulos obrigatórios. Reflita sobre os conteúdos e registre suas percepções. ONDE FAZER: Plataforma UC Sebrae (pesquisar por: Programa de Integridade) COMO COMPROVAR: Certificado de conclusão emitido pela plataforma. | L20: Treinamento e estudo | M20: 2025-08-01 | N20: 2025-12-11 | O20: Atitude Inovadora com Visão de Futuro, Ética, Integridade e Responsabilidade, Gestão de Tempo, Inteligência Emocional e Autoconhecimento, Planejamento, Foco e Resultados, Presença Executiva, Comunicação, Conhecimentos Práticos e Acadêmicos em Marketing
A21: Carlucia Saraiva de Brito | B21: carlucia.brito@to.sebrae.com.br | C21: Regional Portal do Jalapao | D21: Ativo | E21: Millena Pereira Lima Rodrigues | F21: Macro Área: Ética, Integridade e Responsabilidade | G21: Macro Área: Ética, Integridade e Responsabilidade | H21: Competência Técnica: Ética e Conformidade Fortalecer a conduta ética e o alinhamento aos princípios institucionais do Sebrae. | I21: Potencializar | J21: Concluir o Programa de Integridade – UC Sebrae | K21: AÇÃO OBRIGATÓRIA: Concluir o curso "Programa de Integridade" Justificativa: Esta ação integra o Programa de Integridade do Sistema Sebrae e é essencial para o fortalecimento da cultura organizacional baseada em ética, transparência e responsabilidade. A realização do curso é obrigatória para todos os colaboradores, contribuindo para a consolidação de comportamentos alinhados aos princípios institucionais. Como realizar a ação: Acessar a Plataforma UC Sebrae. Pesquisar e localizar o curso "Programa de Integridade" . Concluir todos os módulos obrigatórios disponíveis. Refletir sobre os conteúdos apresentados e registrar suas percepções, se solicitado. Onde fazer: Na Plataforma UC Sebrae (buscar por: Programa de Integridade ). Como comprovar: Certificado de conclusão emitido automaticamente pela plataforma após finalização do curso. | L21: Treinamento e estudo | M21: 2025-09-30 | N21: 2025-11-23 | O21: Ética, Integridade e Responsabilidade, Atendimento e Relacionamento com o Cliente, Estratégia e Indicadores, Gestão de Projetos e Processos, Gestão do Conhecimento e Documentação Institucional, Inteligência Emocional e Autoconhecimento, Liderança e Gestão de Pessoas, Planejamento, Foco e Resultados, Vendas, Negociação e Soluções Comerciais, Comunicação
A22: Eliwania dos Santos Silva | B22: eliwania.santos@to.sebrae.com.br | C22: AUD-UNIDADE DE AUDITORIA INTERNA | D22: Ativo | F22: Macro Área: Ética, Integridade e Responsabilidade | G22: Macro Área: Ética, Integridade e Responsabilidade | H22: Competência Técnica: Ética e Conformidade Fortalecer a conduta ética e o alinhamento aos princípios institucionais do Sebrae. | I22: Potencializar | J22: Concluir o Programa de Integridade – UC Sebrae | K22: AÇÃO OBRIGATÓRIA: Conclusão do Curso “Programa de Integridade” – UC Sebrae JUSTIFICATIVA: Esta ação integra o Programa de Integridade do Sistema Sebrae e é fundamental para o fortalecimento de uma cultura organizacional baseada em ética, transparência, responsabilidade e conformidade . A realização do curso é obrigatória para todos os colaboradores , contribuindo para o alinhamento institucional e a prevenção de condutas inadequadas no ambiente de trabalho. GAP A SER DESENVOLVIDO: Ética Profissional e Conformidade Institucional COMO REALIZAR A AÇÃO: Acesse a Plataforma UC Sebrae . Pesquise pelo curso: “Programa de Integridade” . Conclua todos os módulos obrigatórios , assistindo às videoaulas e realizando as atividades avaliativas. Reflita sobre os principais conteúdos abordados (ética, governança, responsabilidade individual e coletiva). Registre brevemente suas percepções e aprendizados em documento próprio ou no espaço da plataforma. ONDE FAZER: Ambiente virtual – Plataforma UC Sebrae (acesso interno) MATERIAL DE APOIO: Curso "Programa de Integridade" (disponível na UC Sebrae) Materiais complementares disponíveis no curso Caderno de anotações ou arquivo pessoal para reflexões COMO COMPROVAR: Certificado de conclusão emitido automaticamente pela plataforma após finalização do curso. | L22: Treinamento e estudo | M22: 2025-05-31 | N22: 2025-06-09 | O22: Ética, Integridade e Responsabilidade, Gestão de Equipes, Gestão de Tempo, Planejamento, Foco e Resultados, Resolução de Problemas, Comunicação
A23: Juliana Masson Prediger | B23: juliana.prediger@to.sebrae.com.br | C23: Regional Serras Gerais | D23: Ativo | E23: Antonio Louça Curcino | F23: Macro Área: Ética, Integridade e Responsabilidade | G23: Macro Área: Ética, Integridade e Responsabilidade | H23: Competência Técnica: Ética e Conformidade Fortalecer a conduta ética e o alinhamento aos princípios institucionais do Sebrae. | I23: Potencializar | J23: Concluir o Programa de Integridade – UC Sebrae | K23: Ação: Realização do Curso “Programa de Integridade” Justificativa: Esta ação integra o Programa de Integridade do Sistema Sebrae e é essencial para o fortalecimento da cultura organizacional baseada em ética e responsabilidade. A realização do curso é obrigatória para todos os colaboradores, reforçando o compromisso com condutas éticas e alinhadas aos princípios institucionais. Como Realizar a Ação: Acesse a Plataforma UC Sebrae. Pesquise pelo curso “Programa de Integridade” . Conclua todos os módulos obrigatórios. Reflita sobre os conteúdos e registre suas percepções (opcional, mas recomendado para internalização dos aprendizados). Onde Fazer: Plataforma UC Sebrae (https://uc.sebrae.com.br) Como Comprovar: Apresente o certificado de conclusão emitido pela plataforma após finalização do curso. | L23: Treinamento e estudo | M23: 2025-05-20 | N23: 2025-07-29 | O23: Ética, Integridade e Responsabilidade, Estratégia e Indicadores, Gestão de Projetos e Processos, Gestão do Conhecimento e Documentação Institucional, Inteligência Emocional e Autoconhecimento, Liderança e Gestão de Pessoas, Vendas, Negociação e Soluções Comerciais, Comunicação
A24: Marcus Vinicius Vieira Queiroz | B24: marcus.queiroz@to.sebrae.com.br | C24: Regional Norte | D24: Ativo | F24: Macro Área: Ética, Integridade e Responsabilidade | G24: Macro Área: Ética, Integridade e Responsabilidade | H24: Competência Técnica: Ética e Conformidade Fortalecer a conduta ética e o alinhamento aos princípios institucionais do Sebrae. | I24: Potencializar | J24: AÇÃO: Concluir o Programa de Integridade – UC Sebrae | K24: 1. Justificativa da Participação Esta ação faz parte do Programa de Integridade do Sistema Sebrae e tem como objetivo promover e reforçar a cultura organizacional pautada em ética, responsabilidade e conformidade. A participação de todos os colaboradores é essencial para garantir um ambiente de trabalho íntegro, seguro e alinhado às boas práticas de governança. 2. Reflexões e Percepções sobre o Curso Durante o curso, foi possível compreender de forma clara a importância da integridade como um valor essencial dentro da organização. Entre os pontos que mais se destacaram, estão: A importância da ética nas decisões diárias : Percebi como pequenas atitudes refletem diretamente na reputação institucional. O papel da liderança no fortalecimento da cultura de integridade : A postura dos líderes influencia diretamente o comportamento das equipes. Canais de denúncia e mecanismos de controle : Conhecer esses instrumentos reforça a confiança no sistema interno e no compromisso com a transparência. Consequências do não cumprimento das normas : O curso abordou, de forma objetiva, os riscos e impactos de condutas inadequadas, tanto para a organização quanto para os indivíduos. | L24: Treinamento e estudo | M24: 2025-07-31 | N24: 2025-07-14 | O24: Ética, Integridade e Responsabilidade, Atendimento e Relacionamento com o Cliente, Gestão do Conhecimento e Documentação Institucional, Inteligência Emocional e Autoconhecimento, Liderança e Gestão de Pessoas, Planejamento, Foco e Resultados, Relacionamento, Desenvolvimento Programa Integração
A25: Monique Silva de Albuquerque | B25: monique.albuquerque@to.sebrae.com.br | C25: Regional Metropolitana | D25: Ativo | E25: Amaggeldo Barbosa | F25: Macro Área: Ética, Integridade e Responsabilidade | G25: Macro Área: Ética, Integridade e Responsabilidade | H25: Competência Técnica: Ética e Conformidade Fortalecer a conduta ética e o alinhamento aos princípios institucionais do Sebrae. | I25: Potencializar | J25: AÇÃO: Concluir o Programa de Integridade – UC Sebrae | K25: AÇÃO OBRIGATÓRIA – Curso “Programa de Integridade” JUSTIFICATIVA: Esta ação integra o Programa de Integridade do Sistema Sebrae e é essencial para fortalecer a cultura organizacional baseada em ética, responsabilidade e conformidade . A participação no curso é obrigatória para todos os colaboradores ativos , conforme diretriz institucional. COMO REALIZAR A AÇÃO: Acesse a Plataforma UC Sebrae ; Localize o curso “Programa de Integridade” (utilize a ferramenta de busca); Realize todos os módulos obrigatórios do curso com atenção ao conteúdo; Registre suas percepções e reflexões sobre os aprendizados ao final da formação. ONDE FAZER: Plataforma UC Sebrae → https://uc.sebrae.com.br Pesquisar por: Programa de Integridade COMO COMPROVAR: Certificado de conclusão emitido pela plataforma UC Sebrae. | L25: Treinamento e estudo | M25: 2025-02-26 | N25: 2025-08-21 | O25: Ética, Integridade e Responsabilidade, Vendas, Negociação e Soluções Comerciais
A26: Pedro Emilio Rodrigues Alves de Araujo | B26: pedro.araujo@to.sebrae.com.br | C26: URI-UNIDADE DE RELACIONAMENTO INSTITUCIONAL | D26: Ativo | E26: Gilzane Pereira Amaral | F26: Macro Área: Ética, Integridade e Responsabilidade | G26: Macro Área: Ética, Integridade e Responsabilidade | H26: Competência Técnica: Ética e Conformidade Fortalecer a conduta ética e o alinhamento aos princípios institucionais do Sebrae. | I26: Potencializar | J26: AÇÃO: Concluir o Programa de Integridade – UC Sebrae | K26: AÇÃO – Curso “Programa de Integridade” – Plataforma UC Sebrae JUSTIFICATIVA: Esta ação integra o Programa de Integridade do Sistema Sebrae e é essencial para o fortalecimento da cultura organizacional baseada em ética e responsabilidade. A realização do curso é exigida de todos os colaboradores. COMO REALIZAR A AÇÃO: Acesse a Plataforma UC Sebrae. Localize o curso “Programa de Integridade” . Conclua todos os módulos obrigatórios. Reflita sobre os conteúdos apresentados e registre suas percepções. ONDE FAZER: Plataforma UC Sebrae (pesquisar por: Programa de Integridade). COMO COMPROVAR: Certificado de conclusão emitido pela plataforma. | L26: Treinamento e estudo | M26: 2025-10-29 | N26: 2025-10-29 | O26: Ética, Integridade e Responsabilidade, Finanças, Orçamento e Contabilidade Pública, Atitude Inovadora com Visão de Futuro, Inteligência Emocional e Autoconhecimento, Planejamento, Foco e Resultados, Políticas Públicas e Desenvolvimento Territorial, Presença Executiva, Protagonismo, Autogestão e Tomada de Decisão, Tecnologia, Dados e Transformação Digital, Comunicação
A27: Thiago Milhomem Soares | B27: thiago.soares@to.sebrae.com.br | C27: Regional Sul | D27: Ativo | E27: Paula dos Reis Coelho Alencar Sousa | F27: Macro Área: Ética, Integridade e Responsabilidade | G27: Macro Área: Ética, Integridade e Responsabilidade | H27: Competência Técnica: Ética e Conformidade Fortalecer a conduta ética e o alinhamento aos princípios institucionais do Sebrae. | I27: Potencializar | J27: Concluir o Programa de Integridade – UC Sebrae | K27: AÇÃO: Realização do Curso “Programa de Integridade” – UC Sebrae JUSTIFICATIVA: Esta ação integra o Programa de Integridade do Sistema Sebrae e é essencial para o fortalecimento da cultura organizacional baseada em ética, responsabilidade e conformidade. A participação é obrigatória para todos os colaboradores , reforçando o compromisso institucional com práticas íntegras e transparentes. COMO REALIZAR A AÇÃO: Acessar a Plataforma UC Sebrae . Pesquisar pelo curso “Programa de Integridade” . Concluir todos os módulos obrigatórios . Refletir sobre os conteúdos e registrar suas percepções em formato livre (como um resumo, mapa mental ou breve texto reflexivo). ONDE FAZER: Plataforma UC Sebrae: https://uc.sebrae.com.br COMO COMPROVAR: Envio do certificado de conclusão emitido pela plataforma. Entrega do registro de percepção/reflexão individual sobre os aprendizados. | L27: Treinamento e estudo | M27: 2025-06-30 | N27: 2025-08-14 | O27: Ética, Integridade e Responsabilidade, Atitude Inovadora com Visão de Futuro, Gestão do Conhecimento e Documentação Institucional, Inovação, Criatividade e Visão Estratégica, Inteligência Emocional e Autoconhecimento, Liderança e Gestão de Pessoas, Planejamento, Foco e Resultados, Comunicação
A28: Emerson Eduardo Aires Nunes | B28: emerson.nunes@to.sebrae.com.br | C28: UAS-UNIDADE DE ADMINISTRAÇÃO E SUPRIMENTOS | D28: Ativo | E28: Ana Paula Alves Santos | F28: Macro Área: Ética, Integridade e Responsabilidade | G28: Macro Área: Ética, Integridade e Responsabilidade | H28: Competência Técnica: Ética e Conformidade Fortalecer a conduta ética e o alinhamento aos princípios institucionais do Sebrae. | I28: Potencializar | J28: Concluir o Programa de Integridade – UC Sebrae | K28: JUSTIFICATIVA: Esta ação integra o Programa de Integridade do Sistema Sebrae, sendo fundamental para o fortalecimento da cultura organizacional pautada na ética, transparência e responsabilidade. A participação é obrigatória para todos os colaboradores. COMO REALIZAR A AÇÃO: Acesse a Plataforma UC Sebrae , pesquise pelo curso “Programa de Integridade” e conclua todos os módulos obrigatórios. Durante o percurso, reflita sobre os conteúdos e registre suas percepções. ONDE FAZER: Plataforma UC Sebrae (buscar por: Programa de Integridade ) COMO COMPROVAR: Certificado de conclusão emitido pela Plataforma UC Sebrae. | L28: Treinamento e estudo | M28: 2025-09-30 | N28: 2025-09-25 | O28: Ética, Integridade e Responsabilidade, Competências Técnicas da Área, Gestão de Equipes, Gestão de Tempo, Resolução de Problemas
A29: Sirlene Martins da Silva | B29: sirlene.martins@to.sebrae.com.br | C29: URC - UNIDADE DE RELACIONAMENTO COM O CLIENTE | D29: Ativo | E29: Emerson Montenegro Lima | F29: Macro Área: Ética, Integridade e Responsabilidade | G29: Macro Área: Ética, Integridade e Responsabilidade | H29: Competência Técnica: Ética e Conformidade Fortalecer a conduta ética e o alinhamento aos princípios institucionais do Sebrae. | I29: Potencializar | J29: Concluir o Programa de Integridade – UC Sebrae - curto prazo | K29: JUSTIFICATIVA: Esta ação faz parte do Programa de Integridade do Sistema Sebrae e é fundamental para fortalecer a cultura organizacional pautada na ética e na responsabilidade. A realização do curso é obrigatória para todos os colaboradores. COMO REALIZAR A AÇÃO: Acesse a Plataforma UC Sebrae, pesquise pelo curso "Programa de Integridade" , conclua todos os módulos obrigatórios e reflita sobre os conteúdos apresentados. Ao final, registre suas percepções. ONDE FAZER: Plataforma UC Sebrae (pesquisar por: Programa de Integridade ) COMO COMPROVAR: Apresente o certificado de conclusão emitido pela plataforma. | L29: Treinamento e estudo | M29: 2025-09-30 | N29: 2025-10-07 | O29: Ética, Integridade e Responsabilidade, Atitude Inovadora com Visão de Futuro, Gestão de Projetos e Processos, Gestão de Tempo, Inteligência Emocional e Autoconhecimento, Planejamento, Foco e Resultados, Protagonismo, Autogestão e Tomada de Decisão
A30: Pedro Emilio Rodrigues Alves de Araujo | B30: pedro.araujo@to.sebrae.com.br | C30: URI-UNIDADE DE RELACIONAMENTO INSTITUCIONAL | D30: Ativo | E30: Gilzane Pereira Amaral | F30: Macro Área: Finanças, Orçamento e Contabilidade Pública | G30: Macro Área: Finanças, Orçamento e Contabilidade Pública | H30: Competência Técnica: Gestão de Convênios para Colaboradores do Sistema Sebrae - UCSebrae Realizar curso de gestão de convênios da Universidade Corporativa do Sistema Sebrae (UCSebrae), com objeitvo de desenvolver habilidades de gestão e colocá-las em prática por meio de projetos de políticas públicas e desenvolvimento territorial prospectados pelo Sebrae Tocantins. | I30: Desenvolver | J30: Realizar Curso Gestão de Convênios (UCSebrae) | K30: Realizar curso e obter certificado de conclusão com aproveitamento. | L30: Treinamento e estudo | M30: 2025-12-15 | N30: 2025-10-30 | O30: Ética, Integridade e Responsabilidade, Finanças, Orçamento e Contabilidade Pública, Atitude Inovadora com Visão de Futuro, Inteligência Emocional e Autoconhecimento, Planejamento, Foco e Resultados, Políticas Públicas e Desenvolvimento Territorial, Presença Executiva, Protagonismo, Autogestão e Tomada de Decisão, Tecnologia, Dados e Transformação Digital, Comunicação
A31: Adelice Thomaz Soares Novak | B31: adelice@to.sebrae.com.br | C31: UAC-UNIDADE DE ARTICULAÇÃO E COMPETITIVIDADE | D31: Ativo | E31: Bruno Martins Vieira | F31: Macro Área do Comportamento: Planejamento, Foco e Resultados | G31: Macro Área: Planejamento, Foco e Resultados | H31: Desenvolve disciplina e visão de curto, médio e longo prazo. | I31: Potencializar | J31: Plano de ação para 1 projeto estratégico com acompanhamento quinzenal | K31: AÇÃO 1 – Plano de Ação para 1 Projeto Estratégico com Acompanhamento Quinzenal JUSTIFICATIVA: Indicada com base na análise do perfil DISC, avaliação de competências e nos desafios percebidos nas funções desempenhadas por Adelice no Sebrae Tocantins. GAP A SER DESENVOLVIDO: Comportamental – Organização e Planejamento AÇÃO A SER REALIZADA: Estruturar e conduzir um projeto estratégico (em andamento ou novo), utilizando um plano de ação formal e reuniões quinzenais de acompanhamento. COMO FAZER: Escolher um projeto estratégico de relevância institucional. Elaborar um plano de ação completo com escopo, metas, cronograma e responsáveis (sugestão: modelo 5W2H + cronograma Gantt ou Kanban). Agendar encontros quinzenais com o gestor ou equipe para avaliar avanços e gargalos. Registrar decisões, lições aprendidas e ajustes nas reuniões. Redigir um relatório final com aprendizados, resultados e sugestões de melhoria para futuros projetos. Compartilhar o material com a liderança e solicitar feedback formal. ONDE FAZER: Internamente, com apoio da liderança e da UGP Eventualmente com apoio de mentor ou instrutor técnico (caso o projeto envolva capacitação) MATERIAL DE ESTUDO/APOIO: Cursos da Universidade Sebrae relacionados a planejamento e gestão de projetos Livro “Como Fazer Amigos e Influenciar Pessoas” – Dale Carnegie TED Talk: “Como falar de forma que as pessoas queiram ouvir” – Julian Treasure Planilhas e modelos: 5W2H, RACI, Kanban, cronograma Gantt COMO COMPROVAR: Registro do plano de ação com metas e cronograma Atas ou prints das reuniões quinzenais Relatório reflexivo com resultados e plano de melhoria Feedback do gestor direto com validação da entrega AÇÃO 2 (OPCIONAL) – Leitura do Livro “A Arte de Fazer Acontecer” + Prática GTD JUSTIFICATIVA: Recomendada para apoiar a clareza mental, foco e organização da rotina, conforme o modelo GTD – Getting Things Done. GAP A SER DESENVOLVIDO: Produtividade e Foco AÇÃO A SER REALIZADA: Ler os capítulos principais do livro e implantar a metodologia GTD com apoio de ferramentas práticas. COMO FAZER: Ler os capítulos 1 a 5 do livro “A Arte de Fazer Acontecer”. Criar um sistema de organização com base nos 5 passos do GTD (capturar, esclarecer, organizar, refletir e engajar). Utilizar uma planilha GTD ou aplicativo por pelo menos duas semanas. Realizar ajustes no método conforme suas necessidades. Compartilhar com o gestor a experiência, benefícios e dificuldades encontradas. ONDE FAZER: Durante a rotina de planejamento semanal No ambiente pessoal ou profissional Com apoio do gestor ou colega-mentor MATERIAL DE ESTUDO/APOIO: Livro “A Arte de Fazer Acontecer” – David Allen Planilha GTD do Sebrae Vídeo: “Como usar GTD na prática” (YouTube – versão resumida com exemplo real) COMO COMPROVAR: Print da planilha, ferramenta ou método GTD aplicado Relato escrito sobre a experiência e mudanças percebidas Validação do gestor direto | L31: Desafio profissional | M31: 2025-08-15 | N31: 2025-08-14 | O31: Comunicação, Ética, Integridade e Responsabilidade, Liderança e Gestão de Pessoas, Relacionamento, Planejamento, Foco e Resultados, Gestão de Equipes, Tecnologia, Dados e Transformação Digital
A32: Adelice Thomaz Soares Novak | B32: adelice@to.sebrae.com.br | C32: UAC-UNIDADE DE ARTICULAÇÃO E COMPETITIVIDADE | D32: Ativo | E32: Bruno Martins Vieira | F32: Macro Área do Comportamento: Liderança e Gestão de Pessoas | G32: Macro Área: Liderança e Gestão de Pessoas | H32: Melhora a assertividade e análise na escolha de caminhos. | I32: Potencializar | J32: Aplicação de análise SWOT em projeto real com apresentação para liderança | K32: SEGUEM TRÊS AÇÕES: As três as ações são indicações para o seu desenvolvimento e que entendemos podem lhe ajudar neste desafio de aprimorar suas competências. ELAS SÃO OPCIONAIS , não há a necessidade de fazer as três, mas se optar por fazer será um grande ganho no seu desenvolvimento. Caso deseje propor outra ação diferente destas opções, converse com sua liderança e registre a opção alternativa nos comentários para que possamos incluí-la no seu plano. Não há necessidade de apagar as que já constam — qualquer uma que concluir será considerada como AÇÃO REALIZADA. AÇÃO 1 – Aplicação de Análise SWOT em Projeto Real com Apresentação para Liderança JUSTIFICATIVA: Indicada com base na análise do perfil DISC, avaliação de competências e desafios percebidos nas funções desempenhadas por Adelice no Sebrae Tocantins. COMO REALIZAR A AÇÃO: Escolher um projeto institucional ou de equipe que esteja em fase de planejamento ou avaliação. Estruturar a análise SWOT com base em dados, percepções de equipe e contexto externo. Validar o preenchimento com pares e/ou técnico de referência. Apresentar a análise SWOT em reunião com a liderança, com propostas baseadas nas oportunidades e ameaças identificadas. Elaborar um relatório reflexivo com aprendizados, desafios enfrentados e aplicações práticas. ONDE FAZER: Internamente no Sebrae TO Com apoio da UGP, liderança direta ou técnico especialista Estas são apenas sugestões — a escolha deve ser alinhada com sua liderança. MATERIAL DE APOIO: Pesquise por um curso com o objetivo de utilizar ferramentas de planejamento estratégico, preferencialmente na Universidade Sebrae e Degreed Artigo técnico Sebrae sobre ferramentas de planejamento Livro “Comunicação Não-Violenta” – Marshall Rosenberg TED Talk: “Como falar de forma que as pessoas queiram ouvir” – Julian Treasure COMO COMPROVAR: Print ou ata da reunião de apresentação Relatório SWOT aplicado Relatório reflexivo sobre a aplicação e utilidade prática Feedback formal da liderança Validação obrigatória do gestor direto AÇÃO 2 (OPCIONAL) – Leitura de Caso Harvard sobre Decisão Empresarial + Debate em Grupo JUSTIFICATIVA: Estimula o pensamento estratégico com base em contextos reais, fortalece argumentação e visão sistêmica. COMO REALIZAR A AÇÃO: Escolher um caso relevante, como “Mudança Estratégica Radical” (HBR). Dividir a leitura entre os participantes. Agendar um encontro presencial ou online para debate guiado. Identificar visões divergentes e consensos. Produzir uma síntese com os aprendizados extraídos e sua aplicação ao contexto do Sebrae. ONDE FAZER: Reunião interna com apoio da liderança Ambiente online (Teams ou Zoom) Durante horário destinado a formação e desenvolvimento Estas são apenas sugestões — a escolha deve ser alinhada com sua liderança. MATERIAL DE APOIO: Caso “Mudança Estratégica Radical” – HBR Artigo “Como tomar decisões difíceis” – HBR TED “A mente de um estrategista” – Martin Reeves COMO COMPROVAR: Print da leitura realizada Relatório-síntese com aprendizados do grupo Validação ou feedback da liderança ou facilitador AÇÃO 3 – Realizar trilha de capacitação sobre FOCO com aplicação prática da gestão do tempo e produtividade JUSTIFICATIVA: Indicada com base em desafios identificados relacionados à gestão do tempo, priorização de tarefas e aumento de produtividade, comuns em diversos perfis comportamentais e contextos de atuação no Sebrae Tocantins. Esta ação contribui para fortalecer a disciplina, clareza de metas e a execução com foco em resultados — habilidades essenciais para ambientes dinâmicos, projetos múltiplos e entregas estratégicas. COMO REALIZAR A AÇÃO: Realizar a trilha de capacitação sobre “Foco e Produtividade” disponível na Universidade Sebrae. Durante a capacitação, aplicar semanalmente as ferramentas e práticas sugeridas, documentando o processo. Etapas sugeridas: Acesse a trilha pela Universidade Sebrae, com login institucional. Realize todos os módulos propostos da trilha. Escolha uma semana do mês para aplicar integralmente as técnicas aprendidas, como a Matriz de Eisenhower, timeboxing ou planejamento semanal visual. Organize suas principais tarefas da semana em uma matriz de priorização, aplicando os critérios da trilha. Ao final da semana, elabore um mini-relato com: Estratégias aplicadas. Dificuldades encontradas. Benefícios percebidos. Intenções de continuidade. ONDE FAZER: Plataforma Universidade Sebrae (UC Sebrae) Aplicação prática nas rotinas reais de trabalho no Sebrae TO. COMO COMPROVAR: Print da conclusão; Relato escrito com evidências da aplicação prática (modelo livre com até 2 páginas). Print ou foto da matriz de priorização semanal utilizada. Validação obrigatória do gestor direto. | L32: Desafio profissional | M32: 2025-09-15 | N32: 2025-07-28 | O32: Comunicação, Ética, Integridade e Responsabilidade, Liderança e Gestão de Pessoas, Relacionamento, Planejamento, Foco e Resultados, Gestão de Equipes, Tecnologia, Dados e Transformação Digital
A33: Janaina Miranda Xavier | B33: janaina.miranda@to.sebrae.com.br | C33: Regional Metropolitana | D33: Ativo | E33: Amaggeldo Barbosa | F33: Macro Área: Inovação, Criatividade e Visão Estratégica | G33: Macro Área: Inovação, Criatividade e Visão Estratégica | H33: Competência Comportamental: Visão Estratégica Segurança do trabalho e bem-estar | I33: Potencializar | J33: Desenvolver Olhar Empreendedor e Inovador- Medio prazo | K33: Plano de Desenvolvimento Profissional: Olhar Empreendedor e Inovador JUSTIFICATIVA : Esta ação visa potencializar o pensamento estratégico e o olhar empreendedor para identificar novas oportunidades e soluções inovadoras, conforme necessidade apontada na avaliação de desempenho. No mundo atual, onde a inovação é um dos principais motores do sucesso, desenvolver um olhar empreendedor é essencial para qualquer líder. Essa habilidade não apenas impulsiona a carreira, mas também inspira equipes a abraçar a mudança e a criatividade. Ter um olhar empreendedor significa identificar oportunidades, enfrentar desafios com uma mentalidade positiva e fomentar um ambiente de inovação contínua. Ao investir no desenvolvimento dessas competências, você se torna um agente de transformação, capaz de moldar o futuro de sua organização e de sua carreira. COMO REALIZAR: Participar de Workshops e Seminários: Busque eventos locais ou virtuais que abordem empreendedorismo e inovação. Sugestão: Organize um grupo de discussão ou um clube do livro sobre temas de empreendedorismo. Cursos Online: Inscreva-se em cursos que ofereçam certificação em empreendedorismo e inovação. Sugestão: Crie um cronograma de estudos e compartilhe seu progresso com uma rede de apoio. Mentoria: Procure mentores que tenham experiências relevantes em empreendedorismo. Sugestão: Participe de eventos de networking para conectar-se com potenciais mentores. Estudo de Casos: Analise casos de sucesso e fracasso de empreendedores. Sugestão: Discuta suas conclusões com colegas para expandir a visão sobre diferentes abordagens. ONDE FAZER : Faculdade SEBRAE: Inovação e Novos Modelos de Negócio https://faculdadesebrae.com.br/cursos-livres/inovacao-e-novos-modelos-de-negocio/ PUCRS online: Empreendedorismo e Novos Modelos de Negócios https://online.pucrs.br/formacao-gratuita/empreendedorismo-e-novos-modelos-de-negocios Fundação Bradesco: Empreendedorismo e Inovação https://www.ev.org.br/cursos/empreendedorismo-e-inovacao SUGESTÕES EXTRAS : TED Talks: O Poder da Inovação | Marcus Linhares https://youtu.be/BsDifn_0AmE?si=91Fb_iQske_hbcjs Biblioteca Sebrae- https://bis.sebrae.com.br/bis/ COMO COMPROVAR : Declaração: Solicite certificados dos cursos realizados. Crie um portfólio onde você documenta sua jornada de aprendizado e suas experiências práticas. Vídeos: Grave e compartilhe vídeos curtos onde você discute o que aprendeu e como aplicou essas lições em sua vida profissional. ________________________________________ MENSAGEM INSPIRADORA FINAL “A inovação distingue um líder de um seguidor.” - Steve Jobs. Lembre-se, cada passo que você dá em direção ao desenvolvimento de um olhar empreendedor não apenas transforma sua carreira, mas também inspira todos ao seu redor a sonhar e realizar. Vá em frente, desafie-se e abrace a jornada do empreendedorismo | L33: Treinamento e estudo | M33: 2025-12-20 | N33: 2025-11-14 | O33: Atitude Inovadora com Visão de Futuro, Inovação, Criatividade e Visão Estratégica, Protagonismo, Autogestão e Tomada de Decisão, Comunicação, Gestão de Projetos e Processos
A34: Dorival Goncalves de Sousa Junior | B34: dorival.junior@to.sebrae.com.br | C34: UMC-UNIDADE DE MARKETING E COMUNICAÇÃO | D34: Ativo | E34: Nemias Gomes | F34: Macro Área: Inteligência Emocional e Autoconhecimento | G34: Macro Área: Inteligência Emocional e Autoconhecimento | H34: Competência Comportamental: Inteligência Emocional e Desenvolvimento Pessoal Promove o equilíbrio emocional e o autoconhecimento. | I34: Potencializar | J34: Vídeo TED + Roda de Reflexão com Diário de Emoções - curto prazo | K34: SEGUEM DUAS AÇÕES: Ambas as ações são indicações para o seu desenvolvimento e que entendemos podem lhe ajudar neste desafio de aprimorar suas competências. ELAS SÃO OPCIONAIS, não há a necessidade de fazer as duas, mas se optar por fazer será um grande ganho no seu desenvolvimento. Caso deseje propor outra ação diferente destas duas opções, converse com sua liderança e registre a opção alternativa nos comentários para que possamos incluí-la no seu plano. Não há a necessidade de apagar as que já constam, pois a escolha de qual realizar será tua e qualquer uma que concluir será considerada como AÇÃO REALIZADA. AÇÃO 1: Vídeo TED + Roda de Reflexão com Diário de Emoções JUSTIFICATIVA: Foi identificado no DISC que seu perfil altamente influente valoriza reconhecimento e relações harmoniosas, o que pode gerar frustrações quando esse ambiente não se concretiza. Desenvolver inteligência emocional ajudará você a lidar melhor com críticas e pressão. COMO REALIZAR A AÇÃO: Assista ao TED Talk O Poder da Vulnerabilidade , de Brené Brown (disponível no YouTube). Durante sete dias, mantenha um diário de emoções, registrando três momentos por dia, com nomeação dos sentimentos e identificação de gatilhos. Escolha um colega de confiança e compartilhe um aprendizado por semana, baseado nas anotações do diário. Elabore um resumo com os principais padrões emocionais identificados ao longo da prática. ONDE FAZER: TED.com, YouTube e local de trabalho. COMO COMPROVAR: Apresentar o diário de emoções preenchido e o resumo reflexivo final. AÇÃO 2: Leitura Guiada + Podcast com Aplicação Semanal JUSTIFICATIVA: Considerando seu estilo comunicativo e espontâneo, um formato mais leve, reflexivo e acessível pode gerar maior engajamento e continuidade no desenvolvimento. COMO REALIZAR A AÇÃO: Leia o livro Inteligência Emocional , de Daniel Goleman (disponível na biblioteca Sebrae). Escolha três capítulos e elabore um resumo com suas percepções e aprendizados. Ouça o episódio “Liderança e Desenvolvimento” (disponível no Spotify). Durante três semanas, aplique uma técnica de controle emocional em situações reais no trabalho. Registre os impactos percebidos ao longo da prática. ONDE FAZER: Biblioteca Sebrae, Spotify e ambiente de trabalho. COMO COMPROVAR: Enviar o resumo dos capítulos do livro e um relato escrito sobre a aplicação prática das técnicas. | L34: Treinamento e estudo | M34: 2025-12-12 | N34: 2025-12-11 | O34: Atitude Inovadora com Visão de Futuro, Ética, Integridade e Responsabilidade, Gestão de Tempo, Inteligência Emocional e Autoconhecimento, Planejamento, Foco e Resultados, Presença Executiva, Comunicação, Conhecimentos Práticos e Acadêmicos em Marketing
A35: Cynthia Nunes Alves Franca | B35: cynthia.franca@to.sebrae.com.br | C35: URI-UNIDADE DE RELACIONAMENTO INSTITUCIONAL | D35: Ativo | E35: Gilzane Pereira Amaral | F35: Macro Área: Planejamento, Foco e Resultados | G35: Macro Área: Planejamento, Foco e Resultados | H35: Competência Comportamental: Perceptividade - Organização Pessoal Realização do Curso: Organização Pessoal na plataforma Fundação Bradesco LInk: https://www.ev.org.br/cursos/organizacao-pessoal. Com Duração de 10 horas. | I35: Potencializar | J35: Realização do Curso: Organização Pessoal | K35: Realização do Curso: Organização Pessoal na plataforma Fundação Bradesco LInk: https://www.ev.org.br/cursos/organizacao-pessoal. Com Duração de 10 horas. *Realizar curso na plataforma indicada *Anexar Certificado nos comentários | L35: Treinamento e estudo | M35: 2025-10-01 | N35: 2025-10-30 | O35: Planejamento, Foco e Resultados, Gestão do Conhecimento e Documentação Institucional, Inteligência Emocional e Autoconhecimento, Protagonismo, Autogestão e Tomada de Decisão, Comunicação, Desenvolvimento Programa Integração
A36: Dorival Goncalves de Sousa Junior | B36: dorival.junior@to.sebrae.com.br | C36: UMC-UNIDADE DE MARKETING E COMUNICAÇÃO | D36: Ativo | E36: Nemias Gomes | F36: Macro Área: Planejamento, Foco e Resultados | G36: Macro Área: Planejamento, Foco e Resultados | H36: Competência Comportamental: Foco em Resultados Garante direcionamento e entrega com eficiência. | I36: Potencializar | J36: : Simulação de Meta SMART com Aplicação Real | K36: SEGUEM DUAS AÇÕES: Ambas as ações são indicações para o seu desenvolvimento e que entendemos podem lhe ajudar neste desafio de aprimorar suas competências. ELAS SÃO OPCIONAIS, não há a necessidade de fazer as duas, mas se optar por fazer será um grande ganho no seu desenvolvimento. Caso deseje propor outra ação diferente destas duas opções, converse com sua liderança e registre a opção alternativa nos comentários para que possamos incluí-la no seu plano. Não há necessidade de apagar as que já constam — qualquer uma que concluir será considerada como AÇÃO REALIZADA. AÇÃO 1 – Simulação de Meta SMART com Aplicação Real JUSTIFICATIVA: Há indícios no DISC de que sua energia está mais voltada para o relacionamento e criatividade, o que pode comprometer a entrega focada em metas objetivas. Aprender a definir e executar metas com método trará mais equilíbrio entre inovação e resultado. COMO REALIZAR A AÇÃO: Escolha um objetivo simples relacionado à sua rotina (ex: otimizar tempo de produção de conteúdo). Construa uma meta SMART (Específica, Mensurável, Atingível, Relevante e Temporal). Liste de 3 a 5 ações para alcançar a meta em até 30 dias. Registre semanalmente os avanços e dificuldades. Ao final, elabore uma análise dos resultados obtidos. ONDE FAZER: Local de trabalho e planilha pessoal. Estas são apenas sugestões — a escolha deve ser alinhada com sua liderança e validada pela UGP. MATERIAL DE APOIO: Modelo de metas SMART (disponível em diversos sites de gestão), planilhas de acompanhamento (Excel, Google Sheets). COMO COMPROVAR: Documento contendo a meta SMART, plano de ação detalhado e autoavaliação final dos resultados. AÇÃO 2 – Leitura Aplicada + Registro de Indicadores Simples JUSTIFICATIVA: Uma abordagem leve e autodirigida pode funcionar bem para seu perfil. Trabalhar com indicadores práticos ajudará a criar foco em entregas concretas. COMO REALIZAR A AÇÃO: Leia o artigo “Como usar indicadores de desempenho no dia a dia” (Blog Runrun.it ou Resultados Digitais). Escolha um pequeno projeto que esteja desenvolvendo. Crie 2 ou 3 indicadores simples (ex: tempo de resposta, volume de entregas semanais, índice de retrabalho). Monitore os resultados por 15 dias e compare com o esperado. Registre em uma planilha os aprendizados e ajustes futuros. ONDE FAZER: Blog gratuito e planilha local. Estas são apenas sugestões — a escolha deve ser alinhada com sua liderança e validada pela UGP. MATERIAL DE APOIO: Artigos do Blog Runrun.it ou Resultados Digitais, planilhas para controle de indicadores. COMO COMPROVAR: Print da planilha com indicadores preenchidos e descrição dos resultados obtidos. | L36: Treinamento e estudo | M36: 2025-11-27 | N36: 2025-12-11 | O36: Atitude Inovadora com Visão de Futuro, Ética, Integridade e Responsabilidade, Gestão de Tempo, Inteligência Emocional e Autoconhecimento, Planejamento, Foco e Resultados, Presença Executiva, Comunicação, Conhecimentos Práticos e Acadêmicos em Marketing
